Workbook

Sheet 本部部署（重複）
A1: 異動先事業本部 | B1: 異動先部 | C1: 異動先G
A2: CS本部 | B2: CS部 | C2: 運用G
A3: CS本部 | B3: CS本部(部なし) | C3: CS本部(Gなし)
A4: CS本部 | B4: CS部 | C4: CREG
A5: CS本部 | B5: CS部 | C5: CREG
A6: CS本部 | B6: CS本部(部なし) | C6: CS本部(Gなし)
A7: CS本部 | B7: CS部 | C7: 運用G
A8: CS本部 | B8: CS部 | C8: CREG
A9: CS本部 | B9: CX部 | C9: CX部(Gなし)
A10: CS本部 | B10: CX部 | C10: EnhancementG
A11: CS本部 | B11: CS部 | C11: 運用G
A12: CS本部 | B12: CX部 | C12: EnhancementG
... A4031: 内部監査室本部格 | B4031: 内部監査室 | C4031: 内部監査G
A4033: ここからは全角に戻した値
A4034: ＣＳ本部 | B4034: ＣＳ部 | C4034: 運用Ｇ
A4035: ＣＳ本部 | B4035: ＣＳ本部（部なし） | C4035: ＣＳ本部（Ｇなし）
A4036: ＣＳ本部 | B4036: ＣＳ部 | C4036: ＣＲＥＧ
A4037: ＣＳ本部 | B4037: ＣＳ部 | C4037: ＣＲＥＧ
A4038: ＣＳ本部 | B4038: ＣＳ本部（部なし） | C4038: ＣＳ本部（Ｇなし）
A4039: ＣＳ本部 | B4039: ＣＳ部 | C4039: 運用Ｇ
A4040: ＣＳ本部 | B4040: ＣＳ部 | C4040: ＣＲＥＧ
A4041: ＣＳ本部 | B4041: ＣＸ部 | C4041: ＣＸ部（Ｇなし）
A4042: ＣＳ本部 | B4042: ＣＸ部 | C4042: ＥｎｈａｎｃｅｍｅｎｔＧ
A4043: ＣＳ本部 | B4043: ＣＳ部 | C4043: 運用Ｇ
A4044: ＣＳ本部 | B4044: ＣＸ部 | C4044: ＥｎｈａｎｃｅｍｅｎｔＧ
A4045: ＣＳ本部 | B4045: ＣＸ部 | C4045: ＥｎｈａｎｃｅｍｅｎｔＧ
... A8063: 内部監査室本部格 | B8063: 内部監査室 | C8063: 内部監査Ｇ

Sheet 概要
A1: 集計
A2: 項目（div） | B2: 総数 | C2: 合致 | D2: 0file | E2: 仮説 | F2: 不明
A3: div | B3: 497 | C3: 95 | D3: 278 | E3: 100 | F3: 24
A4: 項目（project） | B4: 総数 | C4: 在籍 | D4: 退職（部署判明） | E4: 退職（部署不明） | F4: 管理者不明
A5: Project | B5: 265 | C5: 197 | D5: 33 | E5: 35 | F5: 9
A6: 総 | B6: =SUM(B3:B5) -> 762
A8: divフィルター詳細
A9: フィルタ名 | B9: 内容 | E9: 今後の動き
A10: 合致 | B10: 0fileを除いた、あたりがついているフォルダ | E10: 佑さんの部署遍歴から、仮説の箇所などを判明していく
A11: 0file | B11: ファイル数0で利用していないフォルダ | E11: 各フォルダ詳細から、ホットフォルダとコールドフォルダを分けて分別していく
A12: 仮説 | B12: 0fileを除いた、仮説で記載した項目の内容 仮説も立てられないものは（不明）でカウント ※E列 | E12: 本部と部室を繋げて本当に相違ないか確認予定
A13: 不明 | B13: 0fileを除いた、仮説も立てられないもの | E13: 仮説での本部長/部室長が不明な箇所にもあたりを付けて確認予定
E14: 仮説→あたりを付けられないものは、不明にする
A16: Projectフィルター詳細
A17: フィルタ名 | B17: 内容 | E17: 今後の動き
A18: 在籍 | B18: 管理者が判明している | E18: 各フォルダ詳細から、ホットフォルダとコールドフォルダを分けて分別していく
A19: 退職（部署判明） | B19: 管理者がすでに退職しているが、部署は判明している
A20: 退職（部署不明） | B20: 管理者がすでに退職しており、部署も不明
A21: 管理者不明 | B21: フォルダ管理者が不明のためこれ以上どうしようもない
A23: 本部長、部室長の今あたっていない人を再度あてる 半角カタカナを書き直して
A24: 1列でステータスをわかりやすく、フィルターで単発で表示できるように集計は確定するまで各自に任す、だれが見ても一発でわかるステータスなどにする

Sheet データ仕分け残対応
A1: 項番 | B1: フォルダ枠 | C1: 担当者 | D1: 概要 | E1: ステータス
A2: 1 | B2: div | C2: 戸谷 | D2: 0fileの管理者を特定。 不明なものは不明に変更 | E2: 済
A3: 2 | B3: project | C3: 戸谷 | D3: 最終更新日3年までのものを出して、 AWSとGoogleドライブに分ける | E3: 済
A4: 3 | B4: project | C4: 戸谷 | D4: file数をフォルダごとにあてる →PF側？の作業待ち | E4: 作業待ち
A5: 4 | B5: project | C5: PF | D5: projectフォルダのファイル数を出す
A6: 5 | B6: div | C6: 戸谷 | D6: 管理者不明のところを少し深ぼる | E6: 済
A7: 6 | B7: project | C7: 那須さん | D7: 管理者が不明な箇所の確認先の特定
A8: 7 | B8: project | C8: 戸谷 | D8: 管理者ごとにフォルダの行を追加して、全員退職なら退職などにフラグを変更する 関数を使っていない箇所があるので、もう一度さらう ●関数 ・在籍：=XLOOKUP(G5,'従業員情報'!$A:$A,'従業員情報'!$N:$N,"×") ・退職：=XLOOKUP(G5,'退職者'!$C:$C,'退職者'!$B:$B,"×")&XLOOKUP(G18,'退職者'!$C:$C,'退職者'!$A:$A,"×") ●ステータス ・在籍にヒット＝在籍 ・退職にヒット＝退職 ・退職でもヒットしない＝退職（部署不明） ・管理者の記載のない箇所＝管理者不明（那須さんに個別確認を依頼） | E8: 済
A9: 8 | B9: project | C9: 戸谷 | D9: 列ごとの項目をdivに揃える | E9: 済
A13: 質問
A14: 項番 | B14: フォルダ枠 | D14: 概要 | E14: ステータス | F14: 回答 | G14: 備考
A15: 1 | B15: div | D15: 0fileでも無い最終更新日が無いフォルダを出していただきたい | E15: 済 | F15: データ出力に時間かかるため、一旦はたかん以外はAWSを移行先に指定 守田）11/6時点で一応佐藤さんにデータ出力依頼をしてます。
A16: 2 | B16: project | D16: 容量と最終更新日のシートに記載のないものがあるので出してほしい。 記載のないものは0file or 0容量であれば教えていただきたい | E16: 対応中 | F16: 守田）容量はすべて埋めました。2件だけ#N/Aが存在しますが移行不要でOKです。 最終更新日はないものがちらほらあるので佐藤さんに依頼中です。
A17: 3 | B17: project | D17: projectフォルダのファイル数を算出していただける流れだったと思いますが、そちらは不要になった状況でしょうか？ | E17: 対応中 | F17: 守田）11/6時点で出力中なので少々お待ちを

Sheet （旧）div
A1: div topフォルダ | D1: 本部・本部 | E1: 部室・部室 | F1: 本部・部室 | G1: 部室・本部 | H1: 仮説
A2: スタジオフンザ | C2: 仮説 | E2: 廃止 | G2: × | H2: × | I2: 廃止 | K2: {=XLOOKUP($B2,'部署遍歴'!C:C,'部署遍歴'!D:D,"×")} -> ×
A3: デジタルエンターテインメント事業本部 | C3: 仮説 | E3: 各事業部 (モンスト事業部など) / 開発本部 | G3: × | H3: × | I3: 各事業部 (モンスト事業部など) / 開発本部 | J3: 事業本部制の廃止に伴い、事業や機能ごとに再編されました。 | K3: {=XLOOKUP($B3,'部署遍歴'!C:C,'部署遍歴'!D:D,"×")} -> ×
A4: ミクシィマーケティング | C4: 仮説 | E4: デザイン本部 / 各事業部 | G4: × | H4: × | I4: デザイン本部 / 各事業部 | J4: 全社機能は「デザイン本部」へ、プロダクトごとの機能は各事業部へ移管されたと推測されます。 | K4: {=XLOOKUP($B4,'部署遍歴'!C:C,'部署遍歴'!D:D,"×")} -> ×
A5: 渉外部 | E5: 渉外部本部格 | G5: × | H5: × | K5: {=XLOOKUP($B5,'部署遍歴'!C:C,'部署遍歴'!D:D,"×")} -> ×
A6: 事業デザイン本部 | C6: 仮説 | E6: デザイン本部 | G6: × | H6: × | I6: デザイン本部 | J6: 名称変更、または機能統合された可能性が高いです。 | K6: {=XLOOKUP($B6,'部署遍歴'!C:C,'部署遍歴'!D:D,"×")} -> ×
A7: コーポレートサポート本部 | C7: 仮説 | E7: はたらく環境推進本部 | G7: 平山 英輝 | H7: × | I7: はたらく環境推進本部 | J7: 総務や情報システムなどの機能が引き継がれました。 | K7: {=XLOOKUP($B7,'部署遍歴'!C:C,'部署遍歴'!D:D,"×")} -> ×
A8: 人事部 | C8: 仮説 | E8: 人事本部 | G8: 杉村 元規 | H8: × | I8: 人事本部 | J8: 名称変更、または機能強化による再編です。 | K8: {=XLOOKUP($B8,'部署遍歴'!C:C,'部署遍歴'!D:D,"×")} -> ×
A9: XFLAG ENTERTAINMENT | C9: 仮説 | E9: 開発本部 / デザイン本部 / 各事業部 | G9: × | H9: × | I9: 開発本部 / デザイン本部 / 各事業部 | J9: XFLAGブランドのMIXI本体への統合に伴い、機能が分散・再編されました。 | K9: {=XLOOKUP($B9,'部署遍歴'!C:C,'部署遍歴'!D:D,"×")} -> ×
A10: 会長室 | C10: 仮説 | E10: 社長室 | G10: × | H10: × | I10: 社長室 | J10: 名称変更、または機能統合された可能性が高いです。 | K10: {=XLOOKUP($B10,'部署遍歴'!C:C,'部署遍歴'!D:D,"×")} -> ×
A11: 人事部付 | C11: 仮説 | E11: 特定の役職のため、部署としての再編先はなし | G11: × | H11: × | I11: 特定の役職のため、部署としての再編先はなし | J11: 部署名ではなく、特定の役職としての位置づけのため、現存する部署への再編はありません。 | K11: {=XLOOKUP($B11,'部署遍歴'!C:C,'部署遍歴'!D:D,"×")} -> ×
A12: メディアコンテンツ事業本部 | C12: 仮説 | E12: 廃止（一部機能は他部署へ移管） | G12: × | H12: × | I12: 廃止（一部機能は他部署へ移管） | J12: 直接の後継部署は見当たらず、個別の事業は終了または他部署へ移管されたようです。 | K12: {=XLOOKUP($B12,'部署遍歴'!C:C,'部署遍歴'!D:D,"×")} -> ×
A13: 経営企画本部 | C13: 仮説 | E13: 経営推進本部 → コーポレートデベロップメント本部 など | G13: × | H13: × | I13: 経営推進本部 → コーポレートデベロップメント本部 など | J13: 「経営推進本部」を経て、機能が分散・再編されたと推測されます。 | K13: {=XLOOKUP($B13,'部署遍歴'!C:C,'部署遍歴'!D:D,"×")} -> ×
A14: XFLAG ARTS | C14: 仮説 | E14: 開発本部 / デザイン本部 / 各事業部 | G14: × | H14: × | I14: 開発本部 / デザイン本部 / 各事業部 | J14: XFLAGブランドのMIXI本体への統合に伴い、機能が分散・再編されました。 | K14: {=XLOOKUP($B14,'部署遍歴'!C:C,'部署遍歴'!D:D,"×")} -> ×
A15: スマートヘルス | C15: 仮説 | E15: 廃止（事業終了または他部署へ移管） | G15: × | H15: × | I15: 廃止（事業終了または他部署へ移管） | J15: 現在の組織図には見当たらず、事業としては終了または移管されたようです。 | K15: {=XLOOKUP($B15,'部署遍歴'!C:C,'部署遍歴'!D:D,"×")} -> ×
A16: コンプライアンス本部 | E16: ｺﾝﾌﾟﾗｲｱﾝｽ本部 | G16: × | H16: × | K16: {=XLOOKUP($B16,'部署遍歴'!C:C,'部署遍歴'!D:D,"×")} -> ×
A17: ヴァンテージスタジオ | C17: 仮説 | E17: 廃止 | G17: × | H17: × | I17: 廃止 | J17: 現在の組織図には見当たりません。 | K17: {=XLOOKUP($B17,'部署遍歴'!C:C,'部署遍歴'!D:D,"×")} -> ×
A18: 内部監査室 | E18: 内部監査室本部格 | G18: × | H18: × | K18: {=XLOOKUP($B18,'部署遍歴'!C:C,'部署遍歴'!D:D,"×")} -> ×
A19: チケットキャンプ事業部 | C19: 仮説 | E19: 廃止（事業終了） | G19: × | H19: × | I19: 廃止（事業終了） | J19: 事業が終了しました。 | K19: {=XLOOKUP($B19,'部署遍歴'!C:C,'部署遍歴'!D:D,"×")} -> ×
A20: オレンジスタジオ | C20: 仮説 | E20: MIXI M事業部 オレンジグループ | G20: × | H20: × | I20: MIXI M事業部 オレンジグループ | J20: 「MIXI M事業部」内のグループとして存続している可能性があります。 | K20: {=XLOOKUP($B20,'部署遍歴'!C:C,'部署遍歴'!D:D,"×")} -> ×
A21: ゲーム事業本部 | C21: 仮説 | E21: 各事業部 (モンスト事業部など) | G21: × | H21: × | I21: 各事業部 (モンスト事業部など) | J21: 事業本部制の廃止に伴い、事業ごとに再編されました。 | K21: {=XLOOKUP($B21,'部署遍歴'!C:C,'部署遍歴'!D:D,"×")} -> ×
A22: モンスト事業本部 | C22: 仮説 | E22: モンスト事業部 | G22: × | H22: × | I22: モンスト事業部 | J22: モンスト関連の部署は、現在の「モンスト事業部」に集約・再編されました。 | K22: {=XLOOKUP($B22,'部署遍歴'!C:C,'部署遍歴'!D:D,"×")} -> ×
A24: div 1階層目フォルダ
A25: アドテクスタジオ | B25: アドテクG | C25: 廃止/再編 | D25: {=XLOOKUP($A25,'本部部署'!A:A,'本部部署'!A:A,"×",0,"1")} -> × | E25: {=XLOOKUP($B25,'本部部署'!B:B,'本部部署'!B:B,"×",0,"1")} -> × | F25: {=XLOOKUP($A25,'本部部署'!B:B,'本部部署'!B:B,"×",0,"1")} -> × | G25: {=XLOOKUP($B25,'本部部署'!A:A,'本部部署'!A:A,"×",0,"1")} -> × | H25: 開発本部 / デザイン本部
A26: アドテクスタジオ | B26: 企画G | C26: 廃止/再編 | D26: {=XLOOKUP($A26,'本部部署'!A:A,'本部部署'!A:A,"×",0,"1")} -> × | E26: {=XLOOKUP($B26,'本部部署'!B:B,'本部部署'!B:B,"×",0,"1")} -> × | F26: {=XLOOKUP($A26,'本部部署'!B:B,'本部部署'!B:B,"×",0,"1")} -> × | G26: {=XLOOKUP($B26,'本部部署'!A:A,'本部部署'!A:A,"×",0,"1")} -> × | H26: 開発本部 / デザイン本部
A27: アドテクスタジオ | B27: 開発G | C27: 廃止/再編 | D27: {=XLOOKUP($A27,'本部部署'!A:A,'本部部署'!A:A,"×",0,"1")} -> × | E27: {=XLOOKUP($B27,'本部部署'!B:B,'本部部署'!B:B,"×",0,"1")} -> × | F27: {=XLOOKUP($A27,'本部部署'!B:B,'本部部署'!B:B,"×",0,"1")} -> × | G27: {=XLOOKUP($B27,'本部部署'!A:A,'本部部署'!A:A,"×",0,"1")} -> × | H27: 開発本部 / デザイン本部
A28: アドテクスタジオ | B28: 室共有 | C28: 廃止/再編 | D28: {=XLOOKUP($A28,'本部部署'!A:A,'本部部署'!A:A,"×",0,"1")} -> × | E28: {=XLOOKUP($B28,'本部部署'!B:B,'本部部署'!B:B,"×",0,"1")} -> × | F28: {=XLOOKUP($A28,'本部部署'!B:B,'本部部署'!B:B,"×",0,"1")} -> × | G28: {=XLOOKUP($B28,'本部部署'!A:A,'本部部署'!A:A,"×",0,"1")} -> × | H28: -
A29: メディア事業本部 | B29: mixiゲーム部 | C29: 廃止/再編 | D29: {=XLOOKUP($A29,'本部部署'!A:A,'本部部署'!A:A,"×",0,"1")} -> × | E29: {=XLOOKUP($B29,'本部部署'!B:B,'本部部署'!B:B,"×",0,"1")} -> × | F29: {=XLOOKUP($A29,'本部部署'!B:B,'本部部署'!B:B,"×",0,"1")} -> × | G29: {=XLOOKUP($B29,'本部部署'!A:A,'本部部署'!A:A,"×",0,"1")} -> × | H29: ゲーム事業部
A30: メディア事業本部 | B30: mixiサービス部 | C30: 廃止/再編 | D30: {=XLOOKUP($A30,'本部部署'!A:A,'本部部署'!A:A,"×",0,"1")} -> × | E30: {=XLOOKUP($B30,'本部部署'!B:B,'本部部署'!B:B,"×",0,"1")} -> × | F30: {=XLOOKUP($A30,'本部部署'!B:B,'本部部署'!B:B,"×",0,"1")} -> × | G30: {=XLOOKUP($B30,'本部部署'!A:A,'本部部署'!A:A,"×",0,"1")} -> × | H30: MIXI M事業部
A31: メディア事業本部 | B31: 本部共有 | C31: 廃止/再編 | D31: {=XLOOKUP($A31,'本部部署'!A:A,'本部部署'!A:A,"×",0,"1")} -> × | E31: {=XLOOKUP($B31,'本部部署'!B:B,'本部部署'!B:B,"×",0,"1")} -> × | F31: {=XLOOKUP($A31,'本部部署'!B:B,'本部部署'!B:B,"×",0,"1")} -> × | G31: {=XLOOKUP($B31,'本部部署'!A:A,'本部部署'!A:A,"×",0,"1")} -> × | H31: -
A32: メディア事業本部 | B32: mixiコンテンツ部 | C32: 廃止/再編 | D32: {=XLOOKUP($A32,'本部部署'!A:A,'本部部署'!A:A,"×",0,"1")} -> × | E32: {=XLOOKUP($B32,'本部部署'!B:B,'本部部署'!B:B,"×",0,"1")} -> × | F32: {=XLOOKUP($A32,'本部部署'!B:B,'本部部署'!B:B,"×",0,"1")} -> × | G32: {=XLOOKUP($B32,'本部部署'!A:A,'本部部署'!A:A,"×",0,"1")} -> × | H32: MIXI M事業部
A33: メディア事業本部 | B33: mixiシステム部 | C33: 廃止/再編 | D33: {=XLOOKUP($A33,'本部部署'!A:A,'本部部署'!A:A,"×",0,"1")} -> × | E33: {=XLOOKUP($B33,'本部部署'!B:B,'本部部署'!B:B,"×",0,"1")} -> × | F33: {=XLOOKUP($A33,'本部部署'!B:B,'本部部署'!B:B,"×",0,"1")} -> × | G33: {=XLOOKUP($B33,'本部部署'!A:A,'本部部署'!A:A,"×",0,"1")} -> × | H33: MIXI M事業部
A34: Diverseスタジオ | B34: インドマーケット部 | C34: 廃止/分社化 | D34: {=XLOOKUP($A34,'本部部署'!A:A,'本部部署'!A:A,"×",0,"1")} -> × | E34: {=XLOOKUP($B34,'本部部署'!B:B,'本部部署'!B:B,"×",0,"1")} -> × | F34: {=XLOOKUP($A34,'本部部署'!B:B,'本部部署'!B:B,"×",0,"1")} -> × | G34: {=XLOOKUP($B34,'本部部署'!A:A,'本部部署'!A:A,"×",0,"1")} -> × | H34: 株式会社Diverse
A35: Diverseスタジオ | B35: かいはつ室 | C35: 廃止/分社化 | D35: {=XLOOKUP($A35,'本部部署'!A:A,'本部部署'!A:A,"×",0,"1")} -> × | E35: {=XLOOKUP($B35,'本部部署'!B:B,'本部部署'!B:B,"×",0,"1")} -> × | F35: {=XLOOKUP($A35,'本部部署'!B:B,'本部部署'!B:B,"×",0,"1")} -> × | G35: {=XLOOKUP($B35,'本部部署'!A:A,'本部部署'!A:A,"×",0,"1")} -> × | H35: 株式会社Diverse
A36: Diverseスタジオ | B36: ビジネス推進室 | C36: 廃止/分社化 | D36: {=XLOOKUP($A36,'本部部署'!A:A,'本部部署'!A:A,"×",0,"1")} -> × | E36: {=XLOOKUP($B36,'本部部署'!B:B,'本部部署'!B:B,"×",0,"1")} -> × | F36: {=XLOOKUP($A36,'本部部署'!B:B,'本部部署'!B:B,"×",0,"1")} -> × | G36: {=XLOOKUP($B36,'本部部署'!A:A,'本部部署'!A:A,"×",0,"1")} -> × | H36: 株式会社Diverse
... A38: Diverseスタジオ | B38: Poiboy事業部 | C38: 廃止/分社化 | D38: {=XLOOKUP($A38,'本部部署'!A:A,'本部部署'!A:A,"×",0,"1")} -> × | E38: {=XLOOKUP($B38,'本部部署'!B:B,'本部部署'!B:B,"×",0,"1")} -> × | F38: {=XLOOKUP($A38,'本部部署'!B:B,'本部部署'!B:B,"×",0,"1")} -> × | G38: {=XLOOKUP($B38,'本部部署'!A:A,'本部部署'!A:A,"×",0,"1")} -> × | H38: 株式会社Diverse
A39: Diverseスタジオ | B39: 経営管理部 | D39: {=XLOOKUP($A39,'本部部署'!A:A,'本部部署'!A:A,"×",0,"1")} -> × | E39: {=XLOOKUP($B39,'本部部署'!B:B,'本部部署'!B:B,"×",0,"1")} -> 経営管理部
A40: Diverseスタジオ | B40: 結婚支援事業部 | C40: 廃止/分社化 | D40: {=XLOOKUP($A40,'本部部署'!A:A,'本部部署'!A:A,"×",0,"1")} -> × | E40: {=XLOOKUP($B40,'本部部署'!B:B,'本部部署'!B:B,"×",0,"1")} -> × | F40: {=XLOOKUP($A40,'本部部署'!B:B,'本部部署'!B:B,"×",0,"1")} -> × | G40: {=XLOOKUP($B40,'本部部署'!A:A,'本部部署'!A:A,"×",0,"1")} -> × | H40: 株式会社Diverse
A41: Diverseスタジオ | B41: 新規サービス事業部 | C41: 廃止/分社化 | D41: {=XLOOKUP($A41,'本部部署'!A:A,'本部部署'!A:A,"×",0,"1")} -> × | E41: {=XLOOKUP($B41,'本部部署'!B:B,'本部部署'!B:B,"×",0,"1")} -> × | F41: {=XLOOKUP($A41,'本部部署'!B:B,'本部部署'!B:B,"×",0,"1")} -> × | G41: {=XLOOKUP($B41,'本部部署'!A:A,'本部部署'!A:A,"×",0,"1")} -> × | H41: 株式会社Diverse
A42: Diverseスタジオ | B42: youbride事業部 | C42: 廃止/分社化 | D42: {=XLOOKUP($A42,'本部部署'!A:A,'本部部署'!A:A,"×",0,"1")} -> × | E42: {=XLOOKUP($B42,'本部部署'!B:B,'本部部署'!B:B,"×",0,"1")} -> × | F42: {=XLOOKUP($A42,'本部部署'!B:B,'本部部署'!B:B,"×",0,"1")} -> × | G42: {=XLOOKUP($B42,'本部部署'!A:A,'本部部署'!A:A,"×",0,"1")} -> × | H42: 株式会社Diverse
A43: Diverseスタジオ | B43: 健全化推進室 | C43: 廃止/分社化 | D43: {=XLOOKUP($A43,'本部部署'!A:A,'本部部署'!A:A,"×",0,"1")} -> × | E43: {=XLOOKUP($B43,'本部部署'!B:B,'本部部署'!B:B,"×",0,"1")} -> × | F43: {=XLOOKUP($A43,'本部部署'!B:B,'本部部署'!B:B,"×",0,"1")} -> × | G43: {=XLOOKUP($B43,'本部部署'!A:A,'本部部署'!A:A,"×",0,"1")} -> × | H43: 株式会社Diverse
A44: Diverseスタジオ | B44: 技術研究所 | C44: 廃止/分社化 | D44: {=XLOOKUP($A44,'本部部署'!A:A,'本部部署'!A:A,"×",0,"1")} -> × | E44: {=XLOOKUP($B44,'本部部署'!B:B,'本部部署'!B:B,"×",0,"1")} -> × | F44: {=XLOOKUP($A44,'本部部署'!B:B,'本部部署'!B:B,"×",0,"1")} -> × | G44: {=XLOOKUP($B44,'本部部署'!A:A,'本部部署'!A:A,"×",0,"1")} -> × | H44: 株式会社Diverse
A45: Diverseスタジオ | B45: VEAT事業部 | C45: 廃止/分社化 | D45: {=XLOOKUP($A45,'本部部署'!A:A,'本部部署'!A:A,"×",0,"1")} -> × | E45: {=XLOOKUP($B45,'本部部署'!B:B,'本部部署'!B:B,"×",0,"1")} -> × | F45: {=XLOOKUP($A45,'本部部署'!B:B,'本部部署'!B:B,"×",0,"1")} -> × | G45: {=XLOOKUP($B45,'本部部署'!A:A,'本部部署'!A:A,"×",0,"1")} -> × | H45: 株式会社Diverse
A46: Diverseスタジオ | B46: メディア事業部 | C46: 廃止/分社化 | D46: {=XLOOKUP($A46,'本部部署'!A:A,'本部部署'!A:A,"×",0,"1")} -> × | E46: {=XLOOKUP($B46,'本部部署'!B:B,'本部部署'!B:B,"×",0,"1")} -> × | F46: {=XLOOKUP($A46,'本部部署'!B:B,'本部部署'!B:B,"×",0,"1")} -> × | G46: {=XLOOKUP($B46,'本部部署'!A:A,'本部部署'!A:A,"×",0,"1")} -> × | H46: 株式会社Diverse
A47: Diverseスタジオ | B47: YYC事業部 | C47: 廃止/分社化 | D47: {=XLOOKUP($A47,'本部部署'!A:A,'本部部署'!A:A,"×",0,"1")} -> × | E47: {=XLOOKUP($B47,'本部部署'!B:B,'本部部署'!B:B,"×",0,"1")} -> × | F47: {=XLOOKUP($A47,'本部部署'!B:B,'本部部署'!B:B,"×",0,"1")} -> × | G47: {=XLOOKUP($B47,'本部部署'!A:A,'本部部署'!A:A,"×",0,"1")} -> × | H47: 株式会社Diverse
A48: Diverseスタジオ | B48: 本部共有 | C48: 廃止/分社化 | D48: {=XLOOKUP($A48,'本部部署'!A:A,'本部部署'!A:A,"×",0,"1")} -> × | E48: {=XLOOKUP($B48,'本部部署'!B:B,'本部部署'!B:B,"×",0,"1")} -> × | F48: {=XLOOKUP($A48,'本部部署'!B:B,'本部部署'!B:B,"×",0,"1")} -> × | G48: {=XLOOKUP($B48,'本部部署'!A:A,'本部部署'!A:A,"×",0,"1")} -> × | H48: -
A49: Diverseスタジオ | B49: マッチングサービス事業部 | C49: 廃止/分社化 | D49: {=XLOOKUP($A49,'本部部署'!A:A,'本部部署'!A:A,"×",0,"1")} -> × | E49: {=XLOOKUP($B49,'本部部署'!B:B,'本部部署'!B:B,"×",0,"1")} -> × | F49: {=XLOOKUP($A49,'本部部署'!B:B,'本部部署'!B:B,"×",0,"1")} -> × | G49: {=XLOOKUP($B49,'本部部署'!A:A,'本部部署'!A:A,"×",0,"1")} -> × | H49: 株式会社Diverse
A50: モンストスタジオ | B50: マーケティングG | C50: 廃止/再編 | D50: {=XLOOKUP($A50,'本部部署'!A:A,'本部部署'!A:A,"×",0,"1")} -> × | E50: {=XLOOKUP($B50,'本部部署'!B:B,'本部部署'!B:B,"×",0,"1")} -> × | F50: {=XLOOKUP($A50,'本部部署'!B:B,'本部部署'!B:B,"×",0,"1")} -> × | G50: {=XLOOKUP($B50,'本部部署'!A:A,'本部部署'!A:A,"×",0,"1")} -> × | H50: モンスト事業部
A51: モンストスタジオ | B51: 企画・運用部 | C51: 廃止/再編 | D51: {=XLOOKUP($A51,'本部部署'!A:A,'本部部署'!A:A,"×",0,"1")} -> × | E51: {=XLOOKUP($B51,'本部部署'!B:B,'本部部署'!B:B,"×",0,"1")} -> × | F51: {=XLOOKUP($A51,'本部部署'!B:B,'本部部署'!B:B,"×",0,"1")} -> × | G51: {=XLOOKUP($B51,'本部部署'!A:A,'本部部署'!A:A,"×",0,"1")} -> × | H51: モンスト事業部
... A55: モンストスタジオ | B55: マーケティング部 | C55: 廃止/再編 | D55: {=XLOOKUP($A55,'本部部署'!A:A,'本部部署'!A:A,"×",0,"1")} -> × | E55: {=XLOOKUP($B55,'本部部署'!B:B,'本部部署'!B:B,"×",0,"1")} -> × | F55: {=XLOOKUP($A55,'本部部署'!B:B,'本部部署'!B:B,"×",0,"1")} -> × | G55: {=XLOOKUP($B55,'本部部署'!A:A,'本部部署'!A:A,"×",0,"1")} -> × | H55: モンスト事業部
A56: モンストスタジオ | B56: 事業戦略室 | D56: {=XLOOKUP($A56,'本部部署'!A:A,'本部部署'!A:A,"×",0,"1")} -> × | E56: {=XLOOKUP($B56,'本部部署'!B:B,'本部部署'!B:B,"×",0,"1")} -> 事業戦略室
A57: モンストスタジオ | B57: 本部共有 | C57: 廃止/再編 | D57: {=XLOOKUP($A57,'本部部署'!A:A,'本部部署'!A:A,"×",0,"1")} -> × | E57: {=XLOOKUP($B57,'本部部署'!B:B,'本部部署'!B:B,"×",0,"1")} -> × | F57: {=XLOOKUP($A57,'本部部署'!B:B,'本部部署'!B:B,"×",0,"1")} -> × | G57: {=XLOOKUP($B57,'本部部署'!A:A,'本部部署'!A:A,"×",0,"1")} -> × | H57: -
A58: ノハナ | B58: 全社共有 | C58: 存続 (子会社) | D58: {=XLOOKUP($A58,'本部部署'!A:A,'本部部署'!A:A,"×",0,"1")} -> × | E58: {=XLOOKUP($B58,'本部部署'!B:B,'本部部署'!B:B,"×",0,"1")} -> × | F58: {=XLOOKUP($A58,'本部部署'!B:B,'本部部署'!B:B,"×",0,"1")} -> × | G58: {=XLOOKUP($B58,'本部部署'!A:A,'本部部署'!A:A,"×",0,"1")} -> × | H58: 株式会社ノハナ
A59: 人事本部 | B59: 労務部 | D59: {=XLOOKUP($A59,'本部部署'!A:A,'本部部署'!A:A,"×",0,"1")} -> 人事本部 | E59: {=XLOOKUP($B59,'本部部署'!B:B,'本部部署'!B:B,"×",0,"1")} -> 労務部
A60: 人事本部 | B60: 人材開発部付 | D60: {=XLOOKUP($A60,'本部部署'!A:A,'本部部署'!A:A,"×",0,"1")} -> 人事本部 | E60: {=XLOOKUP($B60,'本部部署'!B:B,'本部部署'!B:B,"×",0,"1")} -> 人材開発部付
A61: 人事本部 | B61: 人事戦略部付 | D61: {=XLOOKUP($A61,'本部部署'!A:A,'本部部署'!A:A,"×",0,"1")} -> 人事本部 | E61: {=XLOOKUP($B61,'本部部署'!B:B,'本部部署'!B:B,"×",0,"1")} -> ×
A62: 人事本部 | B62: 人事企画部 | D62: {=XLOOKUP($A62,'本部部署'!A:A,'本部部署'!A:A,"×",0,"1")} -> 人事本部 | E62: {=XLOOKUP($B62,'本部部署'!B:B,'本部部署'!B:B,"×",0,"1")} -> ×
A63: 人事本部 | B63: 人材開発部 | D63: {=XLOOKUP($A63,'本部部署'!A:A,'本部部署'!A:A,"×",0,"1")} -> 人事本部 | E63: {=XLOOKUP($B63,'本部部署'!B:B,'本部部署'!B:B,"×",0,"1")} -> 人材開発部
A64: 人事本部 | B64: 人事戦略室 | D64: {=XLOOKUP($A64,'本部部署'!A:A,'本部部署'!A:A,"×",0,"1")} -> 人事本部 | E64: {=XLOOKUP($B64,'本部部署'!B:B,'本部部署'!B:B,"×",0,"1")} -> ×
A65: 人事本部 | B65: 人事企画部付 | D65: {=XLOOKUP($A65,'本部部署'!A:A,'本部部署'!A:A,"×",0,"1")} -> 人事本部 | E65: {=XLOOKUP($B65,'本部部署'!B:B,'本部部署'!B:B,"×",0,"1")} -> ×
A66: 人事本部 | B66: グループ会社サポート部 | D66: {=XLOOKUP($A66,'本部部署'!A:A,'本部部署'!A:A,"×",0,"1")} -> 人事本部 | E66: {=XLOOKUP($B66,'本部部署'!B:B,'本部部署'!B:B,"×",0,"1")} -> グループ会社サポート部
A67: 人事本部 | B67: 人材採用部 | D67: {=XLOOKUP($A67,'本部部署'!A:A,'本部部署'!A:A,"×",0,"1")} -> 人事本部 | E67: {=XLOOKUP($B67,'本部部署'!B:B,'本部部署'!B:B,"×",0,"1")} -> ×
A68: 人事本部 | B68: 人材採用部付 | D68: {=XLOOKUP($A68,'本部部署'!A:A,'本部部署'!A:A,"×",0,"1")} -> 人事本部 | E68: {=XLOOKUP($B68,'本部部署'!B:B,'本部部署'!B:B,"×",0,"1")} -> ×
A69: 人事本部 | B69: 人事戦略部 | D69: {=XLOOKUP($A69,'本部部署'!A:A,'本部部署'!A:A,"×",0,"1")} -> 人事本部 | E69: {=XLOOKUP($B69,'本部部署'!B:B,'本部部署'!B:B,"×",0,"1")} -> 人事戦略部
A70: 人事本部 | B70: 組織戦略部 | D70: {=XLOOKUP($A70,'本部部署'!A:A,'本部部署'!A:A,"×",0,"1")} -> 人事本部 | E70: {=XLOOKUP($B70,'本部部署'!B:B,'本部部署'!B:B,"×",0,"1")} -> 組織戦略部
... A76: コーポレートファイナンス本部 | B76: 財務企画部 | D76: {=XLOOKUP($A76,'本部部署'!A:A,'本部部署'!A:A,"×",0,"1")} -> コーポレートファイナンス本部 | E76: {=XLOOKUP($B76,'本部部署'!B:B,'本部部署'!B:B,"×",0,"1")} -> 財務企画部
A77: コーポレートファイナンス本部 | B77: 本部共有 | D77: {=XLOOKUP($A77,'本部部署'!A:A,'本部部署'!A:A,"×",0,"1")} -> コーポレートファイナンス本部 | E77: {=XLOOKUP($B77,'本部部署'!B:B,'本部部署'!B:B,"×",0,"1")} -> × | F77: {=XLOOKUP($A77,'本部部署'!B:B,'本部部署'!B:B,"×",0,"1")} -> × | G77: {=XLOOKUP($B77,'本部部署'!A:A,'本部部署'!A:A,"×",0,"1")} -> ×
A78: コーポレートファイナンス本部 | B78: 経理税務部 | D78: {=XLOOKUP($A78,'本部部署'!A:A,'本部部署'!A:A,"×",0,"1")} -> コーポレートファイナンス本部 | E78: {=XLOOKUP($B78,'本部部署'!B:B,'本部部署'!B:B,"×",0,"1")} -> 経理税務部
A79: コーポレートデベロップメント本部 | B79: Integration Management部 | D79: {=XLOOKUP($A79,'本部部署'!A:A,'本部部署'!A:A,"×",0,"1")} -> コーポレートデベロップメント本部 | E79: {=XLOOKUP($B79,'本部部署'!B:B,'本部部署'!B:B,"×",0,"1")} -> Integration Management部
A80: コーポレートデベロップメント本部 | B80: 事業開発部 | D80: {=XLOOKUP($A80,'本部部署'!A:A,'本部部署'!A:A,"×",0,"1")} -> コーポレートデベロップメント本部 | E80: {=XLOOKUP($B80,'本部部署'!B:B,'本部部署'!B:B,"×",0,"1")} -> × | F80: {=XLOOKUP($A80,'本部部署'!B:B,'本部部署'!B:B,"×",0,"1")} -> × | G80: {=XLOOKUP($B80,'本部部署'!A:A,'本部部署'!A:A,"×",0,"1")} -> ×
A81: コーポレートデベロップメント本部 | B81: 本部共有 | D81: {=XLOOKUP($A81,'本部部署'!A:A,'本部部署'!A:A,"×",0,"1")} -> コーポレートデベロップメント本部 | E81: {=XLOOKUP($B81,'本部部署'!B:B,'本部部署'!B:B,"×",0,"1")} -> × | F81: {=XLOOKUP($A81,'本部部署'!B:B,'本部部署'!B:B,"×",0,"1")} -> × | G81: {=XLOOKUP($B81,'本部部署'!A:A,'本部部署'!A:A,"×",0,"1")} -> ×
A82: コーポレートデベロップメント本部 | B82: 投資事業部 | D82: {=XLOOKUP($A82,'本部部署'!A:A,'本部部署'!A:A,"×",0,"1")} -> コーポレートデベロップメント本部 | E82: {=XLOOKUP($B82,'本部部署'!B:B,'本部部署'!B:B,"×",0,"1")} -> 投資事業部
A83: コーポレートデベロップメント本部 | B83: 事業企画推進部 | D83: {=XLOOKUP($A83,'本部部署'!A:A,'本部部署'!A:A,"×",0,"1")} -> コーポレートデベロップメント本部 | E83: {=XLOOKUP($B83,'本部部署'!B:B,'本部部署'!B:B,"×",0,"1")} -> 事業企画推進部
A84: 経営企画室 | B84: 室共有 | D84: {=XLOOKUP($A84,'本部部署'!A:A,'本部部署'!A:A,"×",0,"1")} -> × | E84: {=XLOOKUP($B84,'本部部署'!B:B,'本部部署'!B:B,"×",0,"1")} -> × | F84: {=XLOOKUP($A84,'本部部署'!B:B,'本部部署'!B:B,"×",0,"1")} -> 経営企画室 | G84: {=XLOOKUP($B84,'本部部署'!A:A,'本部部署'!A:A,"×",0,"1")} -> ×
A85: マーケティング本部 | B85: デジタルマーケティング室 | C85: 廃止/再編 | D85: {=XLOOKUP($A85,'本部部署'!A:A,'本部部署'!A:A,"×",0,"1")} -> × | E85: {=XLOOKUP($B85,'本部部署'!B:B,'本部部署'!B:B,"×",0,"1")} -> × | F85: {=XLOOKUP($A85,'本部部署'!B:B,'本部部署'!B:B,"×",0,"1")} -> × | G85: {=XLOOKUP($B85,'本部部署'!A:A,'本部部署'!A:A,"×",0,"1")} -> × | H85: デザイン本部 / 各事業部
A86: マーケティング本部 | B86: ブランド戦略室 | C86: 廃止/再編 | D86: {=XLOOKUP($A86,'本部部署'!A:A,'本部部署'!A:A,"×",0,"1")} -> × | E86: {=XLOOKUP($B86,'本部部署'!B:B,'本部部署'!B:B,"×",0,"1")} -> × | F86: {=XLOOKUP($A86,'本部部署'!B:B,'本部部署'!B:B,"×",0,"1")} -> × | G86: {=XLOOKUP($B86,'本部部署'!A:A,'本部部署'!A:A,"×",0,"1")} -> × | H86: デザイン本部 / 各事業部
A87: マーケティング本部 | B87: マーケティング推進室 | C87: 廃止/再編 | D87: {=XLOOKUP($A87,'本部部署'!A:A,'本部部署'!A:A,"×",0,"1")} -> × | E87: {=XLOOKUP($B87,'本部部署'!B:B,'本部部署'!B:B,"×",0,"1")} -> × | F87: {=XLOOKUP($A87,'本部部署'!B:B,'本部部署'!B:B,"×",0,"1")} -> × | G87: {=XLOOKUP($B87,'本部部署'!A:A,'本部部署'!A:A,"×",0,"1")} -> × | H87: デザイン本部 / 各事業部
A88: マーケティング本部 | B88: PR室 | C88: 廃止/再編 | D88: {=XLOOKUP($A88,'本部部署'!A:A,'本部部署'!A:A,"×",0,"1")} -> × | E88: {=XLOOKUP($B88,'本部部署'!B:B,'本部部署'!B:B,"×",0,"1")} -> × | F88: {=XLOOKUP($A88,'本部部署'!B:B,'本部部署'!B:B,"×",0,"1")} -> × | G88: {=XLOOKUP($B88,'本部部署'!A:A,'本部部署'!A:A,"×",0,"1")} -> × | H88: デザイン本部 / 各事業部
A89: マーケティング本部 | B89: 本部共有 | C89: 廃止/再編 | D89: {=XLOOKUP($A89,'本部部署'!A:A,'本部部署'!A:A,"×",0,"1")} -> × | E89: {=XLOOKUP($B89,'本部部署'!B:B,'本部部署'!B:B,"×",0,"1")} -> × | F89: {=XLOOKUP($A89,'本部部署'!B:B,'本部部署'!B:B,"×",0,"1")} -> × | G89: {=XLOOKUP($B89,'本部部署'!A:A,'本部部署'!A:A,"×",0,"1")} -> × | H89: -
A90: マーケティング本部 | B90: マーケティング戦略室 | C90: 廃止/再編 | D90: {=XLOOKUP($A90,'本部部署'!A:A,'本部部署'!A:A,"×",0,"1")} -> × | E90: {=XLOOKUP($B90,'本部部署'!B:B,'本部部署'!B:B,"×",0,"1")} -> × | F90: {=XLOOKUP($A90,'本部部署'!B:B,'本部部署'!B:B,"×",0,"1")} -> × | G90: {=XLOOKUP($B90,'本部部署'!A:A,'本部部署'!A:A,"×",0,"1")} -> × | H90: デザイン本部 / 各事業部
A91: デザイン本部 | B91: クリエイティブ室 | D91: {=XLOOKUP($A91,'本部部署'!A:A,'本部部署'!A:A,"×",0,"1")} -> ﾃﾞｻﾞｲﾝ本部 | E91: {=XLOOKUP($B91,'本部部署'!B:B,'本部部署'!B:B,"×",0,"1")} -> ×
A92: デザイン本部 | B92: 制作室 | D92: {=XLOOKUP($A92,'本部部署'!A:A,'本部部署'!A:A,"×",0,"1")} -> ﾃﾞｻﾞｲﾝ本部 | E92: {=XLOOKUP($B92,'本部部署'!B:B,'本部部署'!B:B,"×",0,"1")} -> ×
A93: デザイン本部 | B93: テクニカルデザイン室 | D93: {=XLOOKUP($A93,'本部部署'!A:A,'本部部署'!A:A,"×",0,"1")} -> ﾃﾞｻﾞｲﾝ本部 | E93: {=XLOOKUP($B93,'本部部署'!B:B,'本部部署'!B:B,"×",0,"1")} -> ﾃｸﾆｶﾙﾃﾞｻﾞｲﾝ室
A94: デザイン本部 | B94: プロダクトデザイン室 | D94: {=XLOOKUP($A94,'本部部署'!A:A,'本部部署'!A:A,"×",0,"1")} -> ﾃﾞｻﾞｲﾝ本部 | E94: {=XLOOKUP($B94,'本部部署'!B:B,'本部部署'!B:B,"×",0,"1")} -> ﾌﾟﾛﾀﾞｸﾄﾃﾞｻﾞｲﾝ室
A95: デザイン本部 | B95: ブランドデザイン室 | D95: {=XLOOKUP($A95,'本部部署'!A:A,'本部部署'!A:A,"×",0,"1")} -> ﾃﾞｻﾞｲﾝ本部 | E95: {=XLOOKUP($B95,'本部部署'!B:B,'本部部署'!B:B,"×",0,"1")} -> ﾌﾞﾗﾝﾄﾞﾃﾞｻﾞｲﾝ室
A96: デザイン本部 | B96: デザイン戦略室 | D96: {=XLOOKUP($A96,'本部部署'!A:A,'本部部署'!A:A,"×",0,"1")} -> ﾃﾞｻﾞｲﾝ本部 | E96: {=XLOOKUP($B96,'本部部署'!B:B,'本部部署'!B:B,"×",0,"1")} -> ×
A97: デザイン本部 | B97: デザイン推進室 | D97: {=XLOOKUP($A97,'本部部署'!A:A,'本部部署'!A:A,"×",0,"1")} -> ﾃﾞｻﾞｲﾝ本部 | E97: {=XLOOKUP($B97,'本部部署'!B:B,'本部部署'!B:B,"×",0,"1")} -> ×
A98: デザイン本部 | B98: モンストデザイン室 | D98: {=XLOOKUP($A98,'本部部署'!A:A,'本部部署'!A:A,"×",0,"1")} -> ﾃﾞｻﾞｲﾝ本部 | E98: {=XLOOKUP($B98,'本部部署'!B:B,'本部部署'!B:B,"×",0,"1")} -> ×
A99: デザイン本部 | B99: 本部共有 | D99: {=XLOOKUP($A99,'本部部署'!A:A,'本部部署'!A:A,"×",0,"1")} -> ﾃﾞｻﾞｲﾝ本部 | E99: {=XLOOKUP($B99,'本部部署'!B:B,'本部部署'!B:B,"×",0,"1")} -> ×
A100: デザイン本部 | B100: XFLAGデザイン室 | D100: {=XLOOKUP($A100,'本部部署'!A:A,'本部部署'!A:A,"×",0,"1")} -> ﾃﾞｻﾞｲﾝ本部 | E100: {=XLOOKUP($B100,'本部部署'!B:B,'本部部署'!B:B,"×",0,"1")} -> ×
A101: デザイン本部 | B101: 動画クリエイティブ室 | D101: {=XLOOKUP($A101,'本部部署'!A:A,'本部部署'!A:A,"×",0,"1")} -> ﾃﾞｻﾞｲﾝ本部 | E101: {=XLOOKUP($B101,'本部部署'!B:B,'本部部署'!B:B,"×",0,"1")} -> 動画ｸﾘｴｲﾃｨﾌﾞ室
A102: デザイン本部 | B102: XFLAG PICTURES | D102: {=XLOOKUP($A102,'本部部署'!A:A,'本部部署'!A:A,"×",0,"1")} -> ﾃﾞｻﾞｲﾝ本部 | E102: {=XLOOKUP($B102,'本部部署'!B:B,'本部部署'!B:B,"×",0,"1")} -> ×
... A107: デジタルエンターテインメントオペレーションズ本部 | B107: モンスト開発部 | D107: {=XLOOKUP($A107,'本部部署'!A:A,'本部部署'!A:A,"×",0,"1")} -> デジタルエンターテインメントオペレーションズ本部 | E107: {=XLOOKUP($B107,'本部部署'!B:B,'本部部署'!B:B,"×",0,"1")} -> ﾓﾝｽﾄ開発部
A108: デジタルエンターテインメントオペレーションズ本部 | B108: 本部共有 | D108: {=XLOOKUP($A108,'本部部署'!A:A,'本部部署'!A:A,"×",0,"1")} -> デジタルエンターテインメントオペレーションズ本部 | E108: {=XLOOKUP($B108,'本部部署'!B:B,'本部部署'!B:B,"×",0,"1")} -> × | F108: {=XLOOKUP($A108,'本部部署'!B:B,'本部部署'!B:B,"×",0,"1")} -> × | G108: {=XLOOKUP($B108,'本部部署'!A:A,'本部部署'!A:A,"×",0,"1")} -> ×
A109: デジタルエンターテインメントオペレーションズ本部 | B109: ファンマーケティング部 | D109: {=XLOOKUP($A109,'本部部署'!A:A,'本部部署'!A:A,"×",0,"1")} -> デジタルエンターテインメントオペレーションズ本部 | E109: {=XLOOKUP($B109,'本部部署'!B:B,'本部部署'!B:B,"×",0,"1")} -> ファンマーケティング部 | F109: {=XLOOKUP($A109,'本部部署'!B:B,'本部部署'!B:B,"×",0,"1")} -> × | G109: {=XLOOKUP($B109,'本部部署'!A:A,'本部部署'!A:A,"×",0,"1")} -> ×
A110: デジタルエンターテインメントオペレーションズ本部 | B110: モンスト運営部 | D110: {=XLOOKUP($A110,'本部部署'!A:A,'本部部署'!A:A,"×",0,"1")} -> デジタルエンターテインメントオペレーションズ本部 | E110: {=XLOOKUP($B110,'本部部署'!B:B,'本部部署'!B:B,"×",0,"1")} -> ﾓﾝｽﾄ運営部
A111: デジタルエンターテインメントオペレーションズ本部 | B111: コトダマン事業部 | D111: {=XLOOKUP($A111,'本部部署'!A:A,'本部部署'!A:A,"×",0,"1")} -> デジタルエンターテインメントオペレーションズ本部 | E111: {=XLOOKUP($B111,'本部部署'!B:B,'本部部署'!B:B,"×",0,"1")} -> × | F111: {=XLOOKUP($A111,'本部部署'!B:B,'本部部署'!B:B,"×",0,"1")} -> × | G111: {=XLOOKUP($B111,'本部部署'!A:A,'本部部署'!A:A,"×",0,"1")} -> ×
A112: デジタルエンターテインメントオペレーションズ本部 | B112: モンストIPクリエイション部 | D112: {=XLOOKUP($A112,'本部部署'!A:A,'本部部署'!A:A,"×",0,"1")} -> デジタルエンターテインメントオペレーションズ本部 | E112: {=XLOOKUP($B112,'本部部署'!B:B,'本部部署'!B:B,"×",0,"1")} -> ﾓﾝｽﾄIPｸﾘｴｲｼｮﾝ部
A113: アイ・マーキュリーキャピタル | B113: 全社共有 | C113: 存続 (子会社) | D113: {=XLOOKUP($A113,'本部部署'!A:A,'本部部署'!A:A,"×",0,"1")} -> × | E113: {=XLOOKUP($B113,'本部部署'!B:B,'本部部署'!B:B,"×",0,"1")} -> × | F113: {=XLOOKUP($A113,'本部部署'!B:B,'本部部署'!B:B,"×",0,"1")} -> × | G113: {=XLOOKUP($B113,'本部部署'!A:A,'本部部署'!A:A,"×",0,"1")} -> × | H113: 株式会社アイ・マーキュリーキャピタル
A114: エックスフラッグスタジオ本部 | B114: アドテク部 | C114: 廃止/再編 | D114: {=XLOOKUP($A114,'本部部署'!A:A,'本部部署'!A:A,"×",0,"1")} -> × | E114: {=XLOOKUP($B114,'本部部署'!B:B,'本部部署'!B:B,"×",0,"1")} -> × | F114: {=XLOOKUP($A114,'本部部署'!B:B,'本部部署'!B:B,"×",0,"1")} -> × | G114: {=XLOOKUP($B114,'本部部署'!A:A,'本部部署'!A:A,"×",0,"1")} -> × | H114: 開発本部 / デザイン本部
...

Sheet (旧)project
A1: 管理者退職済み（管理者不明） | E1: 69(10)
A2: 退職フラグのもので、「無記載/無/無し＝退職Jiraに記載なし」、「×＝退職Jiraが起票されていないor記載ミス」
A4: Project topフォルダ | B4: フラグ | C4: 管理者 | D4: C列部署 | E4: 管理者 | F4: 部署 | G4: 管理者 | H4: 部署 | I4: 管理者 | J4: 部署 | K4: 管理者 | L4: 部署 | M4: 管理者 | N4: 部署 | O4: 管理者 | P4: 部署 | Q4: 管理者 | R4: 部署 | S4: 管理者 | T4: 部署 | U4: 退職者部署 | V4: 退職者部署
A5: PJ_F1 | C5: 島村 恒平 | D5: 取締役 | E5: 島村恒平
A6: 共有スケジュール | C6: 長谷川 純子 | D6: コーポレートファイナンス本部/経理税務部/経理グループ | E6: 長谷川純子
A7: group-ip | C7: 村津 文武 | D7: コンプライアンス本部/知財室/商標・著作権グループ | E7: 村津文武
A8: DSP | C8: 尾関 芳郎 | D8: みてね事業本部/みてねプラットフォーム部/SREグループ | E8: 尾関芳郎
A9: ミクシィリサーチ経理業務 | C9: 長岡 輝 | D9: Vantageスタジオ/Romi事業部/UX企画グループ | E9: 長岡輝
A10: UXDワーキンググループ | C10: 藤崎 宏司 | D10: Vantageスタジオ/事業推進室/mercuryグループ | E10: 藤崎宏司
A11: ミクシィグループWebクリッピング | C11: 木下智子、菊池翔平、池谷洋平、寺岡浩史、町井香織、古澤祐幸 | D11: 経営推進本部/広報部/インターナルコミュニケーショングループ/インターナルコミュニケーションチーム | E11: 木下智子 | F11: 経営推進本部/広報部 | G11: 菊池翔平 | H11: 経営推進本部/広報部/サステナビリティ推進グループ | I11: 池谷 洋平 | J11: 経営推進本部/広報部/サステナビリティ推進グループ/次世代育成支援チーム | K11: 寺岡 浩史 | L11: 経営推進本部/広報部/サステナビリティ推進グループ/次世代育成支援チーム | M11: 町井 香織 | N11: 経営推進本部/広報部/企業広報グループ | O11: 古澤 祐幸 | T11: 経営推進本部/広報部/インターナルコミュニケーショングループ/インターナルコミュニケーションチーム
A12: キャリア関連 | C12: 大崎 敦士 | D12: ライブエクスペリエンス事業本部 | E12: 大崎敦士
A13: soup_curry | C13: 楠井 大地、神村 武 | D13: × | E13: 楠井大地 | F13: デジタルエンターテインメントオペレーションズ本部/モンスト運営部/ディレクターグループ | G13: 神村武 | H13: × | T13: ×
A14: 経営企画・法務共有 | C14: 泉望 | D14: コンプライアンス本部/法務部/オペレーショングループ | E14: 泉望 | T14: コンプライアンス本部/法務部/オペレーショングループ
A15: 影舞 | C15: 渡部 喜正 | D15: Vantageスタジオ/mixi事業部 | E15: 渡部喜正
A16: ノハナ採用 | B16: 退職 | C16: 大森 和悦、高杉 沙耶 | D16: 無 | E16: 大森和悦 | F16: 無 | G16: 高杉沙耶 | H16: × | T16: ノハナ事業部 | U16: 無 | V16: ノハナ事業部
A17: セキュリティ | C17: 亀山直生、村瀬龍馬 | D17: セキュリティ室(本部格) | E17: 亀山直生 | F17: × | G17: 村瀬龍馬 | H17: × | T17: セキュリティ室(本部格)
A18: 【機密】登用チャレンジ | C18: 卯木 源一 | D18: 人事本部/組織戦略部/横断HRBPグループ | E18: 卯木源一
A19: mr-scanner-output | C19: 長岡 輝 | D19: Vantageスタジオ/Romi事業部/UX企画グループ | E19: 長岡輝
A20: Bonfire | C20: 澤田祐希、 栗丸侑大、 吉田明広 | D20: 開発本部/たんぽぽ室/ブルーグループ | E20: 澤田祐希 | F20: × | G20: 栗丸侑大 | H20: × | I20: 吉田 明広 | J20: × | T20: 開発本部/たんぽぽ室/ブルーグループ
A21: Enishi | C21: 大崎 敦士 | D21: ライブエクスペリエンス事業本部 | E21: 大崎敦士
A22: mixiモールデータ | C22: 杉田 絵美 | D22: 開発本部/たんぽぽ室/Enablementグループ | E22: 杉田絵美
A23: 契約管理台帳 | C23: 小林 完爾 | D23: 上級執行役員 | E23: 小林完爾
A24: XFLAGアシスタント共有 | C24: 齋藤 敦子、宇佐美裕子、村上 由利奈、峯岸保栄 | D24: デジタルエンターテインメントオペレーションズ本部/モンスト運営部 | E24: 齋藤敦子
A25: ノハナサポート | C25: 牛田美穂 | D25: CS本部/CX部/Enhancementグループ/組織開発チーム | E25: 牛田美穂 | T25: CS本部/CX部/Enhancementグループ/組織開発チーム
A26: Creative | C26: 越智 純平 | D26: デザイン本部/動画クリエイティブ室 | E26: 越智純平
A27: mixiカンファレンス | C27: 岨中 健太 | D27: Vantageスタジオ/事業推進室 | E27: 岨中健太
A28: 知財運用支援 | C28: 村津 文武 | D28: コンプライアンス本部/知財室/商標・著作権グループ | E28: 村津文武
A29: 開発マネージャ共有 | B29: 退職 | C29: 福森 美貴 | D29: 人事部 | E29: 福森美貴 | F29: 人事部 | H29: × | T29: × | U29: 人事部 | V29: ×
A30: CONNECTIT_SF | B30: 退職 | C30: 洪 嘉優 | D30: 投資事業部 | E30: 洪嘉優 | F30: 投資事業部 | H30: × | T30: × | U30: 投資事業部 | V30: ×
A31: LE事業本部AM | C31: 長岡 輝 | D31: Vantageスタジオ/Romi事業部/UX企画グループ | E31: 長岡輝
A32: 経理・財務共有 | C32: 望月 大輔 | D32: コーポレートファイナンス本部/経理税務部 | E32: 望月大輔
A33: mb | B33: 退職 | C33: 竹田 広平 | D33: インキュベーション事業部 | E33: 竹田広平 | F33: インキュベーション事業部 | H33: × | T33: × | U33: インキュベーション事業部 | V33: ×
A34: MFプロジェクト | C34: 嵯峨 勇 | D34: はたらく環境推進本部/せいかつ環境室/せいかつ環境Aグループ | E34: 嵯峨勇
A35: 経理・労務共通 | C35: 中川 真紀子、 酒井 優、坂田 信隆a | D35: 人事本部/グループ会社サポート部 | E35: 中川真紀子
A36: SH人事・労務 | B36: 退職 | C36: 奥田 匡彦 | D36: 無し | E36: 奥田匡彦 | F36: 無し | H36: × | T36: × | U36: 無し | V36: ×
A37: mixipark | C37: 石井 公二 | D37: デジタルエンターテインメントパブリッシング本部 | E37: 石井公二
A38: fanfest2020 | C38: 山口 祥子 | D38: ライブエクスペリエンス事業本部/フットボール事業部/事業推進グループ | E38: 山口祥子
A39: ブラナイ | C39: 澁谷 高広 | D39: ソーシャルベッティング事業本部/TIPSTAR事業部/プロダクト戦略グループ/開発チーム | E39: 澁谷高広
A40: tech_data | C40: 横山 義之、曽我 雄二 | D40: デザイン本部 | E40: 横山義之
A41: 財務・労務共通 | B41: 退職 | C41: 菅原 亜弓、 中川 真紀子 | D41: 労務部 | E41: 菅原亜弓 | F41: 労務部 | G41: 中川真紀子 | H41: × | T41: × | U41: 労務部 | V41: ×
A42: XFLAG人事戦略室 | C42: 諸橋裕 小川大輔 貝島梨紗 山本陽司 柳本修平 | D42: ソーシャルベッティング事業本部/価値創造室/コンテンツグループ/コンテンツビジネスチーム | E42: 諸橋裕 | F42: ライブエクスペリエンス事業本部/企画推進部/HRBPグループ | G42: 小川大輔 | H42: 人事本部/人事戦略部/データ活用推進グループ | I42: 貝島 梨紗 | J42: 人事本部/組織戦略部 | K42: 山本 陽司 | L42: 人事本部/MCS室 | M42: 柳本 修平 | N42: × | T42: ソーシャルベッティング事業本部/価値創造室/コンテンツグループ/コンテンツビジネスチーム
A43: 広報IR共有 | C43: 木下智子、菊池翔平、池谷洋平、寺岡浩史、町井香織 | D43: 経営推進本部/広報部/インターナルコミュニケーショングループ/インターナルコミュニケーションチーム | E43: 木下智子 | F43: 経営推進本部/広報部 | G43: 菊池翔平 | H43: 経営推進本部/広報部/サステナビリティ推進グループ | I43: 池谷 洋平 | J43: 経営推進本部/広報部/サステナビリティ推進グループ/次世代育成支援チーム | K43: 寺岡 浩史 | L43: 経営推進本部/広報部/サステナビリティ推進グループ/次世代育成支援チーム | M43: 町井 香織 | N43: × | T43: 経営推進本部/広報部/インターナルコミュニケーショングループ/インターナルコミュニケーションチーム
A44: コンテンツ管理システム | C44: 杉田 絵美 | D44: 開発本部/たんぽぽ室/Enablementグループ | E44: 杉田絵美
A45: monst_コラボ関連資料 | C45: 田所 将 | D45: デジタルエンターテインメントオペレーションズ本部/モンスト運営部/コラボ推進グループ | E45: 田所将
A46: 株式関連 | C46: 小林 完爾 | D46: 上級執行役員 | E46: 小林完爾
A47: 営業案件 | B47: 退職 | C47: 石井 瞬 | E47: 石井瞬 | F47: 無記載 | H47: × | T47: × | V47: ×
A48: HAMBOURG_PMI | B48: 退職 | C48: 寺谷 祐樹 | D48: × | E48: 寺谷祐樹 | F48: × | H48: × | T48: × | U48: × | V48: ×
A49: リサーチ担当者間共有 | B49: 退職 | C49: × | E49: × | H49: ×
A50: 人材開発temp | B50: 退職 | C50: 太田 雅登 | D50: 無し | E50: 太田雅登 | F50: 無し | H50: × | T50: × | U50: 無し | V50: ×
A51: sfidante | C51: 佐藤 僚 | D51: みてね事業本部 | E51: 佐藤僚
A52: 入稿バナー確認用 | C52: 北 由布子 | D52: Vantageスタジオ/事業推進室/事業推進グループ/アシスタントチーム | E52: 北由布子
A53: 労務・仙台共有 | B53: 退職 | C53: 菅原 亜弓、 中川 真紀子 | D53: 労務部 | E53: 菅原亜弓 | F53: 労務部 | G53: 中川真紀子 | H53: × | T53: × | U53: 労務部 | V53: ×
A54: モンストアニメ | C54: 蛭川 幸太郎、山下 春樹、金子 好宏、宇野 博美、安原 英樹 | D54: はたらく環境推進本部/ビジネスサポート室/インフォメーションハブグループ | E54: 蛭川幸太郎
A55: TED_workspace | C55: 谷 賢史、野上 祐平、原 由佳理 | D55: デザイン本部/テクニカルデザイン室 | E55: 谷賢史
A56: mixi運用 | C56: 渡部 喜正 | D56: Vantageスタジオ/mixi事業部 | E56: 渡部喜正
A57: QA_G | C57: 石井 万祐子 | D57: デジタルエンターテインメントオペレーションズ本部/モンスト開発部/QAグループ/QA3チーム | E57: 石井万祐子
A58: kizuna | B58: 退職 | C58: 楠井 大地 | D58: 人事戦略部付 | E58: 楠井大地 | F58: 人事戦略部付 | H58: × | T58: × | U58: 人事戦略部付 | V58: ×
A59: 広告ダッシュボード | B59: 退職 | C59: 安藤 真祐子 | D59: ﾏｰﾁｬﾝﾀﾞｲｼﾞﾝｸﾞ部 | E59: 安藤真祐子 | F59: ﾏｰﾁｬﾝﾀﾞｲｼﾞﾝｸﾞ部 | H59: × | T59: × | U59: ﾏｰﾁｬﾝﾀﾞｲｼﾞﾝｸﾞ部 | V59: ×
A60: 【CS推進部】特別渉外対応 | B60: 退職 | C60: 疋田 建典 | D60: CS部 | E60: 疋田建典 | F60: CS部 | H60: × | T60: × | U60: CS部 | V60: ×
A61: モンストIPクリエイション部アシスタント共有 | C61: 今野 ひとみ | D61: デジタルエンターテインメントオペレーションズ本部/モンストIPクリエイション部/PJ支援グループ | E61: 今野ひとみ
A62: はたらく環境課情報共有 | C62: 加藤 徳英、菅原 亜弓、宮本 憲枝 | D62: はたらく環境推進本部/コーポレートエンジニアリング部 | E62: 加藤徳英
A63: XFLAG_assistant | C63: 望月美詠、内藤梓、草村衣未、阿部久美 | D63: デジタルエンターテインメントオペレーションズ本部/コトダマン制作部/制作運用グループ/サービス運用チーム | E63: 望月美詠 | F63: はたらく環境推進本部/せいかつ環境室/せいかつ環境Bグループ/せいかつ環境Cチーム | G63: 内藤梓 | H63: 開発本部/たんぽぽ室/BOグループ | I63: 草村 衣未 | J63: はたらく環境推進本部/ビジネスサポート室/ボイスグループ | K63: 阿部 久美 | L63: × | T63: デジタルエンターテインメントオペレーションズ本部/コトダマン制作部/制作運用グループ/サービス運用チーム
A64: SPgamePF共通化PJ | C64: 平山 英輝 | D64: はたらく環境推進本部 | E64: 平山英輝
A65: 【機密】入社者データ共有 | C65: 卯木 源一、佐藤 貴亮、山本 陽司 | D65: 人事本部/組織戦略部/横断HRBPグループ | E65: 卯木源一
A66: Jets_temp | B66: 退職 | C66: × | E66: × | H66: ×
A67: mixiイメージ共有ワークショップ | C67: 渡部 喜正 | D67: Vantageスタジオ/mixi事業部 | E67: 渡部喜正
A68: monsoni | B68: 退職 | C68: 中村良一 | D68: ｲﾝｷｭﾍﾞｰｼｮﾝ事業部 | E68: 中村良一 | F68: ｲﾝｷｭﾍﾞｰｼｮﾝ事業部 | H68: × | T68: × | U68: ｲﾝｷｭﾍﾞｰｼｮﾝ事業部 | V68: ×
A69: SAPインフラ支援 | C69: 小林 一希 | D69: ソーシャルベッティング事業本部/チャリ・ロト事業部/ソリューショングループ/管理チーム | E69: 小林一希
A70: PJ_nd_public | B70: 退職 | C70: × | E70: × | H70: ×
A71: デザイン本部アシスタント共有 | C71: 松崎徳子、土田希望 | D71: デザイン本部/ブランドデザイン室/マネジメントグループ/バックオフィスチーム | E71: 松崎徳子 | F71: デザイン本部/ブランドデザイン室/マネジメントグループ/バックオフィスチーム | G71: 土田希望 | H71: × | T71: デザイン本部/ブランドデザイン室/マネジメントグループ/バックオフィスチーム
A72: プレミアム関連キャンペーン | C72: 山口 太樹 | D72: デジタルエンターテインメントオペレーションズ本部/コトダマン制作部 | E72: 山口太樹
A73: honey | B73: 退職 | C73: 齊藤 優太、桑谷 貴志 | D73: スタースマッシュ事業部 | E73: 齊藤優太 | F73: スタースマッシュ事業部 | G73: 桑谷貴志 | H73: × | T73: × | U73: スタースマッシュ事業部 | V73: ×
A74: 音源 | C74: 早坂 匠、笠島 伸吾 | D74: × | E74: 早坂匠 | F74: デザイン本部/動画クリエイティブ室/クリエイティブサウンドグループ | G74: 笠島伸吾 | H74: × | T74: ×
A75: 部長共有会議 | C75: 木村 弘毅 | D75: 取締役 | E75: 木村弘毅
A76: C社調査 | C76: 船隠 大介、小林 完爾 | D76: 内部監査室(本部格)/内部監査室 | E76: 船隠大介
A77: ﾕｰｻﾞｰｻﾎﾟｰﾄｸﾞﾙｰﾌﾟ | C77: 荒川 司 | D77: みてね事業本部/みてね事業開発部/CSグループ | E77: 荒川司
A78: 人材採用 | C78: 杉村 元規、川原 友希 | D78: 人事本部 | E78: 杉村元規
A79: mixiプレミアムポイントキャンペーン | C79: 渡部 喜正 | D79: Vantageスタジオ/mixi事業部 | E79: 渡部喜正
A80: SWEET_PMI | B80: 退職 | C80: 玉井 賀子 | E80: 玉井賀子 | F80: 無記載 | H80: × | T80: × | V80: ×
A81: AM管理 | B81: 退職 | C81: 平岡 晃 | E81: 平岡晃 | F81: 無記載 | H81: × | T81: × | V81: ×
A82: tech | C82: 横山 義之、曽我 雄二 | D82: デザイン本部 | E82: 横山義之
A83: 株主総会 | C83: 小林 完爾 | D83: 上級執行役員 | E83: 小林完爾
A84: C-039 | C84: 開 光太朗 | D84: 経営推進本部/グループ会社統括支援部 | E84: 開光太朗
A85: 仮想PL | B85: 退職 | C85: 森田潤也 | E85: 森田潤也 | F85: 無記載 | H85: × | T85: × | V85: ×
A86: 労務G | C86: 坂田 信隆a、 中川 真紀子、酒井 優 | D86: 人事本部/労務部 | E86: 坂田信隆a
A87: ＧＫプロジェクト | C87: 間瀬 琴巳 | D87: 開発本部/インフラ室 | E87: 間瀬琴巳
A88: ゲームレポート | C88: 栢木 英行 | D88: Vantageスタジオ/mixi事業部/パートナービジネスグループ | E88: 栢木英行
A89: PC版mixiUIガイドライン策定PJ | C89: 渡部 喜正 | D89: Vantageスタジオ/mixi事業部 | E89: 渡部喜正
A90: j-sox | C90: 小林 完爾、望月 大輔 | D90: 上級執行役員 | E90: 小林完爾
A91: macaron_経理関連 | C91: 鈴木 景子 | D91: デジタルエンターテインメントオペレーションズ本部/モンストIPクリエイション部/キャラプログループ/アート監修チーム | E91: 鈴木景子
A92: soundgroup_databackup | C92: 安井 聡史 | D92: デザイン本部/ブランドデザイン室 | E92: 安井聡史
A93: システム本部からの共有 | B93: 退職 | C93: 渡辺 隆志 | D93: XFLAG事業推進室 | E93: 渡辺隆志 | F93: XFLAG事業推進室 | H93: × | T93: × | U93: XFLAG事業推進室 | V93: ×
A94: スマホアプリ数値管理 | C94: 白岩 優子 | D94: みてね事業本部/みてねマーケティング部/ユーザーコミュニケーショングループ | E94: 白岩優子
A95: 99_作業用テスト | B95: 退職 | C95: × | E95: × | H95: ×
A96: ミクシィリサーチ総務業務 | C96: 長岡 輝 | D96: Vantageスタジオ/Romi事業部/UX企画グループ | E96: 長岡輝
A97: candy | B97: 退職 | C97: 中村良一 | D97: ｲﾝｷｭﾍﾞｰｼｮﾝ事業部 | E97: 中村良一 | F97: ｲﾝｷｭﾍﾞｰｼｮﾝ事業部 | H97: × | T97: × | U97: ｲﾝｷｭﾍﾞｰｼｮﾝ事業部 | V97: ×
A98: 【機密】統括管理本部⇔人事部 | C98: 山本 陽司 | D98: 人事本部/組織戦略部 | E98: 山本陽司
A99: 健全化推進 | C99: 岨中 健太 | D99: Vantageスタジオ/事業推進室 | E99: 岨中健太
A100: 広告運用 | C100: 尾関 芳郎 | D100: みてね事業本部/みてねプラットフォーム部/SREグループ | E100: 尾関芳郎
A101: マネージャー共有 | B101: 退職 | C101: 荻野 泰弘 | D101: × | E101: 荻野泰弘 | F101: × | H101: × | T101: × | U101: × | V101: ×
...

Sheet シート13
A1: アドテクスタジオ | B1: アドテクG
A2: アドテクスタジオ | B2: 企画G
A3: アドテクスタジオ | B3: 開発G
A4: アドテクスタジオ | B4: 室共有
A5: メディア事業本部 | B5: mixiゲーム部
A6: メディア事業本部 | B6: mixiサービス部
A7: メディア事業本部 | B7: 本部共有
A8: メディア事業本部 | B8: mixiコンテンツ部
A9: メディア事業本部 | B9: mixiシステム部
A10: Diverseスタジオ | B10: インドマーケット部
A11: Diverseスタジオ | B11: かいはつ室
A12: Diverseスタジオ | B12: ビジネス推進室
... A278: モンスト事業本部 | B278: 新規事業開発部
A280: 旧本部名 | B280: 旧部署名 | C280: ステータス | D280: 現在の本部/部署名 (予想) | E280: 部室長/室長名 (判明分)
A281: アドテクスタジオ | B281: アドテクG | C281: 廃止/再編 | D281: 開発本部 / デザイン本部 | E281: 不明
A282: アドテクスタジオ | B282: 企画G | C282: 廃止/再編 | D282: 開発本部 / デザイン本部 | E282: 不明
A283: アドテクスタジオ | B283: 開発G | C283: 廃止/再編 | D283: 開発本部 / デザイン本部 | E283: 不明
A284: アドテクスタジオ | B284: 室共有 | C284: 廃止/再編 | D284: - | E284: -
A285: メディア事業本部 | B285: mixiゲーム部 | C285: 廃止/再編 | D285: ゲーム事業部 | E285: 不明
A286: メディア事業本部 | B286: mixiサービス部 | C286: 廃止/再編 | D286: MIXI M事業部 | E286: 不明
A287: メディア事業本部 | B287: 本部共有 | C287: 廃止/再編 | D287: - | E287: -
A288: メディア事業本部 | B288: mixiコンテンツ部 | C288: 廃止/再編 | D288: MIXI M事業部 | E288: 不明
A289: メディア事業本部 | B289: mixiシステム部 | C289: 廃止/再編 | D289: MIXI M事業部 | E289: 不明
A290: Diverseスタジオ | B290: インドマーケット部 | C290: 廃止/分社化 | D290: 株式会社Diverse | E290: 不明
A291: Diverseスタジオ | B291: かいはつ室 | C291: 廃止/分社化 | D291: 株式会社Diverse | E291: 不明
... A558: モンスト事業本部 | B558: 新規事業開発部 | C558: 廃止/再編 | D558: モンスト事業部 | E558: 不明

Sheet 成形について
B3: 0File | C3: 不要そう
B4: 合致 | C4: 管理者が判明
B5: 不明 | C5: 管理者が不明
B6: 仮説 | C6: 組織変更により、現状の組織名と一致しないが、組織名より推測している | H6: 最後
B10: フォルダ名 | C10: 使用の有無 | D10: LastWrightTime | E10: ステータス | F10: 管理者 | G10: 管理者
C11: 0
C12: 300G
D14: ① | E14: ② | F14: ②
A15: 疑問 | G15: メモ
A16: 最初にもらったフォルダの数が合わない →0fileでもなく、最終更新日にも挙がっていないものが対象 | G16: 最終更新日は2020年以前のものをグレーアウト
G17: 最終更新日のシートにないものは、存在しない？
A18: 3年 42
A19: 6年 95 2025～2020
A21: データサイズはファイル数なのか？
A22: フォルダの容量は欲しい ｍｇ～のやつを1024で割って出す logのBytのものにする
A23: 最終更新日でバツがついているもの＝最初にもらったフォルダ一覧に存在しないフォルダは何？
A24: projectの容量を出す
A27: ・新規カラム（移行先）で1列Hot、coldのものを作成
A28: 3年以上更新していないもの＝cold
A30: Hot＝Googleドライブ
A31: cold＝AWS S3
A32: 不要
A33: 個人情報＝別テナント
... A36: 不要、自対応、hatakan依頼

Sheet ヒアリング先
A1: div 対象者 | B1: project 対象者
A2: =IFERROR(__xludf.DUMMYFUNCTION("UNIQUE(FLATTEN('（新）div'!L2:M379))"),"三島 圭介") -> 三島 圭介 | B2: =IFERROR(__xludf.DUMMYFUNCTION("UNIQUE(FLATTEN('（新）project_bk'!E5:E269,'（新）project_bk'!G5:G269,'（新）project_bk'!I5:I269,'（新）project_bk'!K5:K269,'（新）project_bk'!M5:M269,'（新）project_bk'!O5:O269,'（新）project_bk'!S5:S269))"),"山口祥子") -> 山口祥子
A3: =IFERROR(__xludf.DUMMYFUNCTION("""COMPUTED_VALUE"""),"松本 太寛") -> 松本 太寛 | B3: =IFERROR(__xludf.DUMMYFUNCTION("""COMPUTED_VALUE"""),"×") -> ×
A4: =IFERROR(__xludf.DUMMYFUNCTION("""COMPUTED_VALUE"""),"×") -> × | B4: =IFERROR(__xludf.DUMMYFUNCTION("""COMPUTED_VALUE"""),"佐藤僚") -> 佐藤僚
A5: =IFERROR(__xludf.DUMMYFUNCTION("""COMPUTED_VALUE"""),"薮崎 泰一") -> 薮崎 泰一 | B5: =IFERROR(__xludf.DUMMYFUNCTION("""COMPUTED_VALUE"""),"安井聡史") -> 安井聡史
A6: =IFERROR(__xludf.DUMMYFUNCTION("""COMPUTED_VALUE"""),"横山 義之") -> 横山 義之 | B6: =IFERROR(__xludf.DUMMYFUNCTION("""COMPUTED_VALUE"""),"山本陽司") -> 山本陽司
A7: =IFERROR(__xludf.DUMMYFUNCTION("""COMPUTED_VALUE"""),"野原 孝行") -> 野原 孝行 | B7: =IFERROR(__xludf.DUMMYFUNCTION("""COMPUTED_VALUE"""),"楠井大地") -> 楠井大地
A8: =IFERROR(__xludf.DUMMYFUNCTION("""COMPUTED_VALUE"""),"石井 公二") -> 石井 公二 | B8: =IFERROR(__xludf.DUMMYFUNCTION("""COMPUTED_VALUE"""),"佐藤貴亮") -> 佐藤貴亮
A9: =IFERROR(__xludf.DUMMYFUNCTION("""COMPUTED_VALUE"""),"青山 智史") -> 青山 智史 | B9: =IFERROR(__xludf.DUMMYFUNCTION("""COMPUTED_VALUE"""),"島村恒平") -> 島村恒平
A10: =IFERROR(__xludf.DUMMYFUNCTION("""COMPUTED_VALUE"""),"杉村 元規") -> 杉村 元規 | B10: =IFERROR(__xludf.DUMMYFUNCTION("""COMPUTED_VALUE"""),"大田由香") -> 大田由香
A11: =IFERROR(__xludf.DUMMYFUNCTION("""COMPUTED_VALUE"""),"坂田 信隆a") -> 坂田 信隆a | B11: =IFERROR(__xludf.DUMMYFUNCTION("""COMPUTED_VALUE"""),"杉田絵美") -> 杉田絵美
A12: =IFERROR(__xludf.DUMMYFUNCTION("""COMPUTED_VALUE"""),"中川 真紀子") -> 中川 真紀子 | B12: =IFERROR(__xludf.DUMMYFUNCTION("""COMPUTED_VALUE"""),"熊本満里奈") -> 熊本満里奈
A13: =IFERROR(__xludf.DUMMYFUNCTION("""COMPUTED_VALUE"""),"加藤 里紗") -> 加藤 里紗 | B13: =IFERROR(__xludf.DUMMYFUNCTION("""COMPUTED_VALUE"""),"長岡輝") -> 長岡輝
A14: =IFERROR(__xludf.DUMMYFUNCTION("""COMPUTED_VALUE"""),"山本 陽司") -> 山本 陽司 | B14: =IFERROR(__xludf.DUMMYFUNCTION("""COMPUTED_VALUE"""),"安田勇大") -> 安田勇大
A15: =IFERROR(__xludf.DUMMYFUNCTION("""COMPUTED_VALUE"""),"柳本 修平") -> 柳本 修平 | B15: =IFERROR(__xludf.DUMMYFUNCTION("""COMPUTED_VALUE"""),"木村俊也") -> 木村俊也
A16: =IFERROR(__xludf.DUMMYFUNCTION("""COMPUTED_VALUE"""),"井上 慎也") -> 井上 慎也 | B16: =IFERROR(__xludf.DUMMYFUNCTION("""COMPUTED_VALUE"""),"向中野智志") -> 向中野智志
A17: =IFERROR(__xludf.DUMMYFUNCTION("""COMPUTED_VALUE"""),"望月 大輔") -> 望月 大輔 | B17: =IFERROR(__xludf.DUMMYFUNCTION("""COMPUTED_VALUE"""),"菅原亜弓") -> 菅原亜弓
A18: =IFERROR(__xludf.DUMMYFUNCTION("""COMPUTED_VALUE"""),"荒木 豪司") -> 荒木 豪司 | B18: =IFERROR(__xludf.DUMMYFUNCTION("""COMPUTED_VALUE"""),"宇高邦弘") -> 宇高邦弘
A19: =IFERROR(__xludf.DUMMYFUNCTION("""COMPUTED_VALUE"""),"大場 大史") -> 大場 大史 | B19: =IFERROR(__xludf.DUMMYFUNCTION("""COMPUTED_VALUE"""),"西澤明日香") -> 西澤明日香
A20: =IFERROR(__xludf.DUMMYFUNCTION("""COMPUTED_VALUE"""),"宇田川 浩彦") -> 宇田川 浩彦 | B20: =IFERROR(__xludf.DUMMYFUNCTION("""COMPUTED_VALUE"""),"岨中健太") -> 岨中健太
A21: =IFERROR(__xludf.DUMMYFUNCTION("""COMPUTED_VALUE"""),"志々目 孝広") -> 志々目 孝広 | B21: =IFERROR(__xludf.DUMMYFUNCTION("""COMPUTED_VALUE"""),"横山義之") -> 横山義之
A22: =IFERROR(__xludf.DUMMYFUNCTION("""COMPUTED_VALUE"""),"谷 賢史") -> 谷 賢史 | B22: =IFERROR(__xludf.DUMMYFUNCTION("""COMPUTED_VALUE"""),"早川泰彦") -> 早川泰彦
A23: =IFERROR(__xludf.DUMMYFUNCTION("""COMPUTED_VALUE"""),"安井 聡史") -> 安井 聡史 | B23: =IFERROR(__xludf.DUMMYFUNCTION("""COMPUTED_VALUE"""),"小野里浩司") -> 小野里浩司
A24: =IFERROR(__xludf.DUMMYFUNCTION("""COMPUTED_VALUE"""),"越智 純平") -> 越智 純平 | B24: =IFERROR(__xludf.DUMMYFUNCTION("""COMPUTED_VALUE"""),"寺谷祐樹") -> 寺谷祐樹
A25: =IFERROR(__xludf.DUMMYFUNCTION("""COMPUTED_VALUE"""),"大槻 一彦") -> 大槻 一彦 | B25: =IFERROR(__xludf.DUMMYFUNCTION("""COMPUTED_VALUE"""),"櫻井謙士") -> 櫻井謙士
A26: =IFERROR(__xludf.DUMMYFUNCTION("""COMPUTED_VALUE"""),"髙橋 勇太") -> 髙橋 勇太 | B26: =IFERROR(__xludf.DUMMYFUNCTION("""COMPUTED_VALUE"""),"三嶋佳織") -> 三嶋佳織
A27: =IFERROR(__xludf.DUMMYFUNCTION("""COMPUTED_VALUE"""),"岡本 勇太") -> 岡本 勇太 | B27: =IFERROR(__xludf.DUMMYFUNCTION("""COMPUTED_VALUE"""),"新和博") -> 新和博
A28: =IFERROR(__xludf.DUMMYFUNCTION("""COMPUTED_VALUE"""),"吉永 英恵") -> 吉永 英恵 | B28: =IFERROR(__xludf.DUMMYFUNCTION("""COMPUTED_VALUE"""),"加奈山怜") -> 加奈山怜
A29: =IFERROR(__xludf.DUMMYFUNCTION("""COMPUTED_VALUE"""),"照内 大丈") -> 照内 大丈 | B29: =IFERROR(__xludf.DUMMYFUNCTION("""COMPUTED_VALUE"""),"小林誠") -> 小林誠
A30: =IFERROR(__xludf.DUMMYFUNCTION("""COMPUTED_VALUE"""),"砂村 哲平") -> 砂村 哲平 | B30: =IFERROR(__xludf.DUMMYFUNCTION("""COMPUTED_VALUE"""),"玉井賀子") -> 玉井賀子
A31: =IFERROR(__xludf.DUMMYFUNCTION("""COMPUTED_VALUE"""),"吉野 純平") -> 吉野 純平 | B31: =IFERROR(__xludf.DUMMYFUNCTION("""COMPUTED_VALUE"""),"加藤佳代") -> 加藤佳代
B32: =IFERROR(__xludf.DUMMYFUNCTION("""COMPUTED_VALUE"""),"塚田亜希子") -> 塚田亜希子
A33: =IFERROR(__xludf.DUMMYFUNCTION("""COMPUTED_VALUE"""),"小林 家光") -> 小林 家光 | B33: =IFERROR(__xludf.DUMMYFUNCTION("""COMPUTED_VALUE"""),"木村真") -> 木村真
A34: =IFERROR(__xludf.DUMMYFUNCTION("""COMPUTED_VALUE"""),"大崎 敦士") -> 大崎 敦士 | B34: =IFERROR(__xludf.DUMMYFUNCTION("""COMPUTED_VALUE"""),"小林完爾") -> 小林完爾
A35: =IFERROR(__xludf.DUMMYFUNCTION("""COMPUTED_VALUE"""),"川岸 滋也") -> 川岸 滋也 | B35: =IFERROR(__xludf.DUMMYFUNCTION("""COMPUTED_VALUE"""),"石井瞬") -> 石井瞬
A36: =IFERROR(__xludf.DUMMYFUNCTION("""COMPUTED_VALUE"""),"長井 一悟") -> 長井 一悟 | B36: =IFERROR(__xludf.DUMMYFUNCTION("""COMPUTED_VALUE"""),"嵯峨勇") -> 嵯峨勇
A37: =IFERROR(__xludf.DUMMYFUNCTION("""COMPUTED_VALUE"""),"石田 哲久") -> 石田 哲久 | B37: =IFERROR(__xludf.DUMMYFUNCTION("""COMPUTED_VALUE"""),"小林一希") -> 小林一希
A38: =IFERROR(__xludf.DUMMYFUNCTION("""COMPUTED_VALUE"""),"菊池 翔平") -> 菊池 翔平 | B38: =IFERROR(__xludf.DUMMYFUNCTION("""COMPUTED_VALUE"""),"加藤徳英") -> 加藤徳英
A39: =IFERROR(__xludf.DUMMYFUNCTION("""COMPUTED_VALUE"""),"岨中 健太") -> 岨中 健太 | B39: =IFERROR(__xludf.DUMMYFUNCTION("""COMPUTED_VALUE"""),"渡部喜正") -> 渡部喜正
A40: =IFERROR(__xludf.DUMMYFUNCTION("""COMPUTED_VALUE"""),"佐藤 太一") -> 佐藤 太一 | B40: =IFERROR(__xludf.DUMMYFUNCTION("""COMPUTED_VALUE"""),"譚正文") -> 譚正文
A41: =IFERROR(__xludf.DUMMYFUNCTION("""COMPUTED_VALUE"""),"小池 知裕") -> 小池 知裕 | B41: =IFERROR(__xludf.DUMMYFUNCTION("""COMPUTED_VALUE"""),"坂田信隆a") -> 坂田信隆a
A42: =IFERROR(__xludf.DUMMYFUNCTION("""COMPUTED_VALUE"""),"亀山 直生") -> 亀山 直生 | B42: =IFERROR(__xludf.DUMMYFUNCTION("""COMPUTED_VALUE"""),"日下ななみ") -> 日下ななみ
A43: =IFERROR(__xludf.DUMMYFUNCTION("""COMPUTED_VALUE"""),"船隠 大介") -> 船隠 大介 | B43: =IFERROR(__xludf.DUMMYFUNCTION("""COMPUTED_VALUE"""),"石井万祐子") -> 石井万祐子
A44: =IFERROR(__xludf.DUMMYFUNCTION("""COMPUTED_VALUE"""),"中野 康太朗") -> 中野 康太朗 | B44: =IFERROR(__xludf.DUMMYFUNCTION("""COMPUTED_VALUE"""),"武本泰伸") -> 武本泰伸
A45: =IFERROR(__xludf.DUMMYFUNCTION("""COMPUTED_VALUE"""),"横井 速人") -> 横井 速人 | B45: =IFERROR(__xludf.DUMMYFUNCTION("""COMPUTED_VALUE"""),"瀧本晋也") -> 瀧本晋也
A46: =IFERROR(__xludf.DUMMYFUNCTION("""COMPUTED_VALUE"""),"小林 完爾") -> 小林 完爾 | B46: =IFERROR(__xludf.DUMMYFUNCTION("""COMPUTED_VALUE"""),"森本周平") -> 森本周平
A47: =IFERROR(__xludf.DUMMYFUNCTION("""COMPUTED_VALUE"""),"石原 洋輔") -> 石原 洋輔 | B47: =IFERROR(__xludf.DUMMYFUNCTION("""COMPUTED_VALUE"""),"周軼駿") -> 周軼駿
A48: =IFERROR(__xludf.DUMMYFUNCTION("""COMPUTED_VALUE"""),"加藤 翔石") -> 加藤 翔石 | B48: =IFERROR(__xludf.DUMMYFUNCTION("""COMPUTED_VALUE"""),"酒井優") -> 酒井優
A49: =IFERROR(__xludf.DUMMYFUNCTION("""COMPUTED_VALUE"""),"小原 蓉童") -> 小原 蓉童 | B49: =IFERROR(__xludf.DUMMYFUNCTION("""COMPUTED_VALUE"""),"山本忠智香") -> 山本忠智香
A50: =IFERROR(__xludf.DUMMYFUNCTION("""COMPUTED_VALUE"""),"須貝 一貴") -> 須貝 一貴 | B50: =IFERROR(__xludf.DUMMYFUNCTION("""COMPUTED_VALUE"""),"竹井香織") -> 竹井香織
A51: =IFERROR(__xludf.DUMMYFUNCTION("""COMPUTED_VALUE"""),"開 光太朗") -> 開 光太朗 | B51: =IFERROR(__xludf.DUMMYFUNCTION("""COMPUTED_VALUE"""),"栢木英行") -> 栢木英行
A52: =IFERROR(__xludf.DUMMYFUNCTION("""COMPUTED_VALUE"""),"照井 英人") -> 照井 英人 | B52: =IFERROR(__xludf.DUMMYFUNCTION("""COMPUTED_VALUE"""),"長谷川純子") -> 長谷川純子
A53: =IFERROR(__xludf.DUMMYFUNCTION("""COMPUTED_VALUE"""),"渡辺 和宏") -> 渡辺 和宏 | B53: =IFERROR(__xludf.DUMMYFUNCTION("""COMPUTED_VALUE"""),"柳本修平") -> 柳本修平
A54: =IFERROR(__xludf.DUMMYFUNCTION("""COMPUTED_VALUE"""),"竹内 潤") -> 竹内 潤 | B54: =IFERROR(__xludf.DUMMYFUNCTION("""COMPUTED_VALUE"""),"北村奈緒美") -> 北村奈緒美
A55: =IFERROR(__xludf.DUMMYFUNCTION("""COMPUTED_VALUE"""),"貫井 広幸") -> 貫井 広幸 | B55: =IFERROR(__xludf.DUMMYFUNCTION("""COMPUTED_VALUE"""),"根本悠子") -> 根本悠子
A56: =IFERROR(__xludf.DUMMYFUNCTION("""COMPUTED_VALUE"""),"笠原 健治") -> 笠原 健治 | B56: =IFERROR(__xludf.DUMMYFUNCTION("""COMPUTED_VALUE"""),"福森美貴") -> 福森美貴
A57: =IFERROR(__xludf.DUMMYFUNCTION("""COMPUTED_VALUE"""),"清水 勲") -> 清水 勲 | B57: =IFERROR(__xludf.DUMMYFUNCTION("""COMPUTED_VALUE"""),"戸谷栄一") -> 戸谷栄一
A58: =IFERROR(__xludf.DUMMYFUNCTION("""COMPUTED_VALUE"""),"平田 将久a") -> 平田 将久a | B58: =IFERROR(__xludf.DUMMYFUNCTION("""COMPUTED_VALUE"""),"田村征也") -> 田村征也
A59: =IFERROR(__xludf.DUMMYFUNCTION("""COMPUTED_VALUE"""),"渡部 喜正") -> 渡部 喜正 | B59: =IFERROR(__xludf.DUMMYFUNCTION("""COMPUTED_VALUE"""),"中川真紀子") -> 中川真紀子
A60: =IFERROR(__xludf.DUMMYFUNCTION("""COMPUTED_VALUE"""),"佐藤 僚") -> 佐藤 僚 | B60: =IFERROR(__xludf.DUMMYFUNCTION("""COMPUTED_VALUE"""),"石井公二") -> 石井公二
A61: =IFERROR(__xludf.DUMMYFUNCTION("""COMPUTED_VALUE"""),"北村 有吾") -> 北村 有吾 | B61: =IFERROR(__xludf.DUMMYFUNCTION("""COMPUTED_VALUE"""),"安藤希倫") -> 安藤希倫
A62: =IFERROR(__xludf.DUMMYFUNCTION("""COMPUTED_VALUE"""),"杉山 潤") -> 杉山 潤 | B62: =IFERROR(__xludf.DUMMYFUNCTION("""COMPUTED_VALUE"""),"石井訓象") -> 石井訓象
A63: =IFERROR(__xludf.DUMMYFUNCTION("""COMPUTED_VALUE"""),"奥山 翔") -> 奥山 翔 | B63: =IFERROR(__xludf.DUMMYFUNCTION("""COMPUTED_VALUE"""),"佐野直美") -> 佐野直美
A64: =IFERROR(__xludf.DUMMYFUNCTION("""COMPUTED_VALUE"""),"向江 俊和01") -> 向江 俊和01 | B64: =IFERROR(__xludf.DUMMYFUNCTION("""COMPUTED_VALUE"""),"渡辺和宏") -> 渡辺和宏
A65: =IFERROR(__xludf.DUMMYFUNCTION("""COMPUTED_VALUE"""),"馬場 大輝") -> 馬場 大輝 | B65: =IFERROR(__xludf.DUMMYFUNCTION("""COMPUTED_VALUE"""),"成田悟") -> 成田悟
A66: =IFERROR(__xludf.DUMMYFUNCTION("""COMPUTED_VALUE"""),"川又 義照") -> 川又 義照 | B66: =IFERROR(__xludf.DUMMYFUNCTION("""COMPUTED_VALUE"""),"越智純平") -> 越智純平
A67: =IFERROR(__xludf.DUMMYFUNCTION("""COMPUTED_VALUE"""),"岩佐 知則") -> 岩佐 知則 | B67: =IFERROR(__xludf.DUMMYFUNCTION("""COMPUTED_VALUE"""),"八木貴也") -> 八木貴也
A68: =IFERROR(__xludf.DUMMYFUNCTION("""COMPUTED_VALUE"""),"平山 英輝") -> 平山 英輝 | B68: =IFERROR(__xludf.DUMMYFUNCTION("""COMPUTED_VALUE"""),"紅露大輔") -> 紅露大輔
A69: =IFERROR(__xludf.DUMMYFUNCTION("""COMPUTED_VALUE"""),"加藤 徳英") -> 加藤 徳英 | B69: =IFERROR(__xludf.DUMMYFUNCTION("""COMPUTED_VALUE"""),"宮本憲枝") -> 宮本憲枝
A70: =IFERROR(__xludf.DUMMYFUNCTION("""COMPUTED_VALUE"""),"朝倉 文彦") -> 朝倉 文彦 | B70: =IFERROR(__xludf.DUMMYFUNCTION("""COMPUTED_VALUE"""),"砂村哲平") -> 砂村哲平
A71: =IFERROR(__xludf.DUMMYFUNCTION("""COMPUTED_VALUE"""),"宮本 憲枝") -> 宮本 憲枝 | B71: =IFERROR(__xludf.DUMMYFUNCTION("""COMPUTED_VALUE"""),"鈴木景子") -> 鈴木景子
A72: =IFERROR(__xludf.DUMMYFUNCTION("""COMPUTED_VALUE"""),"兼吉 完聡01") -> 兼吉 完聡01 | B72: =IFERROR(__xludf.DUMMYFUNCTION("""COMPUTED_VALUE"""),"髙橋勇太") -> 髙橋勇太
A73: =IFERROR(__xludf.DUMMYFUNCTION("""COMPUTED_VALUE"""),"吉田 聡史") -> 吉田 聡史 | B73: =IFERROR(__xludf.DUMMYFUNCTION("""COMPUTED_VALUE"""),"齋藤敦子") -> 齋藤敦子
B74: =IFERROR(__xludf.DUMMYFUNCTION("""COMPUTED_VALUE"""),"望月大輔") -> 望月大輔
B75: =IFERROR(__xludf.DUMMYFUNCTION("""COMPUTED_VALUE"""),"竹田広平") -> 竹田広平
B76: =IFERROR(__xludf.DUMMYFUNCTION("""COMPUTED_VALUE"""),"田所将") -> 田所将
B77: =IFERROR(__xludf.DUMMYFUNCTION("""COMPUTED_VALUE"""),"今野ひとみ") -> 今野ひとみ
B78: =IFERROR(__xludf.DUMMYFUNCTION("""COMPUTED_VALUE"""),"松崎徳子") -> 松崎徳子
B79: =IFERROR(__xludf.DUMMYFUNCTION("""COMPUTED_VALUE"""),"杉村元規") -> 杉村元規
B80: =IFERROR(__xludf.DUMMYFUNCTION("""COMPUTED_VALUE"""),"中島清貴") -> 中島清貴
B81: =IFERROR(__xludf.DUMMYFUNCTION("""COMPUTED_VALUE"""),"石田哲久") -> 石田哲久
B82: =IFERROR(__xludf.DUMMYFUNCTION("""COMPUTED_VALUE"""),"平山英輝") -> 平山英輝
B83: =IFERROR(__xludf.DUMMYFUNCTION("""COMPUTED_VALUE"""),"泉望") -> 泉望
B84: =IFERROR(__xludf.DUMMYFUNCTION("""COMPUTED_VALUE"""),"比奈本真") -> 比奈本真
B85: =IFERROR(__xludf.DUMMYFUNCTION("""COMPUTED_VALUE"""),"河村勇") -> 河村勇
B86: =IFERROR(__xludf.DUMMYFUNCTION("""COMPUTED_VALUE"""),"蛭川幸太郎") -> 蛭川幸太郎
B87: =IFERROR(__xludf.DUMMYFUNCTION("""COMPUTED_VALUE"""),"卯木源一") -> 卯木源一
B88: =IFERROR(__xludf.DUMMYFUNCTION("""COMPUTED_VALUE"""),"谷賢史") -> 谷賢史
B89: =IFERROR(__xludf.DUMMYFUNCTION("""COMPUTED_VALUE"""),"上野桂子") -> 上野桂子
B90: =IFERROR(__xludf.DUMMYFUNCTION("""COMPUTED_VALUE"""),"澤田祐希") -> 澤田祐希
B91: =IFERROR(__xludf.DUMMYFUNCTION("""COMPUTED_VALUE"""),"原由佳理") -> 原由佳理
B92: =IFERROR(__xludf.DUMMYFUNCTION("""COMPUTED_VALUE"""),"齊藤優太") -> 齊藤優太
B93: =IFERROR(__xludf.DUMMYFUNCTION("""COMPUTED_VALUE"""),"早坂匠") -> 早坂匠
B94: =IFERROR(__xludf.DUMMYFUNCTION("""COMPUTED_VALUE"""),"荒川司") -> 荒川司
B95: =IFERROR(__xludf.DUMMYFUNCTION("""COMPUTED_VALUE"""),"洪嘉優") -> 洪嘉優
B96: =IFERROR(__xludf.DUMMYFUNCTION("""COMPUTED_VALUE"""),"吉村順也") -> 吉村順也
B97: =IFERROR(__xludf.DUMMYFUNCTION("""COMPUTED_VALUE"""),"木下智子") -> 木下智子
B98: =IFERROR(__xludf.DUMMYFUNCTION("""COMPUTED_VALUE"""),"澁谷高広") -> 澁谷高広
B99: =IFERROR(__xludf.DUMMYFUNCTION("""COMPUTED_VALUE"""),"奥田匡彦") -> 奥田匡彦
B100: =IFERROR(__xludf.DUMMYFUNCTION("""COMPUTED_VALUE"""),"太田雅登") -> 太田雅登
...

Sheet div回答シートURL一覧
A1: 確認先氏名 | B1: SpreadsheetのURL | C1: 件数
A2: 松本 太寛 | B2: https://docs.google.com/spreadsheets/d/1nwdJm_GfdQ1mcJ2ioPHTpKfA3jFL6Blrp61iAHbQq-c/edit | C2: 3
A3: 薮崎 泰一 | B3: https://docs.google.com/spreadsheets/d/1UTgk-a5mWckfGHmzn_hf00PInd0E0gt1VwiCmDn6Uuc/edit | C3: 6
A4: 横山 義之 | B4: https://docs.google.com/spreadsheets/d/1_3QaojSh1OFHSnWqh0FLKul75t-aTpo21dF3aIh9tY8/edit | C4: 12
A5: 野原 孝行 | B5: https://docs.google.com/spreadsheets/d/1gK_f1y2An-sgoKBeFe6btEDLSqxQ_2RZg4KRoRMXbqw/edit | C5: 1
A6: div不明 | B6: https://docs.google.com/spreadsheets/d/1dODR5r7IHQs_bBrnoAAFSNDXLRruZN-RMagTfP3qFLk/edit | C6: 39
A7: 三島 圭介 | B7: https://docs.google.com/spreadsheets/d/1cLWKrRc_FAfJGmNFDGTAwVG_SLS1TbFIyBMUouoody0/edit | C7: 27
A8: 坂田 信隆a | B8: https://docs.google.com/spreadsheets/d/19DE5eeNf5sI0lMc68eIG_RaDD1__D-CDnCY2D-hJQOI/edit | C8: 1
A9: 杉村 元規 | B9: https://docs.google.com/spreadsheets/d/1fuiSwtPkqEMOKFjLpSFKPv3fXVsy__MDJUzC_nUk23A/edit | C9: 12
A10: 加藤 里紗 | B10: https://docs.google.com/spreadsheets/d/1w8zBslU49e2rqaezMVBA-oZv6Kg9-sw_uL14ui46wck/edit | C10: 1
A11: 山本 陽司 | B11: https://docs.google.com/spreadsheets/d/1za6ZHPnww1HLwYW674Eds8fg-tIe40_e4AmQHlL0bus/edit | C11: 1
A12: 井上 慎也 | B12: https://docs.google.com/spreadsheets/d/1uxA1q_ItA1ql8CLzdvoi-bSamIO6-cscLDpaMms0Tts/edit | C12: 1
A13: 志々目 孝広 | B13: https://docs.google.com/spreadsheets/d/1ACC2Z-s-EYf4tJg_Vwfqmwgu7nypM_daoXlVfG60ybM/edit | C13: 5
... A44: div確認先を除外 | B44: https://docs.google.com/spreadsheets/d/1DwpFEZ4f8P6Obxtdd6OB5tjjtth5liWQaXvwvNz6r-8/edit | C44: 286

Sheet project回答シートURL一覧
A1: 確認先氏名 | B1: SpreadsheetのURL | C1: 件数
A2: project不明 | B2: https://docs.google.com/spreadsheets/d/1CcjRFBFG7iOiqTD2fTfX3OMgml3WL0QjCSl6NYf1H7Y/edit | C2: 324

Sheet （新）div
A1: div 1階層目フォルダ | B1: div 2階層目フォルダ | C1: ステータス | D1: フォルダ数 | E1: ファイル数 | F1: データ容量GB） | G1: 最終更新日 | H1: 移行先 | I1: 移行方法 | J1: 本部予想 | K1: 部室予想 | L1: 確認先（本部長） | M1: 確認先（部室長） | N1: 現状予測 | O1: 仮説 | P1: LastEditDate
A2: アドテクスタジオ | B2: アドテクG | C2: 0file | D2: =IFERROR(__xludf.DUMMYFUNCTION("XLOOKUP(JOIN(""/"",$A2:$B2),'source merged_div_data'!$A:$A,'source merged_div_data'!B:B)"),4.0) -> 4 | E2: =IFERROR(__xludf.DUMMYFUNCTION("XLOOKUP(JOIN(""/"",$A2:$B2),'source merged_div_data'!$A:$A,'source merged_div_data'!C:C)"),0.0) -> 0 | F2: {=IFERROR( IFS( XLOOKUP(TEXTJOIN("/", TRUE, $A2:$B2), 'source merged_div_data'!$A:$A, 'source merged_div_data'!F:F) < 1024, XLOOKUP(TEXTJOIN("/", TRUE, $A2:$B2), 'source merged_div_data'!$A:$A, 'source merged_div_data'!F:F) & " B", XLOOKUP(TEXTJOIN("/", TRUE, $A2:$B2), 'source merged_div_data'!$A:$A, 'source merged_div_data'!F:F) < 1048576, ROUND(XLOOKUP(TEXTJOIN("/", TRUE, $A2:$B2), 'source merged_div_data'!$A:$A, 'source merged_div_data'!F:F)/1024, 2) & " KB", XLOOKUP(TEXTJOIN("/", TRUE, $A2:$B2), 'source merged_div_data'!$A:$A, 'source merged_div_data'!F:F) < 1073741824, ROUND(XLOOKUP(TEXTJOIN("/", TRUE, $A2:$B2), 'source merged_div_data'!$A:$A, 'source merged_div_data'!F:F)/1048576, 2) & " MB", TRUE, ROUND(XLOOKUP(TEXTJOIN("/", TRUE, $A2:$B2), 'source merged_div_data'!$A:$A, 'source merged_div_data'!F:F)/1073741824, 2) & " GB" ), "×" )} -> 86 B | G2: × | J2: デジタルエンターテインメントオペレーションズ本部 | K2: 宣伝部 | L2: 三島 圭介 | M2: 松本 太寛 | N2: 廃止/再編 | O2: 開発本部 / デザイン本部 | P2: =IFERROR(__xludf.DUMMYFUNCTION("XLOOKUP(JOIN(""/"",$A2:$B2),'source isilon_divまとめ'!$A:$A,'source isilon_divまとめ'!$D:$D,XLOOKUP(JOIN(""\"",$A2:$B2),'source NetApp-file-sv01-div'!A:A,TEXT('source NetApp-file-sv01-div'!C:C,""yyyy/mm/dd"")))"),"#N/A") -> #N/A
A3: アドテクスタジオ | B3: 企画G | C3: 0file | D3: =IFERROR(__xludf.DUMMYFUNCTION("XLOOKUP(JOIN(""/"",$A3:$B3),'source merged_div_data'!$A:$A,'source merged_div_data'!B:B)"),3.0) -> 3 | E3: =IFERROR(__xludf.DUMMYFUNCTION("XLOOKUP(JOIN(""/"",$A3:$B3),'source merged_div_data'!$A:$A,'source merged_div_data'!C:C)"),0.0) -> 0 | F3: {=IFERROR( IFS( XLOOKUP(TEXTJOIN("/", TRUE, $A3:$B3), 'source merged_div_data'!$A:$A, 'source merged_div_data'!F:F) < 1024, XLOOKUP(TEXTJOIN("/", TRUE, $A3:$B3), 'source merged_div_data'!$A:$A, 'source merged_div_data'!F:F) & " B", XLOOKUP(TEXTJOIN("/", TRUE, $A3:$B3), 'source merged_div_data'!$A:$A, 'source merged_div_data'!F:F) < 1048576, ROUND(XLOOKUP(TEXTJOIN("/", TRUE, $A3:$B3), 'source merged_div_data'!$A:$A, 'source merged_div_data'!F:F)/1024, 2) & " KB", XLOOKUP(TEXTJOIN("/", TRUE, $A3:$B3), 'source merged_div_data'!$A:$A, 'source merged_div_data'!F:F) < 1073741824, ROUND(XLOOKUP(TEXTJOIN("/", TRUE, $A3:$B3), 'source merged_div_data'!$A:$A, 'source merged_div_data'!F:F)/1048576, 2) & " MB", TRUE, ROUND(XLOOKUP(TEXTJOIN("/", TRUE, $A3:$B3), 'source merged_div_data'!$A:$A, 'source merged_div_data'!F:F)/1073741824, 2) & " GB" ), "×" )} -> 61 B | G3: × | J3: デジタルエンターテインメントオペレーションズ本部 | K3: 宣伝部 | L3: 三島 圭介 | M3: 松本 太寛 | N3: 廃止/再編 | O3: 開発本部 / デザイン本部 | P3: =IFERROR(__xludf.DUMMYFUNCTION("XLOOKUP(JOIN(""/"",$A3:$B3),'source isilon_divまとめ'!$A:$A,'source isilon_divまとめ'!$D:$D,XLOOKUP(JOIN(""\"",$A3:$B3),'source NetApp-file-sv01-div'!A:A,TEXT('source NetApp-file-sv01-div'!C:C,""yyyy/mm/dd"")))"),"#N/A") -> #N/A
A4: アドテクスタジオ | B4: 開発G | C4: 0file | D4: =IFERROR(__xludf.DUMMYFUNCTION("XLOOKUP(JOIN(""/"",$A4:$B4),'source merged_div_data'!$A:$A,'source merged_div_data'!B:B)"),3.0) -> 3 | E4: =IFERROR(__xludf.DUMMYFUNCTION("XLOOKUP(JOIN(""/"",$A4:$B4),'source merged_div_data'!$A:$A,'source merged_div_data'!C:C)"),0.0) -> 0 | F4: {=IFERROR( IFS( XLOOKUP(TEXTJOIN("/", TRUE, $A4:$B4), 'source merged_div_data'!$A:$A, 'source merged_div_data'!F:F) < 1024, XLOOKUP(TEXTJOIN("/", TRUE, $A4:$B4), 'source merged_div_data'!$A:$A, 'source merged_div_data'!F:F) & " B", XLOOKUP(TEXTJOIN("/", TRUE, $A4:$B4), 'source merged_div_data'!$A:$A, 'source merged_div_data'!F:F) < 1048576, ROUND(XLOOKUP(TEXTJOIN("/", TRUE, $A4:$B4), 'source merged_div_data'!$A:$A, 'source merged_div_data'!F:F)/1024, 2) & " KB", XLOOKUP(TEXTJOIN("/", TRUE, $A4:$B4), 'source merged_div_data'!$A:$A, 'source merged_div_data'!F:F) < 1073741824, ROUND(XLOOKUP(TEXTJOIN("/", TRUE, $A4:$B4), 'source merged_div_data'!$A:$A, 'source merged_div_data'!F:F)/1048576, 2) & " MB", TRUE, ROUND(XLOOKUP(TEXTJOIN("/", TRUE, $A4:$B4), 'source merged_div_data'!$A:$A, 'source merged_div_data'!F:F)/1073741824, 2) & " GB" ), "×" )} -> 61 B | G4: × | J4: デジタルエンターテインメントオペレーションズ本部 | K4: 宣伝部 | L4: 三島 圭介 | M4: 松本 太寛 | N4: 廃止/再編 | O4: 開発本部 / デザイン本部 | P4: =IFERROR(__xludf.DUMMYFUNCTION("XLOOKUP(JOIN(""/"",$A4:$B4),'source isilon_divまとめ'!$A:$A,'source isilon_divまとめ'!$D:$D,XLOOKUP(JOIN(""\"",$A4:$B4),'source NetApp-file-sv01-div'!A:A,TEXT('source NetApp-file-sv01-div'!C:C,""yyyy/mm/dd"")))"),"#N/A") -> #N/A
A5: アドテクスタジオ | B5: 室共有 | C5: 0file | D5: =IFERROR(__xludf.DUMMYFUNCTION("XLOOKUP(JOIN(""/"",$A5:$B5),'source merged_div_data'!$A:$A,'source merged_div_data'!B:B)"),2.0) -> 2 | E5: =IFERROR(__xludf.DUMMYFUNCTION("XLOOKUP(JOIN(""/"",$A5:$B5),'source merged_div_data'!$A:$A,'source merged_div_data'!C:C)"),0.0) -> 0 | F5: {=IFERROR( IFS( XLOOKUP(TEXTJOIN("/", TRUE, $A5:$B5), 'source merged_div_data'!$A:$A, 'source merged_div_data'!F:F) < 1024, XLOOKUP(TEXTJOIN("/", TRUE, $A5:$B5), 'source merged_div_data'!$A:$A, 'source merged_div_data'!F:F) & " B", XLOOKUP(TEXTJOIN("/", TRUE, $A5:$B5), 'source merged_div_data'!$A:$A, 'source merged_div_data'!F:F) < 1048576, ROUND(XLOOKUP(TEXTJOIN("/", TRUE, $A5:$B5), 'source merged_div_data'!$A:$A, 'source merged_div_data'!F:F)/1024, 2) & " KB", XLOOKUP(TEXTJOIN("/", TRUE, $A5:$B5), 'source merged_div_data'!$A:$A, 'source merged_div_data'!F:F) < 1073741824, ROUND(XLOOKUP(TEXTJOIN("/", TRUE, $A5:$B5), 'source merged_div_data'!$A:$A, 'source merged_div_data'!F:F)/1048576, 2) & " MB", TRUE, ROUND(XLOOKUP(TEXTJOIN("/", TRUE, $A5:$B5), 'source merged_div_data'!$A:$A, 'source merged_div_data'!F:F)/1073741824, 2) & " GB" ), "×" )} -> 39 B | G5: × | J5: デジタルエンターテインメントオペレーションズ本部 | K5: 宣伝部 | L5: 三島 圭介 | M5: 松本 太寛 | N5: 廃止/再編 | O5: - | P5: =IFERROR(__xludf.DUMMYFUNCTION("XLOOKUP(JOIN(""/"",$A5:$B5),'source isilon_divまとめ'!$A:$A,'source isilon_divまとめ'!$D:$D,XLOOKUP(JOIN(""\"",$A5:$B5),'source NetApp-file-sv01-div'!A:A,TEXT('source NetApp-file-sv01-div'!C:C,""yyyy/mm/dd"")))"),"#N/A") -> #N/A
A6: メディア事業本部 | B6: mixiゲーム部 | C6: 仮説 | D6: =IFERROR(__xludf.DUMMYFUNCTION("XLOOKUP(JOIN(""/"",$A6:$B6),'source merged_div_data'!$A:$A,'source merged_div_data'!B:B)"),32.0) -> 32 | E6: =IFERROR(__xludf.DUMMYFUNCTION("XLOOKUP(JOIN(""/"",$A6:$B6),'source merged_div_data'!$A:$A,'source merged_div_data'!C:C)"),17.0) -> 17 | F6: {=IFERROR( IFS( XLOOKUP(TEXTJOIN("/", TRUE, $A6:$B6), 'source merged_div_data'!$A:$A, 'source merged_div_data'!F:F) < 1024, XLOOKUP(TEXTJOIN("/", TRUE, $A6:$B6), 'source merged_div_data'!$A:$A, 'source merged_div_data'!F:F) & " B", XLOOKUP(TEXTJOIN("/", TRUE, $A6:$B6), 'source merged_div_data'!$A:$A, 'source merged_div_data'!F:F) < 1048576, ROUND(XLOOKUP(TEXTJOIN("/", TRUE, $A6:$B6), 'source merged_div_data'!$A:$A, 'source merged_div_data'!F:F)/1024, 2) & " KB", XLOOKUP(TEXTJOIN("/", TRUE, $A6:$B6), 'source merged_div_data'!$A:$A, 'source merged_div_data'!F:F) < 1073741824, ROUND(XLOOKUP(TEXTJOIN("/", TRUE, $A6:$B6), 'source merged_div_data'!$A:$A, 'source merged_div_data'!F:F)/1048576, 2) & " MB", TRUE, ROUND(XLOOKUP(TEXTJOIN("/", TRUE, $A6:$B6), 'source merged_div_data'!$A:$A, 'source merged_div_data'!F:F)/1073741824, 2) & " GB" ), "×" )} -> 19.25 MB | G6: 2016/04/20 | H6: AWS S3 | J6: デジタルエンターテインメントオペレーションズ本部 | K6: 宣伝部 | L6: 三島 圭介 | M6: 松本 太寛 | N6: 廃止/再編 | O6: ゲーム事業部 | P6: =IFERROR(__xludf.DUMMYFUNCTION("XLOOKUP(JOIN(""/"",$A6:$B6),'source isilon_divまとめ'!$A:$A,'source isilon_divまとめ'!$D:$D,XLOOKUP(JOIN(""\"",$A6:$B6),'source NetApp-file-sv01-div'!A:A,TEXT('source NetApp-file-sv01-div'!C:C,""yyyy/mm/dd"")))"),"2016/04/20") -> 2016/04/20
A7: メディア事業本部 | B7: mixiサービス部 | C7: 仮説 | D7: =IFERROR(__xludf.DUMMYFUNCTION("XLOOKUP(JOIN(""/"",$A7:$B7),'source merged_div_data'!$A:$A,'source merged_div_data'!B:B)"),55.0) -> 55 | E7: =IFERROR(__xludf.DUMMYFUNCTION("XLOOKUP(JOIN(""/"",$A7:$B7),'source merged_div_data'!$A:$A,'source merged_div_data'!C:C)"),53.0) -> 53 | F7: {=IFERROR( IFS( XLOOKUP(TEXTJOIN("/", TRUE, $A7:$B7), 'source merged_div_data'!$A:$A, 'source merged_div_data'!F:F) < 1024, XLOOKUP(TEXTJOIN("/", TRUE, $A7:$B7), 'source merged_div_data'!$A:$A, 'source merged_div_data'!F:F) & " B", XLOOKUP(TEXTJOIN("/", TRUE, $A7:$B7), 'source merged_div_data'!$A:$A, 'source merged_div_data'!F:F) < 1048576, ROUND(XLOOKUP(TEXTJOIN("/", TRUE, $A7:$B7), 'source merged_div_data'!$A:$A, 'source merged_div_data'!F:F)/1024, 2) & " KB", XLOOKUP(TEXTJOIN("/", TRUE, $A7:$B7), 'source merged_div_data'!$A:$A, 'source merged_div_data'!F:F) < 1073741824, ROUND(XLOOKUP(TEXTJOIN("/", TRUE, $A7:$B7), 'source merged_div_data'!$A:$A, 'source merged_div_data'!F:F)/1048576, 2) & " MB", TRUE, ROUND(XLOOKUP(TEXTJOIN("/", TRUE, $A7:$B7), 'source merged_div_data'!$A:$A, 'source merged_div_data'!F:F)/1073741824, 2) & " GB" ), "×" )} -> 8.61 MB | G7: 2016/03/04 | H7: AWS S3 | J7: 開発本部 | K7: MIXI M 事業部 | L7: × | M7: 薮崎 泰一 | N7: 廃止/再編 | O7: MIXI M事業部 | P7: =IFERROR(__xludf.DUMMYFUNCTION("XLOOKUP(JOIN(""/"",$A7:$B7),'source isilon_divまとめ'!$A:$A,'source isilon_divまとめ'!$D:$D,XLOOKUP(JOIN(""\"",$A7:$B7),'source NetApp-file-sv01-div'!A:A,TEXT('source NetApp-file-sv01-div'!C:C,""yyyy/mm/dd"")))"),"2016/03/04") -> 2016/03/04
A8: メディア事業本部 | B8: 本部共有 | C8: 不明 | D8: =IFERROR(__xludf.DUMMYFUNCTION("XLOOKUP(JOIN(""/"",$A8:$B8),'source merged_div_data'!$A:$A,'source merged_div_data'!B:B)"),1345.0) -> 1345 | E8: =IFERROR(__xludf.DUMMYFUNCTION("XLOOKUP(JOIN(""/"",$A8:$B8),'source merged_div_data'!$A:$A,'source merged_div_data'!C:C)"),9883.0) -> 9883 | F8: {=IFERROR( IFS( XLOOKUP(TEXTJOIN("/", TRUE, $A8:$B8), 'source merged_div_data'!$A:$A, 'source merged_div_data'!F:F) < 1024, XLOOKUP(TEXTJOIN("/", TRUE, $A8:$B8), 'source merged_div_data'!$A:$A, 'source merged_div_data'!F:F) & " B", XLOOKUP(TEXTJOIN("/", TRUE, $A8:$B8), 'source merged_div_data'!$A:$A, 'source merged_div_data'!F:F) < 1048576, ROUND(XLOOKUP(TEXTJOIN("/", TRUE, $A8:$B8), 'source merged_div_data'!$A:$A, 'source merged_div_data'!F:F)/1024, 2) & " KB", XLOOKUP(TEXTJOIN("/", TRUE, $A8:$B8), 'source merged_div_data'!$A:$A, 'source merged_div_data'!F:F) < 1073741824, ROUND(XLOOKUP(TEXTJOIN("/", TRUE, $A8:$B8), 'source merged_div_data'!$A:$A, 'source merged_div_data'!F:F)/1048576, 2) & " MB", TRUE, ROUND(XLOOKUP(TEXTJOIN("/", TRUE, $A8:$B8), 'source merged_div_data'!$A:$A, 'source merged_div_data'!F:F)/1073741824, 2) & " GB" ), "×" )} -> 7.72 GB | G8: 2022/04/16 | H8: AWS S3 | J8: デザイン本部 | L8: 横山 義之 | M8: × | N8: 廃止/再編 | O8: - | P8: =IFERROR(__xludf.DUMMYFUNCTION("XLOOKUP(JOIN(""/"",$A8:$B8),'source isilon_divまとめ'!$A:$A,'source isilon_divまとめ'!$D:$D,XLOOKUP(JOIN(""\"",$A8:$B8),'source NetApp-file-sv01-div'!A:A,TEXT('source NetApp-file-sv01-div'!C:C,""yyyy/mm/dd"")))"),"2022/04/16") -> 2022/04/16
A9: メディア事業本部 | B9: mixiコンテンツ部 | C9: 0file | D9: =IFERROR(__xludf.DUMMYFUNCTION("XLOOKUP(JOIN(""/"",$A9:$B9),'source merged_div_data'!$A:$A,'source merged_div_data'!B:B)"),29.0) -> 29 | E9: =IFERROR(__xludf.DUMMYFUNCTION("XLOOKUP(JOIN(""/"",$A9:$B9),'source merged_div_data'!$A:$A,'source merged_div_data'!C:C)"),0.0) -> 0 | F9: {=IFERROR( IFS( XLOOKUP(TEXTJOIN("/", TRUE, $A9:$B9), 'source merged_div_data'!$A:$A, 'source merged_div_data'!F:F) < 1024, XLOOKUP(TEXTJOIN("/", TRUE, $A9:$B9), 'source merged_div_data'!$A:$A, 'source merged_div_data'!F:F) & " B", XLOOKUP(TEXTJOIN("/", TRUE, $A9:$B9), 'source merged_div_data'!$A:$A, 'source merged_div_data'!F:F) < 1048576, ROUND(XLOOKUP(TEXTJOIN("/", TRUE, $A9:$B9), 'source merged_div_data'!$A:$A, 'source merged_div_data'!F:F)/1024, 2) & " KB", XLOOKUP(TEXTJOIN("/", TRUE, $A9:$B9), 'source merged_div_data'!$A:$A, 'source merged_div_data'!F:F) < 1073741824, ROUND(XLOOKUP(TEXTJOIN("/", TRUE, $A9:$B9), 'source merged_div_data'!$A:$A, 'source merged_div_data'!F:F)/1048576, 2) & " MB", TRUE, ROUND(XLOOKUP(TEXTJOIN("/", TRUE, $A9:$B9), 'source merged_div_data'!$A:$A, 'source merged_div_data'!F:F)/1073741824, 2) & " GB" ), "×" )} -> 868 B | G9: × | J9: 開発本部 | K9: MIXI M 事業部 | L9: × | M9: 薮崎 泰一 | N9: 廃止/再編 | O9: MIXI M事業部 | P9: =IFERROR(__xludf.DUMMYFUNCTION("XLOOKUP(JOIN(""/"",$A9:$B9),'source isilon_divまとめ'!$A:$A,'source isilon_divまとめ'!$D:$D,XLOOKUP(JOIN(""\"",$A9:$B9),'source NetApp-file-sv01-div'!A:A,TEXT('source NetApp-file-sv01-div'!C:C,""yyyy/mm/dd"")))"),"#N/A") -> #N/A
A10: メディア事業本部 | B10: mixiシステム部 | C10: 仮説 | D10: =IFERROR(__xludf.DUMMYFUNCTION("XLOOKUP(JOIN(""/"",$A10:$B10),'source merged_div_data'!$A:$A,'source merged_div_data'!B:B)"),19.0) -> 19 | E10: =IFERROR(__xludf.DUMMYFUNCTION("XLOOKUP(JOIN(""/"",$A10:$B10),'source merged_div_data'!$A:$A,'source merged_div_data'!C:C)"),19.0) -> 19 | F10: {=IFERROR( IFS( XLOOKUP(TEXTJOIN("/", TRUE, $A10:$B10), 'source merged_div_data'!$A:$A, 'source merged_div_data'!F:F) < 1024, XLOOKUP(TEXTJOIN("/", TRUE, $A10:$B10), 'source merged_div_data'!$A:$A, 'source merged_div_data'!F:F) & " B", XLOOKUP(TEXTJOIN("/", TRUE, $A10:$B10), 'source merged_div_data'!$A:$A, 'source merged_div_data'!F:F) < 1048576, ROUND(XLOOKUP(TEXTJOIN("/", TRUE, $A10:$B10), 'source merged_div_data'!$A:$A, 'source merged_div_data'!F:F)/1024, 2) & " KB", XLOOKUP(TEXTJOIN("/", TRUE, $A10:$B10), 'source merged_div_data'!$A:$A, 'source merged_div_data'!F:F) < 1073741824, ROUND(XLOOKUP(TEXTJOIN("/", TRUE, $A10:$B10), 'source merged_div_data'!$A:$A, 'source merged_div_data'!F:F)/1048576, 2) & " MB", TRUE, ROUND(XLOOKUP(TEXTJOIN("/", TRUE, $A10:$B10), 'source merged_div_data'!$A:$A, 'source merged_div_data'!F:F)/1073741824, 2) & " GB" ), "×" )} -> 29.29 MB | G10: 2016/05/19 | H10: AWS S3 | J10: 開発本部 | K10: MIXI M 事業部 | L10: × | M10: 薮崎 泰一 | N10: 廃止/再編 | O10: MIXI M事業部 | P10: =IFERROR(__xludf.DUMMYFUNCTION("XLOOKUP(JOIN(""/"",$A10:$B10),'source isilon_divまとめ'!$A:$A,'source isilon_divまとめ'!$D:$D,XLOOKUP(JOIN(""\"",$A10:$B10),'source NetApp-file-sv01-div'!A:A,TEXT('source NetApp-file-sv01-div'!C:C,""yyyy/mm/dd"")))"),"2016/05/19") -> 2016/05/19
A11: Diverseスタジオ | B11: インドマーケット部 | C11: 不明 | D11: =IFERROR(__xludf.DUMMYFUNCTION("XLOOKUP(JOIN(""/"",$A11:$B11),'source merged_div_data'!$A:$A,'source merged_div_data'!B:B)"),4.0) -> 4 | E11: =IFERROR(__xludf.DUMMYFUNCTION("XLOOKUP(JOIN(""/"",$A11:$B11),'source merged_div_data'!$A:$A,'source merged_div_data'!C:C)"),0.0) -> 0 | F11: {=IFERROR( IFS( XLOOKUP(TEXTJOIN("/", TRUE, $A11:$B11), 'source merged_div_data'!$A:$A, 'source merged_div_data'!F:F) < 1024, XLOOKUP(TEXTJOIN("/", TRUE, $A11:$B11), 'source merged_div_data'!$A:$A, 'source merged_div_data'!F:F) & " B", XLOOKUP(TEXTJOIN("/", TRUE, $A11:$B11), 'source merged_div_data'!$A:$A, 'source merged_div_data'!F:F) < 1048576, ROUND(XLOOKUP(TEXTJOIN("/", TRUE, $A11:$B11), 'source merged_div_data'!$A:$A, 'source merged_div_data'!F:F)/1024, 2) & " KB", XLOOKUP(TEXTJOIN("/", TRUE, $A11:$B11), 'source merged_div_data'!$A:$A, 'source merged_div_data'!F:F) < 1073741824, ROUND(XLOOKUP(TEXTJOIN("/", TRUE, $A11:$B11), 'source merged_div_data'!$A:$A, 'source merged_div_data'!F:F)/1048576, 2) & " MB", TRUE, ROUND(XLOOKUP(TEXTJOIN("/", TRUE, $A11:$B11), 'source merged_div_data'!$A:$A, 'source merged_div_data'!F:F)/1073741824, 2) & " GB" ), "×" )} -> 106 B | G11: × | J11: 株式会社Diverse | L11: × | M11: × | N11: 廃止/分社化 | O11: 株式会社Diverse | P11: =IFERROR(__xludf.DUMMYFUNCTION("XLOOKUP(JOIN(""/"",$A11:$B11),'source isilon_divまとめ'!$A:$A,'source isilon_divまとめ'!$D:$D,XLOOKUP(JOIN(""\"",$A11:$B11),'source NetApp-file-sv01-div'!A:A,TEXT('source NetApp-file-sv01-div'!C:C,""yyyy/mm/dd"")))"),"#N/A") -> #N/A
A12: Diverseスタジオ | B12: かいはつ室 | C12: 不明 | D12: =IFERROR(__xludf.DUMMYFUNCTION("XLOOKUP(JOIN(""/"",$A12:$B12),'source merged_div_data'!$A:$A,'source merged_div_data'!B:B)"),2.0) -> 2 | E12: =IFERROR(__xludf.DUMMYFUNCTION("XLOOKUP(JOIN(""/"",$A12:$B12),'source merged_div_data'!$A:$A,'source merged_div_data'!C:C)"),0.0) -> 0 | F12: {=IFERROR( IFS( XLOOKUP(TEXTJOIN("/", TRUE, $A12:$B12), 'source merged_div_data'!$A:$A, 'source merged_div_data'!F:F) < 1024, XLOOKUP(TEXTJOIN("/", TRUE, $A12:$B12), 'source merged_div_data'!$A:$A, 'source merged_div_data'!F:F) & " B", XLOOKUP(TEXTJOIN("/", TRUE, $A12:$B12), 'source merged_div_data'!$A:$A, 'source merged_div_data'!F:F) < 1048576, ROUND(XLOOKUP(TEXTJOIN("/", TRUE, $A12:$B12), 'source merged_div_data'!$A:$A, 'source merged_div_data'!F:F)/1024, 2) & " KB", XLOOKUP(TEXTJOIN("/", TRUE, $A12:$B12), 'source merged_div_data'!$A:$A, 'source merged_div_data'!F:F) < 1073741824, ROUND(XLOOKUP(TEXTJOIN("/", TRUE, $A12:$B12), 'source merged_div_data'!$A:$A, 'source merged_div_data'!F:F)/1048576, 2) & " MB", TRUE, ROUND(XLOOKUP(TEXTJOIN("/", TRUE, $A12:$B12), 'source merged_div_data'!$A:$A, 'source merged_div_data'!F:F)/1073741824, 2) & " GB" ), "×" )} -> 27 B | G12: × | J12: 株式会社Diverse | L12: × | M12: × | N12: 廃止/分社化 | O12: 株式会社Diverse | P12: =IFERROR(__xludf.DUMMYFUNCTION("XLOOKUP(JOIN(""/"",$A12:$B12),'source isilon_divまとめ'!$A:$A,'source isilon_divまとめ'!$D:$D,XLOOKUP(JOIN(""\"",$A12:$B12),'source NetApp-file-sv01-div'!A:A,TEXT('source NetApp-file-sv01-div'!C:C,""yyyy/mm/dd"")))"),"#N/A") -> #N/A
A13: Diverseスタジオ | B13: ビジネス推進室 | C13: 不明 | D13: =IFERROR(__xludf.DUMMYFUNCTION("XLOOKUP(JOIN(""/"",$A13:$B13),'source merged_div_data'!$A:$A,'source merged_div_data'!B:B)"),2.0) -> 2 | E13: =IFERROR(__xludf.DUMMYFUNCTION("XLOOKUP(JOIN(""/"",$A13:$B13),'source merged_div_data'!$A:$A,'source merged_div_data'!C:C)"),0.0) -> 0 | F13: {=IFERROR( IFS( XLOOKUP(TEXTJOIN("/", TRUE, $A13:$B13), 'source merged_div_data'!$A:$A, 'source merged_div_data'!F:F) < 1024, XLOOKUP(TEXTJOIN("/", TRUE, $A13:$B13), 'source merged_div_data'!$A:$A, 'source merged_div_data'!F:F) & " B", XLOOKUP(TEXTJOIN("/", TRUE, $A13:$B13), 'source merged_div_data'!$A:$A, 'source merged_div_data'!F:F) < 1048576, ROUND(XLOOKUP(TEXTJOIN("/", TRUE, $A13:$B13), 'source merged_div_data'!$A:$A, 'source merged_div_data'!F:F)/1024, 2) & " KB", XLOOKUP(TEXTJOIN("/", TRUE, $A13:$B13), 'source merged_div_data'!$A:$A, 'source merged_div_data'!F:F) < 1073741824, ROUND(XLOOKUP(TEXTJOIN("/", TRUE, $A13:$B13), 'source merged_div_data'!$A:$A, 'source merged_div_data'!F:F)/1048576, 2) & " MB", TRUE, ROUND(XLOOKUP(TEXTJOIN("/", TRUE, $A13:$B13), 'source merged_div_data'!$A:$A, 'source merged_div_data'!F:F)/1073741824, 2) & " GB" ), "×" )} -> 27 B | G13: × | J13: 株式会社Diverse | L13: × | M13: × | N13: 廃止/分社化 | O13: 株式会社Diverse | P13: =IFERROR(__xludf.DUMMYFUNCTION("XLOOKUP(JOIN(""/"",$A13:$B13),'source isilon_divまとめ'!$A:$A,'source isilon_divまとめ'!$D:$D,XLOOKUP(JOIN(""\"",$A13:$B13),'source NetApp-file-sv01-div'!A:A,TEXT('source NetApp-file-sv01-div'!C:C,""yyyy/mm/dd"")))"),"#N/A") -> #N/A
A14: Diverseスタジオ | B14: マーケティング室 | C14: 不明 | D14: =IFERROR(__xludf.DUMMYFUNCTION("XLOOKUP(JOIN(""/"",$A14:$B14),'source merged_div_data'!$A:$A,'source merged_div_data'!B:B)"),10.0) -> 10 | E14: =IFERROR(__xludf.DUMMYFUNCTION("XLOOKUP(JOIN(""/"",$A14:$B14),'source merged_div_data'!$A:$A,'source merged_div_data'!C:C)"),0.0) -> 0 | F14: {=IFERROR( IFS( XLOOKUP(TEXTJOIN("/", TRUE, $A14:$B14), 'source merged_div_data'!$A:$A, 'source merged_div_data'!F:F) < 1024, XLOOKUP(TEXTJOIN("/", TRUE, $A14:$B14), 'source merged_div_data'!$A:$A, 'source merged_div_data'!F:F) & " B", XLOOKUP(TEXTJOIN("/", TRUE, $A14:$B14), 'source merged_div_data'!$A:$A, 'source merged_div_data'!F:F) < 1048576, ROUND(XLOOKUP(TEXTJOIN("/", TRUE, $A14:$B14), 'source merged_div_data'!$A:$A, 'source merged_div_data'!F:F)/1024, 2) & " KB", XLOOKUP(TEXTJOIN("/", TRUE, $A14:$B14), 'source merged_div_data'!$A:$A, 'source merged_div_data'!F:F) < 1073741824, ROUND(XLOOKUP(TEXTJOIN("/", TRUE, $A14:$B14), 'source merged_div_data'!$A:$A, 'source merged_div_data'!F:F)/1048576, 2) & " MB", TRUE, ROUND(XLOOKUP(TEXTJOIN("/", TRUE, $A14:$B14), 'source merged_div_data'!$A:$A, 'source merged_div_data'!F:F)/1073741824, 2) & " GB" ), "×" )} -> 288 B | G14: × | J14: 株式会社Diverse | L14: × | M14: × | N14: 廃止/分社化 | O14: 株式会社Diverse | P14: =IFERROR(__xludf.DUMMYFUNCTION("XLOOKUP(JOIN(""/"",$A14:$B14),'source isilon_divまとめ'!$A:$A,'source isilon_divまとめ'!$D:$D,XLOOKUP(JOIN(""\"",$A14:$B14),'source NetApp-file-sv01-div'!A:A,TEXT('source NetApp-file-sv01-div'!C:C,""yyyy/mm/dd"")))"),"#N/A") -> #N/A
A15: Diverseスタジオ | B15: Poiboy事業部 | C15: 不明 | D15: =IFERROR(__xludf.DUMMYFUNCTION("XLOOKUP(JOIN(""/"",$A15:$B15),'source merged_div_data'!$A:$A,'source merged_div_data'!B:B)"),4.0) -> 4 | E15: =IFERROR(__xludf.DUMMYFUNCTION("XLOOKUP(JOIN(""/"",$A15:$B15),'source merged_div_data'!$A:$A,'source merged_div_data'!C:C)"),0.0) -> 0 | F15: {=IFERROR( IFS( XLOOKUP(TEXTJOIN("/", TRUE, $A15:$B15), 'source merged_div_data'!$A:$A, 'source merged_div_data'!F:F) < 1024, XLOOKUP(TEXTJOIN("/", TRUE, $A15:$B15), 'source merged_div_data'!$A:$A, 'source merged_div_data'!F:F) & " B", XLOOKUP(TEXTJOIN("/", TRUE, $A15:$B15), 'source merged_div_data'!$A:$A, 'source merged_div_data'!F:F) < 1048576, ROUND(XLOOKUP(TEXTJOIN("/", TRUE, $A15:$B15), 'source merged_div_data'!$A:$A, 'source merged_div_data'!F:F)/1024, 2) & " KB", XLOOKUP(TEXTJOIN("/", TRUE, $A15:$B15), 'source merged_div_data'!$A:$A, 'source merged_div_data'!F:F) < 1073741824, ROUND(XLOOKUP(TEXTJOIN("/", TRUE, $A15:$B15), 'source merged_div_data'!$A:$A, 'source merged_div_data'!F:F)/1048576, 2) & " MB", TRUE, ROUND(XLOOKUP(TEXTJOIN("/", TRUE, $A15:$B15), 'source merged_div_data'!$A:$A, 'source merged_div_data'!F:F)/1073741824, 2) & " GB" ), "×" )} -> 88 B | G15: × | J15: 株式会社Diverse | L15: × | M15: × | N15: 廃止/分社化 | O15: 株式会社Diverse | P15: =IFERROR(__xludf.DUMMYFUNCTION("XLOOKUP(JOIN(""/"",$A15:$B15),'source isilon_divまとめ'!$A:$A,'source isilon_divまとめ'!$D:$D,XLOOKUP(JOIN(""\"",$A15:$B15),'source NetApp-file-sv01-div'!A:A,TEXT('source NetApp-file-sv01-div'!C:C,""yyyy/mm/dd"")))"),"#N/A") -> #N/A
A16: Diverseスタジオ | B16: 経営管理部 | C16: 仮説 | D16: =IFERROR(__xludf.DUMMYFUNCTION("XLOOKUP(JOIN(""/"",$A16:$B16),'source merged_div_data'!$A:$A,'source merged_div_data'!B:B)"),4342.0) -> 4342 | E16: =IFERROR(__xludf.DUMMYFUNCTION("XLOOKUP(JOIN(""/"",$A16:$B16),'source merged_div_data'!$A:$A,'source merged_div_data'!C:C)"),26544.0) -> 26544 | F16: {=IFERROR( IFS( XLOOKUP(TEXTJOIN("/", TRUE, $A16:$B16), 'source merged_div_data'!$A:$A, 'source merged_div_data'!F:F) < 1024, XLOOKUP(TEXTJOIN("/", TRUE, $A16:$B16), 'source merged_div_data'!$A:$A, 'source merged_div_data'!F:F) & " B", XLOOKUP(TEXTJOIN("/", TRUE, $A16:$B16), 'source merged_div_data'!$A:$A, 'source merged_div_data'!F:F) < 1048576, ROUND(XLOOKUP(TEXTJOIN("/", TRUE, $A16:$B16), 'source merged_div_data'!$A:$A, 'source merged_div_data'!F:F)/1024, 2) & " KB", XLOOKUP(TEXTJOIN("/", TRUE, $A16:$B16), 'source merged_div_data'!$A:$A, 'source merged_div_data'!F:F) < 1073741824, ROUND(XLOOKUP(TEXTJOIN("/", TRUE, $A16:$B16), 'source merged_div_data'!$A:$A, 'source merged_div_data'!F:F)/1048576, 2) & " MB", TRUE, ROUND(XLOOKUP(TEXTJOIN("/", TRUE, $A16:$B16), 'source merged_div_data'!$A:$A, 'source merged_div_data'!F:F)/1073741824, 2) & " GB" ), "×" )} -> 24.1 GB | G16: 2019/03/12 | H16: AWS S3 | J16: 経営管理本部 | K16: 経営管理部 | L16: 野原 孝行 | M16: × | P16: =IFERROR(__xludf.DUMMYFUNCTION("XLOOKUP(JOIN(""/"",$A16:$B16),'source isilon_divまとめ'!$A:$A,'source isilon_divまとめ'!$D:$D,XLOOKUP(JOIN(""\"",$A16:$B16),'source NetApp-file-sv01-div'!A:A,TEXT('source NetApp-file-sv01-div'!C:C,""yyyy/mm/dd"")))"),"2019/03/12") -> 2019/03/12
A17: Diverseスタジオ | B17: 結婚支援事業部 | C17: 不明 | D17: =IFERROR(__xludf.DUMMYFUNCTION("XLOOKUP(JOIN(""/"",$A17:$B17),'source merged_div_data'!$A:$A,'source merged_div_data'!B:B)"),13.0) -> 13 | E17: =IFERROR(__xludf.DUMMYFUNCTION("XLOOKUP(JOIN(""/"",$A17:$B17),'source merged_div_data'!$A:$A,'source merged_div_data'!C:C)"),0.0) -> 0 | F17: {=IFERROR( IFS( XLOOKUP(TEXTJOIN("/", TRUE, $A17:$B17), 'source merged_div_data'!$A:$A, 'source merged_div_data'!F:F) < 1024, XLOOKUP(TEXTJOIN("/", TRUE, $A17:$B17), 'source merged_div_data'!$A:$A, 'source merged_div_data'!F:F) & " B", XLOOKUP(TEXTJOIN("/", TRUE, $A17:$B17), 'source merged_div_data'!$A:$A, 'source merged_div_data'!F:F) < 1048576, ROUND(XLOOKUP(TEXTJOIN("/", TRUE, $A17:$B17), 'source merged_div_data'!$A:$A, 'source merged_div_data'!F:F)/1024, 2) & " KB", XLOOKUP(TEXTJOIN("/", TRUE, $A17:$B17), 'source merged_div_data'!$A:$A, 'source merged_div_data'!F:F) < 1073741824, ROUND(XLOOKUP(TEXTJOIN("/", TRUE, $A17:$B17), 'source merged_div_data'!$A:$A, 'source merged_div_data'!F:F)/1048576, 2) & " MB", TRUE, ROUND(XLOOKUP(TEXTJOIN("/", TRUE, $A17:$B17), 'source merged_div_data'!$A:$A, 'source merged_div_data'!F:F)/1073741824, 2) & " GB" ), "×" )} -> 372 B | G17: × | J17: 株式会社Diverse | L17: × | M17: × | N17: 廃止/分社化 | O17: 株式会社Diverse | P17: =IFERROR(__xludf.DUMMYFUNCTION("XLOOKUP(JOIN(""/"",$A17:$B17),'source isilon_divまとめ'!$A:$A,'source isilon_divまとめ'!$D:$D,XLOOKUP(JOIN(""\"",$A17:$B17),'source NetApp-file-sv01-div'!A:A,TEXT('source NetApp-file-sv01-div'!C:C,""yyyy/mm/dd"")))"),"#N/A") -> #N/A
A18: Diverseスタジオ | B18: 新規サービス事業部 | C18: 不明 | D18: =IFERROR(__xludf.DUMMYFUNCTION("XLOOKUP(JOIN(""/"",$A18:$B18),'source merged_div_data'!$A:$A,'source merged_div_data'!B:B)"),6.0) -> 6 | E18: =IFERROR(__xludf.DUMMYFUNCTION("XLOOKUP(JOIN(""/"",$A18:$B18),'source merged_div_data'!$A:$A,'source merged_div_data'!C:C)"),0.0) -> 0 | F18: {=IFERROR( IFS( XLOOKUP(TEXTJOIN("/", TRUE, $A18:$B18), 'source merged_div_data'!$A:$A, 'source merged_div_data'!F:F) < 1024, XLOOKUP(TEXTJOIN("/", TRUE, $A18:$B18), 'source merged_div_data'!$A:$A, 'source merged_div_data'!F:F) & " B", XLOOKUP(TEXTJOIN("/", TRUE, $A18:$B18), 'source merged_div_data'!$A:$A, 'source merged_div_data'!F:F) < 1048576, ROUND(XLOOKUP(TEXTJOIN("/", TRUE, $A18:$B18), 'source merged_div_data'!$A:$A, 'source merged_div_data'!F:F)/1024, 2) & " KB", XLOOKUP(TEXTJOIN("/", TRUE, $A18:$B18), 'source merged_div_data'!$A:$A, 'source merged_div_data'!F:F) < 1073741824, ROUND(XLOOKUP(TEXTJOIN("/", TRUE, $A18:$B18), 'source merged_div_data'!$A:$A, 'source merged_div_data'!F:F)/1048576, 2) & " MB", TRUE, ROUND(XLOOKUP(TEXTJOIN("/", TRUE, $A18:$B18), 'source merged_div_data'!$A:$A, 'source merged_div_data'!F:F)/1073741824, 2) & " GB" ), "×" )} -> 148 B | G18: × | J18: 株式会社Diverse | L18: × | M18: × | N18: 廃止/分社化 | O18: 株式会社Diverse | P18: =IFERROR(__xludf.DUMMYFUNCTION("XLOOKUP(JOIN(""/"",$A18:$B18),'source isilon_divまとめ'!$A:$A,'source isilon_divまとめ'!$D:$D,XLOOKUP(JOIN(""\"",$A18:$B18),'source NetApp-file-sv01-div'!A:A,TEXT('source NetApp-file-sv01-div'!C:C,""yyyy/mm/dd"")))"),"#N/A") -> #N/A
A19: Diverseスタジオ | B19: youbride事業部 | C19: 不明 | D19: =IFERROR(__xludf.DUMMYFUNCTION("XLOOKUP(JOIN(""/"",$A19:$B19),'source merged_div_data'!$A:$A,'source merged_div_data'!B:B)"),4.0) -> 4 | E19: =IFERROR(__xludf.DUMMYFUNCTION("XLOOKUP(JOIN(""/"",$A19:$B19),'source merged_div_data'!$A:$A,'source merged_div_data'!C:C)"),0.0) -> 0 | F19: {=IFERROR( IFS( XLOOKUP(TEXTJOIN("/", TRUE, $A19:$B19), 'source merged_div_data'!$A:$A, 'source merged_div_data'!F:F) < 1024, XLOOKUP(TEXTJOIN("/", TRUE, $A19:$B19), 'source merged_div_data'!$A:$A, 'source merged_div_data'!F:F) & " B", XLOOKUP(TEXTJOIN("/", TRUE, $A19:$B19), 'source merged_div_data'!$A:$A, 'source merged_div_data'!F:F) < 1048576, ROUND(XLOOKUP(TEXTJOIN("/", TRUE, $A19:$B19), 'source merged_div_data'!$A:$A, 'source merged_div_data'!F:F)/1024, 2) & " KB", XLOOKUP(TEXTJOIN("/", TRUE, $A19:$B19), 'source merged_div_data'!$A:$A, 'source merged_div_data'!F:F) < 1073741824, ROUND(XLOOKUP(TEXTJOIN("/", TRUE, $A19:$B19), 'source merged_div_data'!$A:$A, 'source merged_div_data'!F:F)/1048576, 2) & " MB", TRUE, ROUND(XLOOKUP(TEXTJOIN("/", TRUE, $A19:$B19), 'source merged_div_data'!$A:$A, 'source merged_div_data'!F:F)/1073741824, 2) & " GB" ), "×" )} -> 90 B | G19: × | J19: 株式会社Diverse | L19: × | M19: × | N19: 廃止/分社化 | O19: 株式会社Diverse | P19: =IFERROR(__xludf.DUMMYFUNCTION("XLOOKUP(JOIN(""/"",$A19:$B19),'source isilon_divまとめ'!$A:$A,'source isilon_divまとめ'!$D:$D,XLOOKUP(JOIN(""\"",$A19:$B19),'source NetApp-file-sv01-div'!A:A,TEXT('source NetApp-file-sv01-div'!C:C,""yyyy/mm/dd"")))"),"#N/A") -> #N/A
A20: Diverseスタジオ | B20: 健全化推進室 | C20: 不明 | D20: =IFERROR(__xludf.DUMMYFUNCTION("XLOOKUP(JOIN(""/"",$A20:$B20),'source merged_div_data'!$A:$A,'source merged_div_data'!B:B)"),2.0) -> 2 | E20: =IFERROR(__xludf.DUMMYFUNCTION("XLOOKUP(JOIN(""/"",$A20:$B20),'source merged_div_data'!$A:$A,'source merged_div_data'!C:C)"),0.0) -> 0 | F20: {=IFERROR( IFS( XLOOKUP(TEXTJOIN("/", TRUE, $A20:$B20), 'source merged_div_data'!$A:$A, 'source merged_div_data'!F:F) < 1024, XLOOKUP(TEXTJOIN("/", TRUE, $A20:$B20), 'source merged_div_data'!$A:$A, 'source merged_div_data'!F:F) & " B", XLOOKUP(TEXTJOIN("/", TRUE, $A20:$B20), 'source merged_div_data'!$A:$A, 'source merged_div_data'!F:F) < 1048576, ROUND(XLOOKUP(TEXTJOIN("/", TRUE, $A20:$B20), 'source merged_div_data'!$A:$A, 'source merged_div_data'!F:F)/1024, 2) & " KB", XLOOKUP(TEXTJOIN("/", TRUE, $A20:$B20), 'source merged_div_data'!$A:$A, 'source merged_div_data'!F:F) < 1073741824, ROUND(XLOOKUP(TEXTJOIN("/", TRUE, $A20:$B20), 'source merged_div_data'!$A:$A, 'source merged_div_data'!F:F)/1048576, 2) & " MB", TRUE, ROUND(XLOOKUP(TEXTJOIN("/", TRUE, $A20:$B20), 'source merged_div_data'!$A:$A, 'source merged_div_data'!F:F)/1073741824, 2) & " GB" ), "×" )} -> 27 B | G20: × | J20: 株式会社Diverse | L20: × | M20: × | N20: 廃止/分社化 | O20: 株式会社Diverse | P20: =IFERROR(__xludf.DUMMYFUNCTION("XLOOKUP(JOIN(""/"",$A20:$B20),'source isilon_divまとめ'!$A:$A,'source isilon_divまとめ'!$D:$D,XLOOKUP(JOIN(""\"",$A20:$B20),'source NetApp-file-sv01-div'!A:A,TEXT('source NetApp-file-sv01-div'!C:C,""yyyy/mm/dd"")))"),"#N/A") -> #N/A
A21: Diverseスタジオ | B21: 技術研究所 | C21: 不明 | D21: =IFERROR(__xludf.DUMMYFUNCTION("XLOOKUP(JOIN(""/"",$A21:$B21),'source merged_div_data'!$A:$A,'source merged_div_data'!B:B)"),2.0) -> 2 | E21: =IFERROR(__xludf.DUMMYFUNCTION("XLOOKUP(JOIN(""/"",$A21:$B21),'source merged_div_data'!$A:$A,'source merged_div_data'!C:C)"),0.0) -> 0 | F21: {=IFERROR( IFS( XLOOKUP(TEXTJOIN("/", TRUE, $A21:$B21), 'source merged_div_data'!$A:$A, 'source merged_div_data'!F:F) < 1024, XLOOKUP(TEXTJOIN("/", TRUE, $A21:$B21), 'source merged_div_data'!$A:$A, 'source merged_div_data'!F:F) & " B", XLOOKUP(TEXTJOIN("/", TRUE, $A21:$B21), 'source merged_div_data'!$A:$A, 'source merged_div_data'!F:F) < 1048576, ROUND(XLOOKUP(TEXTJOIN("/", TRUE, $A21:$B21), 'source merged_div_data'!$A:$A, 'source merged_div_data'!F:F)/1024, 2) & " KB", XLOOKUP(TEXTJOIN("/", TRUE, $A21:$B21), 'source merged_div_data'!$A:$A, 'source merged_div_data'!F:F) < 1073741824, ROUND(XLOOKUP(TEXTJOIN("/", TRUE, $A21:$B21), 'source merged_div_data'!$A:$A, 'source merged_div_data'!F:F)/1048576, 2) & " MB", TRUE, ROUND(XLOOKUP(TEXTJOIN("/", TRUE, $A21:$B21), 'source merged_div_data'!$A:$A, 'source merged_div_data'!F:F)/1073741824, 2) & " GB" ), "×" )} -> 27 B | G21: × | J21: 株式会社Diverse | L21: × | M21: × | N21: 廃止/分社化 | O21: 株式会社Diverse | P21: =IFERROR(__xludf.DUMMYFUNCTION("XLOOKUP(JOIN(""/"",$A21:$B21),'source isilon_divまとめ'!$A:$A,'source isilon_divまとめ'!$D:$D,XLOOKUP(JOIN(""\"",$A21:$B21),'source NetApp-file-sv01-div'!A:A,TEXT('source NetApp-file-sv01-div'!C:C,""yyyy/mm/dd"")))"),"#N/A") -> #N/A
A22: Diverseスタジオ | B22: VEAT事業部 | C22: 不明 | D22: =IFERROR(__xludf.DUMMYFUNCTION("XLOOKUP(JOIN(""/"",$A22:$B22),'source merged_div_data'!$A:$A,'source merged_div_data'!B:B)"),4.0) -> 4 | E22: =IFERROR(__xludf.DUMMYFUNCTION("XLOOKUP(JOIN(""/"",$A22:$B22),'source merged_div_data'!$A:$A,'source merged_div_data'!C:C)"),0.0) -> 0 | F22: {=IFERROR( IFS( XLOOKUP(TEXTJOIN("/", TRUE, $A22:$B22), 'source merged_div_data'!$A:$A, 'source merged_div_data'!F:F) < 1024, XLOOKUP(TEXTJOIN("/", TRUE, $A22:$B22), 'source merged_div_data'!$A:$A, 'source merged_div_data'!F:F) & " B", XLOOKUP(TEXTJOIN("/", TRUE, $A22:$B22), 'source merged_div_data'!$A:$A, 'source merged_div_data'!F:F) < 1048576, ROUND(XLOOKUP(TEXTJOIN("/", TRUE, $A22:$B22), 'source merged_div_data'!$A:$A, 'source merged_div_data'!F:F)/1024, 2) & " KB", XLOOKUP(TEXTJOIN("/", TRUE, $A22:$B22), 'source merged_div_data'!$A:$A, 'source merged_div_data'!F:F) < 1073741824, ROUND(XLOOKUP(TEXTJOIN("/", TRUE, $A22:$B22), 'source merged_div_data'!$A:$A, 'source merged_div_data'!F:F)/1048576, 2) & " MB", TRUE, ROUND(XLOOKUP(TEXTJOIN("/", TRUE, $A22:$B22), 'source merged_div_data'!$A:$A, 'source merged_div_data'!F:F)/1073741824, 2) & " GB" ), "×" )} -> 86 B | G22: {=IFERROR( IFS( XLOOKUP(TEXTJOIN("/", TRUE, $A22:$B22), 'source merged_div_data'!$A:$A, 'source merged_div_data'!G:G) < 1024, XLOOKUP(TEXTJOIN("/", TRUE, $A22:$B22), 'source merged_div_data'!$A:$A, 'source merged_div_data'!G:G) & " B", XLOOKUP(TEXTJOIN("/", TRUE, $A22:$B22), 'source merged_div_data'!$A:$A, 'source merged_div_data'!G:G) < 1048576, ROUND(XLOOKUP(TEXTJOIN("/", TRUE, $A22:$B22), 'source merged_div_data'!$A:$A, 'source merged_div_data'!G:G)/1024, 2) & " KB", XLOOKUP(TEXTJOIN("/", TRUE, $A22:$B22), 'source merged_div_data'!$A:$A, 'source merged_div_data'!G:G) < 1073741824, ROUND(XLOOKUP(TEXTJOIN("/", TRUE, $A22:$B22), 'source merged_div_data'!$A:$A, 'source merged_div_data'!G:G)/1048576, 2) & " MB", TRUE, ROUND(XLOOKUP(TEXTJOIN("/", TRUE, $A22:$B22), 'source merged_div_data'!$A:$A, 'source merged_div_data'!G:G)/1073741824, 2) & " GB" ), "×" )} -> 128 KB | J22: 株式会社Diverse | L22: × | M22: × | N22: 廃止/分社化 | O22: 株式会社Diverse | P22: =IFERROR(__xludf.DUMMYFUNCTION("XLOOKUP(JOIN(""/"",$A22:$B22),'source isilon_divまとめ'!$A:$A,'source isilon_divまとめ'!$D:$D,XLOOKUP(JOIN(""\"",$A22:$B22),'source NetApp-file-sv01-div'!A:A,TEXT('source NetApp-file-sv01-div'!C:C,""yyyy/mm/dd"")))"),"#N/A") -> #N/A
A23: Diverseスタジオ | B23: メディア事業部 | C23: 不明 | D23: =IFERROR(__xludf.DUMMYFUNCTION("XLOOKUP(JOIN(""/"",$A23:$B23),'source merged_div_data'!$A:$A,'source merged_div_data'!B:B)"),6.0) -> 6 | E23: =IFERROR(__xludf.DUMMYFUNCTION("XLOOKUP(JOIN(""/"",$A23:$B23),'source merged_div_data'!$A:$A,'source merged_div_data'!C:C)"),0.0) -> 0 | F23: {=IFERROR( IFS( XLOOKUP(TEXTJOIN("/", TRUE, $A23:$B23), 'source merged_div_data'!$A:$A, 'source merged_div_data'!F:F) < 1024, XLOOKUP(TEXTJOIN("/", TRUE, $A23:$B23), 'source merged_div_data'!$A:$A, 'source merged_div_data'!F:F) & " B", XLOOKUP(TEXTJOIN("/", TRUE, $A23:$B23), 'source merged_div_data'!$A:$A, 'source merged_div_data'!F:F) < 1048576, ROUND(XLOOKUP(TEXTJOIN("/", TRUE, $A23:$B23), 'source merged_div_data'!$A:$A, 'source merged_div_data'!F:F)/1024, 2) & " KB", XLOOKUP(TEXTJOIN("/", TRUE, $A23:$B23), 'source merged_div_data'!$A:$A, 'source merged_div_data'!F:F) < 1073741824, ROUND(XLOOKUP(TEXTJOIN("/", TRUE, $A23:$B23), 'source merged_div_data'!$A:$A, 'source merged_div_data'!F:F)/1048576, 2) & " MB", TRUE, ROUND(XLOOKUP(TEXTJOIN("/", TRUE, $A23:$B23), 'source merged_div_data'!$A:$A, 'source merged_div_data'!F:F)/1073741824, 2) & " GB" ), "×" )} -> 151 B | G23: × | J23: 株式会社Diverse | L23: × | M23: × | N23: 廃止/分社化 | O23: 株式会社Diverse | P23: =IFERROR(__xludf.DUMMYFUNCTION("XLOOKUP(JOIN(""/"",$A23:$B23),'source isilon_divまとめ'!$A:$A,'source isilon_divまとめ'!$D:$D,XLOOKUP(JOIN(""\"",$A23:$B23),'source NetApp-file-sv01-div'!A:A,TEXT('source NetApp-file-sv01-div'!C:C,""yyyy/mm/dd"")))"),"#N/A") -> #N/A
A24: Diverseスタジオ | B24: YYC事業部 | C24: 不明 | D24: =IFERROR(__xludf.DUMMYFUNCTION("XLOOKUP(JOIN(""/"",$A24:$B24),'source merged_div_data'!$A:$A,'source merged_div_data'!B:B)"),7.0) -> 7 | E24: =IFERROR(__xludf.DUMMYFUNCTION("XLOOKUP(JOIN(""/"",$A24:$B24),'source merged_div_data'!$A:$A,'source merged_div_data'!C:C)"),0.0) -> 0 | F24: {=IFERROR( IFS( XLOOKUP(TEXTJOIN("/", TRUE, $A24:$B24), 'source merged_div_data'!$A:$A, 'source merged_div_data'!F:F) < 1024, XLOOKUP(TEXTJOIN("/", TRUE, $A24:$B24), 'source merged_div_data'!$A:$A, 'source merged_div_data'!F:F) & " B", XLOOKUP(TEXTJOIN("/", TRUE, $A24:$B24), 'source merged_div_data'!$A:$A, 'source merged_div_data'!F:F) < 1048576, ROUND(XLOOKUP(TEXTJOIN("/", TRUE, $A24:$B24), 'source merged_div_data'!$A:$A, 'source merged_div_data'!F:F)/1024, 2) & " KB", XLOOKUP(TEXTJOIN("/", TRUE, $A24:$B24), 'source merged_div_data'!$A:$A, 'source merged_div_data'!F:F) < 1073741824, ROUND(XLOOKUP(TEXTJOIN("/", TRUE, $A24:$B24), 'source merged_div_data'!$A:$A, 'source merged_div_data'!F:F)/1048576, 2) & " MB", TRUE, ROUND(XLOOKUP(TEXTJOIN("/", TRUE, $A24:$B24), 'source merged_div_data'!$A:$A, 'source merged_div_data'!F:F)/1073741824, 2) & " GB" ), "×" )} -> 213 B | G24: × | J24: 株式会社Diverse | L24: × | M24: × | N24: 廃止/分社化 | O24: 株式会社Diverse | P24: =IFERROR(__xludf.DUMMYFUNCTION("XLOOKUP(JOIN(""/"",$A24:$B24),'source isilon_divまとめ'!$A:$A,'source isilon_divまとめ'!$D:$D,XLOOKUP(JOIN(""\"",$A24:$B24),'source NetApp-file-sv01-div'!A:A,TEXT('source NetApp-file-sv01-div'!C:C,""yyyy/mm/dd"")))"),"#N/A") -> #N/A
A25: Diverseスタジオ | B25: 本部共有 | C25: 仮説 | D25: =IFERROR(__xludf.DUMMYFUNCTION("XLOOKUP(JOIN(""/"",$A25:$B25),'source merged_div_data'!$A:$A,'source merged_div_data'!B:B)"),1.0) -> 1 | E25: =IFERROR(__xludf.DUMMYFUNCTION("XLOOKUP(JOIN(""/"",$A25:$B25),'source merged_div_data'!$A:$A,'source merged_div_data'!C:C)"),1.0) -> 1 | F25: {=IFERROR( IFS( XLOOKUP(TEXTJOIN("/", TRUE, $A25:$B25), 'source merged_div_data'!$A:$A, 'source merged_div_data'!F:F) < 1024, XLOOKUP(TEXTJOIN("/", TRUE, $A25:$B25), 'source merged_div_data'!$A:$A, 'source merged_div_data'!F:F) & " B", XLOOKUP(TEXTJOIN("/", TRUE, $A25:$B25), 'source merged_div_data'!$A:$A, 'source merged_div_data'!F:F) < 1048576, ROUND(XLOOKUP(TEXTJOIN("/", TRUE, $A25:$B25), 'source merged_div_data'!$A:$A, 'source merged_div_data'!F:F)/1024, 2) & " KB", XLOOKUP(TEXTJOIN("/", TRUE, $A25:$B25), 'source merged_div_data'!$A:$A, 'source merged_div_data'!F:F) < 1073741824, ROUND(XLOOKUP(TEXTJOIN("/", TRUE, $A25:$B25), 'source merged_div_data'!$A:$A, 'source merged_div_data'!F:F)/1048576, 2) & " MB", TRUE, ROUND(XLOOKUP(TEXTJOIN("/", TRUE, $A25:$B25), 'source merged_div_data'!$A:$A, 'source merged_div_data'!F:F)/1073741824, 2) & " GB" ), "×" )} -> 6.03 KB | G25: × | H25: AWS S3 | J25: 株式会社Diverse | L25: × | M25: × | N25: 廃止/分社化 | O25: - | P25: =IFERROR(__xludf.DUMMYFUNCTION("XLOOKUP(JOIN(""/"",$A25:$B25),'source isilon_divまとめ'!$A:$A,'source isilon_divまとめ'!$D:$D,XLOOKUP(JOIN(""\"",$A25:$B25),'source NetApp-file-sv01-div'!A:A,TEXT('source NetApp-file-sv01-div'!C:C,""yyyy/mm/dd"")))"),"#N/A") -> #N/A
A26: Diverseスタジオ | B26: マッチングサービス事業部 | C26: 不明 | D26: =IFERROR(__xludf.DUMMYFUNCTION("XLOOKUP(JOIN(""/"",$A26:$B26),'source merged_div_data'!$A:$A,'source merged_div_data'!B:B)"),9.0) -> 9 | E26: =IFERROR(__xludf.DUMMYFUNCTION("XLOOKUP(JOIN(""/"",$A26:$B26),'source merged_div_data'!$A:$A,'source merged_div_data'!C:C)"),0.0) -> 0 | F26: {=IFERROR( IFS( XLOOKUP(TEXTJOIN("/", TRUE, $A26:$B26), 'source merged_div_data'!$A:$A, 'source merged_div_data'!F:F) < 1024, XLOOKUP(TEXTJOIN("/", TRUE, $A26:$B26), 'source merged_div_data'!$A:$A, 'source merged_div_data'!F:F) & " B", XLOOKUP(TEXTJOIN("/", TRUE, $A26:$B26), 'source merged_div_data'!$A:$A, 'source merged_div_data'!F:F) < 1048576, ROUND(XLOOKUP(TEXTJOIN("/", TRUE, $A26:$B26), 'source merged_div_data'!$A:$A, 'source merged_div_data'!F:F)/1024, 2) & " KB", XLOOKUP(TEXTJOIN("/", TRUE, $A26:$B26), 'source merged_div_data'!$A:$A, 'source merged_div_data'!F:F) < 1073741824, ROUND(XLOOKUP(TEXTJOIN("/", TRUE, $A26:$B26), 'source merged_div_data'!$A:$A, 'source merged_div_data'!F:F)/1048576, 2) & " MB", TRUE, ROUND(XLOOKUP(TEXTJOIN("/", TRUE, $A26:$B26), 'source merged_div_data'!$A:$A, 'source merged_div_data'!F:F)/1073741824, 2) & " GB" ), "×" )} -> 276 B | G26: × | J26: 株式会社Diverse | L26: × | M26: × | N26: 廃止/分社化 | O26: 株式会社Diverse | P26: =IFERROR(__xludf.DUMMYFUNCTION("XLOOKUP(JOIN(""/"",$A26:$B26),'source isilon_divまとめ'!$A:$A,'source isilon_divまとめ'!$D:$D,XLOOKUP(JOIN(""\"",$A26:$B26),'source NetApp-file-sv01-div'!A:A,TEXT('source NetApp-file-sv01-div'!C:C,""yyyy/mm/dd"")))"),"#N/A") -> #N/A
A27: モンストスタジオ | B27: マーケティングG | C27: 仮説 | D27: =IFERROR(__xludf.DUMMYFUNCTION("XLOOKUP(JOIN(""/"",$A27:$B27),'source merged_div_data'!$A:$A,'source merged_div_data'!B:B)"),275.0) -> 275 | E27: =IFERROR(__xludf.DUMMYFUNCTION("XLOOKUP(JOIN(""/"",$A27:$B27),'source merged_div_data'!$A:$A,'source merged_div_data'!C:C)"),909.0) -> 909 | F27: {=IFERROR( IFS( XLOOKUP(TEXTJOIN("/", TRUE, $A27:$B27), 'source merged_div_data'!$A:$A, 'source merged_div_data'!F:F) < 1024, XLOOKUP(TEXTJOIN("/", TRUE, $A27:$B27), 'source merged_div_data'!$A:$A, 'source merged_div_data'!F:F) & " B", XLOOKUP(TEXTJOIN("/", TRUE, $A27:$B27), 'source merged_div_data'!$A:$A, 'source merged_div_data'!F:F) < 1048576, ROUND(XLOOKUP(TEXTJOIN("/", TRUE, $A27:$B27), 'source merged_div_data'!$A:$A, 'source merged_div_data'!F:F)/1024, 2) & " KB", XLOOKUP(TEXTJOIN("/", TRUE, $A27:$B27), 'source merged_div_data'!$A:$A, 'source merged_div_data'!F:F) < 1073741824, ROUND(XLOOKUP(TEXTJOIN("/", TRUE, $A27:$B27), 'source merged_div_data'!$A:$A, 'source merged_div_data'!F:F)/1048576, 2) & " MB", TRUE, ROUND(XLOOKUP(TEXTJOIN("/", TRUE, $A27:$B27), 'source merged_div_data'!$A:$A, 'source merged_div_data'!F:F)/1073741824, 2) & " GB" ), "×" )} -> 20.85 GB | G27: 2014/12/16 | H27: AWS S3 | J27: デジタルエンターテインメントオペレーションズ本部 | L27: 三島 圭介 | M27: × | N27: 廃止/再編 | O27: モンスト事業部 | P27: =IFERROR(__xludf.DUMMYFUNCTION("XLOOKUP(JOIN(""/"",$A27:$B27),'source isilon_divまとめ'!$A:$A,'source isilon_divまとめ'!$D:$D,XLOOKUP(JOIN(""\"",$A27:$B27),'source NetApp-file-sv01-div'!A:A,TEXT('source NetApp-file-sv01-div'!C:C,""yyyy/mm/dd"")))"),"2014/12/16") -> 2014/12/16
A28: モンストスタジオ | B28: 企画・運用部 | C28: 仮説 | D28: =IFERROR(__xludf.DUMMYFUNCTION("XLOOKUP(JOIN(""/"",$A28:$B28),'source merged_div_data'!$A:$A,'source merged_div_data'!B:B)"),3844.0) -> 3844 | E28: =IFERROR(__xludf.DUMMYFUNCTION("XLOOKUP(JOIN(""/"",$A28:$B28),'source merged_div_data'!$A:$A,'source merged_div_data'!C:C)"),91526.0) -> 91526 | F28: {=IFERROR( IFS( XLOOKUP(TEXTJOIN("/", TRUE, $A28:$B28), 'source merged_div_data'!$A:$A, 'source merged_div_data'!F:F) < 1024, XLOOKUP(TEXTJOIN("/", TRUE, $A28:$B28), 'source merged_div_data'!$A:$A, 'source merged_div_data'!F:F) & " B", XLOOKUP(TEXTJOIN("/", TRUE, $A28:$B28), 'source merged_div_data'!$A:$A, 'source merged_div_data'!F:F) < 1048576, ROUND(XLOOKUP(TEXTJOIN("/", TRUE, $A28:$B28), 'source merged_div_data'!$A:$A, 'source merged_div_data'!F:F)/1024, 2) & " KB", XLOOKUP(TEXTJOIN("/", TRUE, $A28:$B28), 'source merged_div_data'!$A:$A, 'source merged_div_data'!F:F) < 1073741824, ROUND(XLOOKUP(TEXTJOIN("/", TRUE, $A28:$B28), 'source merged_div_data'!$A:$A, 'source merged_div_data'!F:F)/1048576, 2) & " MB", TRUE, ROUND(XLOOKUP(TEXTJOIN("/", TRUE, $A28:$B28), 'source merged_div_data'!$A:$A, 'source merged_div_data'!F:F)/1073741824, 2) & " GB" ), "×" )} -> 358.06 GB | G28: 2025/07/07 | H28: Googleドライブ | J28: デジタルエンターテインメントオペレーションズ本部 | L28: 三島 圭介 | M28: × | N28: 廃止/再編 | O28: モンスト事業部 | P28: =IFERROR(__xludf.DUMMYFUNCTION("XLOOKUP(JOIN(""/"",$A28:$B28),'source isilon_divまとめ'!$A:$A,'source isilon_divまとめ'!$D:$D,XLOOKUP(JOIN(""\"",$A28:$B28),'source NetApp-file-sv01-div'!A:A,TEXT('source NetApp-file-sv01-div'!C:C,""yyyy/mm/dd"")))"),"2025/07/07") -> 2025/07/07
A29: モンストスタジオ | B29: 新規事業推進室 | C29: 仮説 | D29: =IFERROR(__xludf.DUMMYFUNCTION("XLOOKUP(JOIN(""/"",$A29:$B29),'source merged_div_data'!$A:$A,'source merged_div_data'!B:B)"),58.0) -> 58 | E29: =IFERROR(__xludf.DUMMYFUNCTION("XLOOKUP(JOIN(""/"",$A29:$B29),'source merged_div_data'!$A:$A,'source merged_div_data'!C:C)"),103.0) -> 103 | F29: {=IFERROR( IFS( XLOOKUP(TEXTJOIN("/", TRUE, $A29:$B29), 'source merged_div_data'!$A:$A, 'source merged_div_data'!F:F) < 1024, XLOOKUP(TEXTJOIN("/", TRUE, $A29:$B29), 'source merged_div_data'!$A:$A, 'source merged_div_data'!F:F) & " B", XLOOKUP(TEXTJOIN("/", TRUE, $A29:$B29), 'source merged_div_data'!$A:$A, 'source merged_div_data'!F:F) < 1048576, ROUND(XLOOKUP(TEXTJOIN("/", TRUE, $A29:$B29), 'source merged_div_data'!$A:$A, 'source merged_div_data'!F:F)/1024, 2) & " KB", XLOOKUP(TEXTJOIN("/", TRUE, $A29:$B29), 'source merged_div_data'!$A:$A, 'source merged_div_data'!F:F) < 1073741824, ROUND(XLOOKUP(TEXTJOIN("/", TRUE, $A29:$B29), 'source merged_div_data'!$A:$A, 'source merged_div_data'!F:F)/1048576, 2) & " MB", TRUE, ROUND(XLOOKUP(TEXTJOIN("/", TRUE, $A29:$B29), 'source merged_div_data'!$A:$A, 'source merged_div_data'!F:F)/1073741824, 2) & " GB" ), "×" )} -> 91.86 MB | G29: 2015/12/01 | H29: AWS S3 | J29: デジタルエンターテインメントオペレーションズ本部 | L29: 三島 圭介 | M29: × | N29: 廃止/再編 | O29: モンスト事業部 | P29: =IFERROR(__xludf.DUMMYFUNCTION("XLOOKUP(JOIN(""/"",$A29:$B29),'source isilon_divまとめ'!$A:$A,'source isilon_divまとめ'!$D:$D,XLOOKUP(JOIN(""\"",$A29:$B29),'source NetApp-file-sv01-div'!A:A,TEXT('source NetApp-file-sv01-div'!C:C,""yyyy/mm/dd"")))"),"2015/12/01") -> 2015/12/01
A30: モンストスタジオ | B30: システム開発部 | C30: 仮説 | D30: =IFERROR(__xludf.DUMMYFUNCTION("XLOOKUP(JOIN(""/"",$A30:$B30),'source merged_div_data'!$A:$A,'source merged_div_data'!B:B)"),447.0) -> 447 | E30: =IFERROR(__xludf.DUMMYFUNCTION("XLOOKUP(JOIN(""/"",$A30:$B30),'source merged_div_data'!$A:$A,'source merged_div_data'!C:C)"),4523.0) -> 4523 | F30: {=IFERROR( IFS( XLOOKUP(TEXTJOIN("/", TRUE, $A30:$B30), 'source merged_div_data'!$A:$A, 'source merged_div_data'!F:F) < 1024, XLOOKUP(TEXTJOIN("/", TRUE, $A30:$B30), 'source merged_div_data'!$A:$A, 'source merged_div_data'!F:F) & " B", XLOOKUP(TEXTJOIN("/", TRUE, $A30:$B30), 'source merged_div_data'!$A:$A, 'source merged_div_data'!F:F) < 1048576, ROUND(XLOOKUP(TEXTJOIN("/", TRUE, $A30:$B30), 'source merged_div_data'!$A:$A, 'source merged_div_data'!F:F)/1024, 2) & " KB", XLOOKUP(TEXTJOIN("/", TRUE, $A30:$B30), 'source merged_div_data'!$A:$A, 'source merged_div_data'!F:F) < 1073741824, ROUND(XLOOKUP(TEXTJOIN("/", TRUE, $A30:$B30), 'source merged_div_data'!$A:$A, 'source merged_div_data'!F:F)/1048576, 2) & " MB", TRUE, ROUND(XLOOKUP(TEXTJOIN("/", TRUE, $A30:$B30), 'source merged_div_data'!$A:$A, 'source merged_div_data'!F:F)/1073741824, 2) & " GB" ), "×" )} -> 404.83 MB | G30: 2017/04/11 | H30: AWS S3 | J30: デジタルエンターテインメントオペレーションズ本部 | L30: 三島 圭介 | M30: × | N30: 廃止/再編 | O30: モンスト事業部 | P30: =IFERROR(__xludf.DUMMYFUNCTION("XLOOKUP(JOIN(""/"",$A30:$B30),'source isilon_divまとめ'!$A:$A,'source isilon_divまとめ'!$D:$D,XLOOKUP(JOIN(""\"",$A30:$B30),'source NetApp-file-sv01-div'!A:A,TEXT('source NetApp-file-sv01-div'!C:C,""yyyy/mm/dd"")))"),"2017/04/11") -> 2017/04/11
A31: モンストスタジオ | B31: メディアミックス部 | C31: 仮説 | D31: =IFERROR(__xludf.DUMMYFUNCTION("XLOOKUP(JOIN(""/"",$A31:$B31),'source merged_div_data'!$A:$A,'source merged_div_data'!B:B)"),1626.0) -> 1626 | E31: =IFERROR(__xludf.DUMMYFUNCTION("XLOOKUP(JOIN(""/"",$A31:$B31),'source merged_div_data'!$A:$A,'source merged_div_data'!C:C)"),10752.0) -> 10752 | F31: {=IFERROR( IFS( XLOOKUP(TEXTJOIN("/", TRUE, $A31:$B31), 'source merged_div_data'!$A:$A, 'source merged_div_data'!F:F) < 1024, XLOOKUP(TEXTJOIN("/", TRUE, $A31:$B31), 'source merged_div_data'!$A:$A, 'source merged_div_data'!F:F) & " B", XLOOKUP(TEXTJOIN("/", TRUE, $A31:$B31), 'source merged_div_data'!$A:$A, 'source merged_div_data'!F:F) < 1048576, ROUND(XLOOKUP(TEXTJOIN("/", TRUE, $A31:$B31), 'source merged_div_data'!$A:$A, 'source merged_div_data'!F:F)/1024, 2) & " KB", XLOOKUP(TEXTJOIN("/", TRUE, $A31:$B31), 'source merged_div_data'!$A:$A, 'source merged_div_data'!F:F) < 1073741824, ROUND(XLOOKUP(TEXTJOIN("/", TRUE, $A31:$B31), 'source merged_div_data'!$A:$A, 'source merged_div_data'!F:F)/1048576, 2) & " MB", TRUE, ROUND(XLOOKUP(TEXTJOIN("/", TRUE, $A31:$B31), 'source merged_div_data'!$A:$A, 'source merged_div_data'!F:F)/1073741824, 2) & " GB" ), "×" )} -> 118.1 GB | G31: 2016/01/20 | H31: AWS S3 | J31: デジタルエンターテインメントオペレーションズ本部 | L31: 三島 圭介 | M31: × | N31: 廃止/再編 | O31: モンスト事業部 | P31: =IFERROR(__xludf.DUMMYFUNCTION("XLOOKUP(JOIN(""/"",$A31:$B31),'source isilon_divまとめ'!$A:$A,'source isilon_divまとめ'!$D:$D,XLOOKUP(JOIN(""\"",$A31:$B31),'source NetApp-file-sv01-div'!A:A,TEXT('source NetApp-file-sv01-div'!C:C,""yyyy/mm/dd"")))"),"2016/01/20") -> 2016/01/20
A32: モンストスタジオ | B32: マーケティング部 | C32: 仮説 | D32: =IFERROR(__xludf.DUMMYFUNCTION("XLOOKUP(JOIN(""/"",$A32:$B32),'source merged_div_data'!$A:$A,'source merged_div_data'!B:B)"),59696.0) -> 59696 | E32: =IFERROR(__xludf.DUMMYFUNCTION("XLOOKUP(JOIN(""/"",$A32:$B32),'source merged_div_data'!$A:$A,'source merged_div_data'!C:C)"),263909.0) -> 263909 | F32: {=IFERROR( IFS( XLOOKUP(TEXTJOIN("/", TRUE, $A32:$B32), 'source merged_div_data'!$A:$A, 'source merged_div_data'!F:F) < 1024, XLOOKUP(TEXTJOIN("/", TRUE, $A32:$B32), 'source merged_div_data'!$A:$A, 'source merged_div_data'!F:F) & " B", XLOOKUP(TEXTJOIN("/", TRUE, $A32:$B32), 'source merged_div_data'!$A:$A, 'source merged_div_data'!F:F) < 1048576, ROUND(XLOOKUP(TEXTJOIN("/", TRUE, $A32:$B32), 'source merged_div_data'!$A:$A, 'source merged_div_data'!F:F)/1024, 2) & " KB", XLOOKUP(TEXTJOIN("/", TRUE, $A32:$B32), 'source merged_div_data'!$A:$A, 'source merged_div_data'!F:F) < 1073741824, ROUND(XLOOKUP(TEXTJOIN("/", TRUE, $A32:$B32), 'source merged_div_data'!$A:$A, 'source merged_div_data'!F:F)/1048576, 2) & " MB", TRUE, ROUND(XLOOKUP(TEXTJOIN("/", TRUE, $A32:$B32), 'source merged_div_data'!$A:$A, 'source merged_div_data'!F:F)/1073741824, 2) & " GB" ), "×" )} -> 1479.68 GB | G32: 2022/06/03 | H32: AWS S3 | J32: デジタルエンターテインメントオペレーションズ本部 | L32: 三島 圭介 | M32: × | N32: 廃止/再編 | O32: モンスト事業部 | P32: =IFERROR(__xludf.DUMMYFUNCTION("XLOOKUP(JOIN(""/"",$A32:$B32),'source isilon_divまとめ'!$A:$A,'source isilon_divまとめ'!$D:$D,XLOOKUP(JOIN(""\"",$A32:$B32),'source NetApp-file-sv01-div'!A:A,TEXT('source NetApp-file-sv01-div'!C:C,""yyyy/mm/dd"")))"),"2022/06/03") -> 2022/06/03
A33: モンストスタジオ | B33: 事業戦略室 | C33: 0file | D33: =IFERROR(__xludf.DUMMYFUNCTION("XLOOKUP(JOIN(""/"",$A33:$B33),'source merged_div_data'!$A:$A,'source merged_div_data'!B:B)"),6.0) -> 6 | E33: =IFERROR(__xludf.DUMMYFUNCTION("XLOOKUP(JOIN(""/"",$A33:$B33),'source merged_div_data'!$A:$A,'source merged_div_data'!C:C)"),0.0) -> 0 | F33: {=IFERROR( IFS( XLOOKUP(TEXTJOIN("/", TRUE, $A33:$B33), 'source merged_div_data'!$A:$A, 'source merged_div_data'!F:F) < 1024, XLOOKUP(TEXTJOIN("/", TRUE, $A33:$B33), 'source merged_div_data'!$A:$A, 'source merged_div_data'!F:F) & " B", XLOOKUP(TEXTJOIN("/", TRUE, $A33:$B33), 'source merged_div_data'!$A:$A, 'source merged_div_data'!F:F) < 1048576, ROUND(XLOOKUP(TEXTJOIN("/", TRUE, $A33:$B33), 'source merged_div_data'!$A:$A, 'source merged_div_data'!F:F)/1024, 2) & " KB", XLOOKUP(TEXTJOIN("/", TRUE, $A33:$B33), 'source merged_div_data'!$A:$A, 'source merged_div_data'!F:F) < 1073741824, ROUND(XLOOKUP(TEXTJOIN("/", TRUE, $A33:$B33), 'source merged_div_data'!$A:$A, 'source merged_div_data'!F:F)/1048576, 2) & " MB", TRUE, ROUND(XLOOKUP(TEXTJOIN("/", TRUE, $A33:$B33), 'source merged_div_data'!$A:$A, 'source merged_div_data'!F:F)/1073741824, 2) & " GB" ), "×" )} -> 170 B | G33: × | J33: ﾃﾞｼﾞﾀﾙｴﾝﾀｰﾃｲﾝﾒﾝﾄﾊﾟﾌﾞﾘｯｼﾝｸﾞ本部 | K33: 事業戦略室 | L33: 石井 公二 | M33: 青山 智史 | P33: =IFERROR(__xludf.DUMMYFUNCTION("XLOOKUP(JOIN(""/"",$A33:$B33),'source isilon_divまとめ'!$A:$A,'source isilon_divまとめ'!$D:$D,XLOOKUP(JOIN(""\"",$A33:$B33),'source NetApp-file-sv01-div'!A:A,TEXT('source NetApp-file-sv01-div'!C:C,""yyyy/mm/dd"")))"),"#N/A") -> #N/A
A34: モンストスタジオ | B34: 本部共有 | C34: 不明 | D34: =IFERROR(__xludf.DUMMYFUNCTION("XLOOKUP(JOIN(""/"",$A34:$B34),'source merged_div_data'!$A:$A,'source merged_div_data'!B:B)"),3062.0) -> 3062 | E34: =IFERROR(__xludf.DUMMYFUNCTION("XLOOKUP(JOIN(""/"",$A34:$B34),'source merged_div_data'!$A:$A,'source merged_div_data'!C:C)"),143503.0) -> 143503 | F34: {=IFERROR( IFS( XLOOKUP(TEXTJOIN("/", TRUE, $A34:$B34), 'source merged_div_data'!$A:$A, 'source merged_div_data'!F:F) < 1024, XLOOKUP(TEXTJOIN("/", TRUE, $A34:$B34), 'source merged_div_data'!$A:$A, 'source merged_div_data'!F:F) & " B", XLOOKUP(TEXTJOIN("/", TRUE, $A34:$B34), 'source merged_div_data'!$A:$A, 'source merged_div_data'!F:F) < 1048576, ROUND(XLOOKUP(TEXTJOIN("/", TRUE, $A34:$B34), 'source merged_div_data'!$A:$A, 'source merged_div_data'!F:F)/1024, 2) & " KB", XLOOKUP(TEXTJOIN("/", TRUE, $A34:$B34), 'source merged_div_data'!$A:$A, 'source merged_div_data'!F:F) < 1073741824, ROUND(XLOOKUP(TEXTJOIN("/", TRUE, $A34:$B34), 'source merged_div_data'!$A:$A, 'source merged_div_data'!F:F)/1048576, 2) & " MB", TRUE, ROUND(XLOOKUP(TEXTJOIN("/", TRUE, $A34:$B34), 'source merged_div_data'!$A:$A, 'source merged_div_data'!F:F)/1073741824, 2) & " GB" ), "×" )} -> 499.2 GB | G34: 2018/04/15 | H34: AWS S3 | J34: - | L34: × | M34: × | N34: 廃止/再編 | O34: - | P34: =IFERROR(__xludf.DUMMYFUNCTION("XLOOKUP(JOIN(""/"",$A34:$B34),'source isilon_divまとめ'!$A:$A,'source isilon_divまとめ'!$D:$D,XLOOKUP(JOIN(""\"",$A34:$B34),'source NetApp-file-sv01-div'!A:A,TEXT('source NetApp-file-sv01-div'!C:C,""yyyy/mm/dd"")))"),"2018/04/15") -> 2018/04/15
A35: ノハナ | B35: 全社共有 | C35: 不明 | D35: =IFERROR(__xludf.DUMMYFUNCTION("XLOOKUP(JOIN(""/"",$A35:$B35),'source merged_div_data'!$A:$A,'source merged_div_data'!B:B)"),16182.0) -> 16182 | E35: =IFERROR(__xludf.DUMMYFUNCTION("XLOOKUP(JOIN(""/"",$A35:$B35),'source merged_div_data'!$A:$A,'source merged_div_data'!C:C)"),185216.0) -> 185216 | F35: {=IFERROR( IFS( XLOOKUP(TEXTJOIN("/", TRUE, $A35:$B35), 'source merged_div_data'!$A:$A, 'source merged_div_data'!F:F) < 1024, XLOOKUP(TEXTJOIN("/", TRUE, $A35:$B35), 'source merged_div_data'!$A:$A, 'source merged_div_data'!F:F) & " B", XLOOKUP(TEXTJOIN("/", TRUE, $A35:$B35), 'source merged_div_data'!$A:$A, 'source merged_div_data'!F:F) < 1048576, ROUND(XLOOKUP(TEXTJOIN("/", TRUE, $A35:$B35), 'source merged_div_data'!$A:$A, 'source merged_div_data'!F:F)/1024, 2) & " KB", XLOOKUP(TEXTJOIN("/", TRUE, $A35:$B35), 'source merged_div_data'!$A:$A, 'source merged_div_data'!F:F) < 1073741824, ROUND(XLOOKUP(TEXTJOIN("/", TRUE, $A35:$B35), 'source merged_div_data'!$A:$A, 'source merged_div_data'!F:F)/1048576, 2) & " MB", TRUE, ROUND(XLOOKUP(TEXTJOIN("/", TRUE, $A35:$B35), 'source merged_div_data'!$A:$A, 'source merged_div_data'!F:F)/1073741824, 2) & " GB" ), "×" )} -> 735.66 GB | G35: 2019/03/29 | H35: AWS S3 | J35: 株式会社ノハナ | L35: × | M35: × | N35: 存続 (子会社) | O35: 株式会社ノハナ | P35: =IFERROR(__xludf.DUMMYFUNCTION("XLOOKUP(JOIN(""/"",$A35:$B35),'source isilon_divまとめ'!$A:$A,'source isilon_divまとめ'!$D:$D,XLOOKUP(JOIN(""\"",$A35:$B35),'source NetApp-file-sv01-div'!A:A,TEXT('source NetApp-file-sv01-div'!C:C,""yyyy/mm/dd"")))"),"2019/03/29") -> 2019/03/29
A36: 人事本部 | B36: 労務部 | C36: 合致 | D36: =IFERROR(__xludf.DUMMYFUNCTION("XLOOKUP(JOIN(""/"",$A36:$B36),'source merged_div_data'!$A:$A,'source merged_div_data'!B:B)"),47.0) -> 47 | E36: =IFERROR(__xludf.DUMMYFUNCTION("XLOOKUP(JOIN(""/"",$A36:$B36),'source merged_div_data'!$A:$A,'source merged_div_data'!C:C)"),1.0) -> 1 | F36: {=IFERROR( IFS( XLOOKUP(TEXTJOIN("/", TRUE, $A36:$B36), 'source merged_div_data'!$A:$A, 'source merged_div_data'!F:F) < 1024, XLOOKUP(TEXTJOIN("/", TRUE, $A36:$B36), 'source merged_div_data'!$A:$A, 'source merged_div_data'!F:F) & " B", XLOOKUP(TEXTJOIN("/", TRUE, $A36:$B36), 'source merged_div_data'!$A:$A, 'source merged_div_data'!F:F) < 1048576, ROUND(XLOOKUP(TEXTJOIN("/", TRUE, $A36:$B36), 'source merged_div_data'!$A:$A, 'source merged_div_data'!F:F)/1024, 2) & " KB", XLOOKUP(TEXTJOIN("/", TRUE, $A36:$B36), 'source merged_div_data'!$A:$A, 'source merged_div_data'!F:F) < 1073741824, ROUND(XLOOKUP(TEXTJOIN("/", TRUE, $A36:$B36), 'source merged_div_data'!$A:$A, 'source merged_div_data'!F:F)/1048576, 2) & " MB", TRUE, ROUND(XLOOKUP(TEXTJOIN("/", TRUE, $A36:$B36), 'source merged_div_data'!$A:$A, 'source merged_div_data'!F:F)/1073741824, 2) & " GB" ), "×" )} -> 7.54 KB | G36: × | H36: AWS S3 | J36: 人事本部 | K36: 労務部 | L36: 杉村 元規 | M36: 坂田 信隆a | P36: =IFERROR(__xludf.DUMMYFUNCTION("XLOOKUP(JOIN(""/"",$A36:$B36),'source isilon_divまとめ'!$A:$A,'source isilon_divまとめ'!$D:$D,XLOOKUP(JOIN(""\"",$A36:$B36),'source NetApp-file-sv01-div'!A:A,TEXT('source NetApp-file-sv01-div'!C:C,""yyyy/mm/dd"")))"),"#N/A") -> #N/A
A37: 人事本部 | B37: 人材開発部付 | C37: 0file | D37: =IFERROR(__xludf.DUMMYFUNCTION("XLOOKUP(JOIN(""/"",$A37:$B37),'source merged_div_data'!$A:$A,'source merged_div_data'!B:B)"),2.0) -> 2 | E37: =IFERROR(__xludf.DUMMYFUNCTION("XLOOKUP(JOIN(""/"",$A37:$B37),'source merged_div_data'!$A:$A,'source merged_div_data'!C:C)"),0.0) -> 0 | F37: {=IFERROR( IFS( XLOOKUP(TEXTJOIN("/", TRUE, $A37:$B37), 'source merged_div_data'!$A:$A, 'source merged_div_data'!F:F) < 1024, XLOOKUP(TEXTJOIN("/", TRUE, $A37:$B37), 'source merged_div_data'!$A:$A, 'source merged_div_data'!F:F) & " B", XLOOKUP(TEXTJOIN("/", TRUE, $A37:$B37), 'source merged_div_data'!$A:$A, 'source merged_div_data'!F:F) < 1048576, ROUND(XLOOKUP(TEXTJOIN("/", TRUE, $A37:$B37), 'source merged_div_data'!$A:$A, 'source merged_div_data'!F:F)/1024, 2) & " KB", XLOOKUP(TEXTJOIN("/", TRUE, $A37:$B37), 'source merged_div_data'!$A:$A, 'source merged_div_data'!F:F) < 1073741824, ROUND(XLOOKUP(TEXTJOIN("/", TRUE, $A37:$B37), 'source merged_div_data'!$A:$A, 'source merged_div_data'!F:F)/1048576, 2) & " MB", TRUE, ROUND(XLOOKUP(TEXTJOIN("/", TRUE, $A37:$B37), 'source merged_div_data'!$A:$A, 'source merged_div_data'!F:F)/1073741824, 2) & " GB" ), "×" )} -> 27 B | G37: × | J37: 人事本部 | K37: 人材開発部付 | L37: 杉村 元規 | M37: × | P37: =IFERROR(__xludf.DUMMYFUNCTION("XLOOKUP(JOIN(""/"",$A37:$B37),'source isilon_divまとめ'!$A:$A,'source isilon_divまとめ'!$D:$D,XLOOKUP(JOIN(""\"",$A37:$B37),'source NetApp-file-sv01-div'!A:A,TEXT('source NetApp-file-sv01-div'!C:C,""yyyy/mm/dd"")))"),"#N/A") -> #N/A
A38: 人事本部 | B38: 人事戦略部付 | C38: 0file | D38: =IFERROR(__xludf.DUMMYFUNCTION("XLOOKUP(JOIN(""/"",$A38:$B38),'source merged_div_data'!$A:$A,'source merged_div_data'!B:B)"),2.0) -> 2 | E38: =IFERROR(__xludf.DUMMYFUNCTION("XLOOKUP(JOIN(""/"",$A38:$B38),'source merged_div_data'!$A:$A,'source merged_div_data'!C:C)"),0.0) -> 0 | F38: {=IFERROR( IFS( XLOOKUP(TEXTJOIN("/", TRUE, $A38:$B38), 'source merged_div_data'!$A:$A, 'source merged_div_data'!F:F) < 1024, XLOOKUP(TEXTJOIN("/", TRUE, $A38:$B38), 'source merged_div_data'!$A:$A, 'source merged_div_data'!F:F) & " B", XLOOKUP(TEXTJOIN("/", TRUE, $A38:$B38), 'source merged_div_data'!$A:$A, 'source merged_div_data'!F:F) < 1048576, ROUND(XLOOKUP(TEXTJOIN("/", TRUE, $A38:$B38), 'source merged_div_data'!$A:$A, 'source merged_div_data'!F:F)/1024, 2) & " KB", XLOOKUP(TEXTJOIN("/", TRUE, $A38:$B38), 'source merged_div_data'!$A:$A, 'source merged_div_data'!F:F) < 1073741824, ROUND(XLOOKUP(TEXTJOIN("/", TRUE, $A38:$B38), 'source merged_div_data'!$A:$A, 'source merged_div_data'!F:F)/1048576, 2) & " MB", TRUE, ROUND(XLOOKUP(TEXTJOIN("/", TRUE, $A38:$B38), 'source merged_div_data'!$A:$A, 'source merged_div_data'!F:F)/1073741824, 2) & " GB" ), "×" )} -> 27 B | G38: × | J38: 人事本部 | K38: × | L38: 杉村 元規 | M38: × | P38: =IFERROR(__xludf.DUMMYFUNCTION("XLOOKUP(JOIN(""/"",$A38:$B38),'source isilon_divまとめ'!$A:$A,'source isilon_divまとめ'!$D:$D,XLOOKUP(JOIN(""\"",$A38:$B38),'source NetApp-file-sv01-div'!A:A,TEXT('source NetApp-file-sv01-div'!C:C,""yyyy/mm/dd"")))"),"#N/A") -> #N/A
A39: 人事本部 | B39: 人事企画部 | C39: 合致 | D39: =IFERROR(__xludf.DUMMYFUNCTION("XLOOKUP(JOIN(""/"",$A39:$B39),'source merged_div_data'!$A:$A,'source merged_div_data'!B:B)"),19.0) -> 19 | E39: =IFERROR(__xludf.DUMMYFUNCTION("XLOOKUP(JOIN(""/"",$A39:$B39),'source merged_div_data'!$A:$A,'source merged_div_data'!C:C)"),26.0) -> 26 | F39: {=IFERROR( IFS( XLOOKUP(TEXTJOIN("/", TRUE, $A39:$B39), 'source merged_div_data'!$A:$A, 'source merged_div_data'!F:F) < 1024, XLOOKUP(TEXTJOIN("/", TRUE, $A39:$B39), 'source merged_div_data'!$A:$A, 'source merged_div_data'!F:F) & " B", XLOOKUP(TEXTJOIN("/", TRUE, $A39:$B39), 'source merged_div_data'!$A:$A, 'source merged_div_data'!F:F) < 1048576, ROUND(XLOOKUP(TEXTJOIN("/", TRUE, $A39:$B39), 'source merged_div_data'!$A:$A, 'source merged_div_data'!F:F)/1024, 2) & " KB", XLOOKUP(TEXTJOIN("/", TRUE, $A39:$B39), 'source merged_div_data'!$A:$A, 'source merged_div_data'!F:F) < 1073741824, ROUND(XLOOKUP(TEXTJOIN("/", TRUE, $A39:$B39), 'source merged_div_data'!$A:$A, 'source merged_div_data'!F:F)/1048576, 2) & " MB", TRUE, ROUND(XLOOKUP(TEXTJOIN("/", TRUE, $A39:$B39), 'source merged_div_data'!$A:$A, 'source merged_div_data'!F:F)/1073741824, 2) & " GB" ), "×" )} -> 2.37 MB | G39: 2021/05/13 | H39: AWS S3 | J39: 人事本部 | K39: × | L39: 杉村 元規 | M39: × | P39: =IFERROR(__xludf.DUMMYFUNCTION("XLOOKUP(JOIN(""/"",$A39:$B39),'source isilon_divまとめ'!$A:$A,'source isilon_divまとめ'!$D:$D,XLOOKUP(JOIN(""\"",$A39:$B39),'source NetApp-file-sv01-div'!A:A,TEXT('source NetApp-file-sv01-div'!C:C,""yyyy/mm/dd"")))"),"2021/05/13") -> 2021/05/13
A40: 人事本部 | B40: 人材開発部 | C40: 合致 | D40: =IFERROR(__xludf.DUMMYFUNCTION("XLOOKUP(JOIN(""/"",$A40:$B40),'source merged_div_data'!$A:$A,'source merged_div_data'!B:B)"),894.0) -> 894 | E40: =IFERROR(__xludf.DUMMYFUNCTION("XLOOKUP(JOIN(""/"",$A40:$B40),'source merged_div_data'!$A:$A,'source merged_div_data'!C:C)"),5215.0) -> 5215 | F40: {=IFERROR( IFS( XLOOKUP(TEXTJOIN("/", TRUE, $A40:$B40), 'source merged_div_data'!$A:$A, 'source merged_div_data'!F:F) < 1024, XLOOKUP(TEXTJOIN("/", TRUE, $A40:$B40), 'source merged_div_data'!$A:$A, 'source merged_div_data'!F:F) & " B", XLOOKUP(TEXTJOIN("/", TRUE, $A40:$B40), 'source merged_div_data'!$A:$A, 'source merged_div_data'!F:F) < 1048576, ROUND(XLOOKUP(TEXTJOIN("/", TRUE, $A40:$B40), 'source merged_div_data'!$A:$A, 'source merged_div_data'!F:F)/1024, 2) & " KB", XLOOKUP(TEXTJOIN("/", TRUE, $A40:$B40), 'source merged_div_data'!$A:$A, 'source merged_div_data'!F:F) < 1073741824, ROUND(XLOOKUP(TEXTJOIN("/", TRUE, $A40:$B40), 'source merged_div_data'!$A:$A, 'source merged_div_data'!F:F)/1048576, 2) & " MB", TRUE, ROUND(XLOOKUP(TEXTJOIN("/", TRUE, $A40:$B40), 'source merged_div_data'!$A:$A, 'source merged_div_data'!F:F)/1073741824, 2) & " GB" ), "×" )} -> 7.18 GB | G40: 2025/07/08 | H40: Googleドライブ | J40: 人事本部 | K40: 人材開発部 | L40: 杉村 元規 | M40: × | P40: =IFERROR(__xludf.DUMMYFUNCTION("XLOOKUP(JOIN(""/"",$A40:$B40),'source isilon_divまとめ'!$A:$A,'source isilon_divまとめ'!$D:$D,XLOOKUP(JOIN(""\"",$A40:$B40),'source NetApp-file-sv01-div'!A:A,TEXT('source NetApp-file-sv01-div'!C:C,""yyyy/mm/dd"")))"),"2025/07/08") -> 2025/07/08
A41: 人事本部 | B41: 人事戦略室 | C41: 0file | D41: =IFERROR(__xludf.DUMMYFUNCTION("XLOOKUP(JOIN(""/"",$A41:$B41),'source merged_div_data'!$A:$A,'source merged_div_data'!B:B)"),6.0) -> 6 | E41: =IFERROR(__xludf.DUMMYFUNCTION("XLOOKUP(JOIN(""/"",$A41:$B41),'source merged_div_data'!$A:$A,'source merged_div_data'!C:C)"),0.0) -> 0 | F41: {=IFERROR( IFS( XLOOKUP(TEXTJOIN("/", TRUE, $A41:$B41), 'source merged_div_data'!$A:$A, 'source merged_div_data'!F:F) < 1024, XLOOKUP(TEXTJOIN("/", TRUE, $A41:$B41), 'source merged_div_data'!$A:$A, 'source merged_div_data'!F:F) & " B", XLOOKUP(TEXTJOIN("/", TRUE, $A41:$B41), 'source merged_div_data'!$A:$A, 'source merged_div_data'!F:F) < 1048576, ROUND(XLOOKUP(TEXTJOIN("/", TRUE, $A41:$B41), 'source merged_div_data'!$A:$A, 'source merged_div_data'!F:F)/1024, 2) & " KB", XLOOKUP(TEXTJOIN("/", TRUE, $A41:$B41), 'source merged_div_data'!$A:$A, 'source merged_div_data'!F:F) < 1073741824, ROUND(XLOOKUP(TEXTJOIN("/", TRUE, $A41:$B41), 'source merged_div_data'!$A:$A, 'source merged_div_data'!F:F)/1048576, 2) & " MB", TRUE, ROUND(XLOOKUP(TEXTJOIN("/", TRUE, $A41:$B41), 'source merged_div_data'!$A:$A, 'source merged_div_data'!F:F)/1073741824, 2) & " GB" ), "×" )} -> 153 B | G41: × | J41: 人事本部 | K41: × | L41: 杉村 元規 | M41: × | P41: =IFERROR(__xludf.DUMMYFUNCTION("XLOOKUP(JOIN(""/"",$A41:$B41),'source isilon_divまとめ'!$A:$A,'source isilon_divまとめ'!$D:$D,XLOOKUP(JOIN(""\"",$A41:$B41),'source NetApp-file-sv01-div'!A:A,TEXT('source NetApp-file-sv01-div'!C:C,""yyyy/mm/dd"")))"),"#N/A") -> #N/A
A42: 人事本部 | B42: 人事企画部付 | C42: 0file | D42: =IFERROR(__xludf.DUMMYFUNCTION("XLOOKUP(JOIN(""/"",$A42:$B42),'source merged_div_data'!$A:$A,'source merged_div_data'!B:B)"),2.0) -> 2 | E42: =IFERROR(__xludf.DUMMYFUNCTION("XLOOKUP(JOIN(""/"",$A42:$B42),'source merged_div_data'!$A:$A,'source merged_div_data'!C:C)"),0.0) -> 0 | F42: {=IFERROR( IFS( XLOOKUP(TEXTJOIN("/", TRUE, $A42:$B42), 'source merged_div_data'!$A:$A, 'source merged_div_data'!F:F) < 1024, XLOOKUP(TEXTJOIN("/", TRUE, $A42:$B42), 'source merged_div_data'!$A:$A, 'source merged_div_data'!F:F) & " B", XLOOKUP(TEXTJOIN("/", TRUE, $A42:$B42), 'source merged_div_data'!$A:$A, 'source merged_div_data'!F:F) < 1048576, ROUND(XLOOKUP(TEXTJOIN("/", TRUE, $A42:$B42), 'source merged_div_data'!$A:$A, 'source merged_div_data'!F:F)/1024, 2) & " KB", XLOOKUP(TEXTJOIN("/", TRUE, $A42:$B42), 'source merged_div_data'!$A:$A, 'source merged_div_data'!F:F) < 1073741824, ROUND(XLOOKUP(TEXTJOIN("/", TRUE, $A42:$B42), 'source merged_div_data'!$A:$A, 'source merged_div_data'!F:F)/1048576, 2) & " MB", TRUE, ROUND(XLOOKUP(TEXTJOIN("/", TRUE, $A42:$B42), 'source merged_div_data'!$A:$A, 'source merged_div_data'!F:F)/1073741824, 2) & " GB" ), "×" )} -> 27 B | G42: × | J42: 人事本部 | K42: × | L42: 杉村 元規 | M42: × | P42: =IFERROR(__xludf.DUMMYFUNCTION("XLOOKUP(JOIN(""/"",$A42:$B42),'source isilon_divまとめ'!$A:$A,'source isilon_divまとめ'!$D:$D,XLOOKUP(JOIN(""\"",$A42:$B42),'source NetApp-file-sv01-div'!A:A,TEXT('source NetApp-file-sv01-div'!C:C,""yyyy/mm/dd"")))"),"#N/A") -> #N/A
A43: 人事本部 | B43: グループ会社サポート部 | C43: 0file | D43: =IFERROR(__xludf.DUMMYFUNCTION("XLOOKUP(JOIN(""/"",$A43:$B43),'source merged_div_data'!$A:$A,'source merged_div_data'!B:B)"),7.0) -> 7 | E43: =IFERROR(__xludf.DUMMYFUNCTION("XLOOKUP(JOIN(""/"",$A43:$B43),'source merged_div_data'!$A:$A,'source merged_div_data'!C:C)"),0.0) -> 0 | F43: {=IFERROR( IFS( XLOOKUP(TEXTJOIN("/", TRUE, $A43:$B43), 'source merged_div_data'!$A:$A, 'source merged_div_data'!F:F) < 1024, XLOOKUP(TEXTJOIN("/", TRUE, $A43:$B43), 'source merged_div_data'!$A:$A, 'source merged_div_data'!F:F) & " B", XLOOKUP(TEXTJOIN("/", TRUE, $A43:$B43), 'source merged_div_data'!$A:$A, 'source merged_div_data'!F:F) < 1048576, ROUND(XLOOKUP(TEXTJOIN("/", TRUE, $A43:$B43), 'source merged_div_data'!$A:$A, 'source merged_div_data'!F:F)/1024, 2) & " KB", XLOOKUP(TEXTJOIN("/", TRUE, $A43:$B43), 'source merged_div_data'!$A:$A, 'source merged_div_data'!F:F) < 1073741824, ROUND(XLOOKUP(TEXTJOIN("/", TRUE, $A43:$B43), 'source merged_div_data'!$A:$A, 'source merged_div_data'!F:F)/1048576, 2) & " MB", TRUE, ROUND(XLOOKUP(TEXTJOIN("/", TRUE, $A43:$B43), 'source merged_div_data'!$A:$A, 'source merged_div_data'!F:F)/1073741824, 2) & " GB" ), "×" )} -> 201 B | G43: × | J43: 人事本部 | K43: グループ会社サポート部 | L43: 杉村 元規 | M43: 中川 真紀子 | P43: =IFERROR(__xludf.DUMMYFUNCTION("XLOOKUP(JOIN(""/"",$A43:$B43),'source isilon_divまとめ'!$A:$A,'source isilon_divまとめ'!$D:$D,XLOOKUP(JOIN(""\"",$A43:$B43),'source NetApp-file-sv01-div'!A:A,TEXT('source NetApp-file-sv01-div'!C:C,""yyyy/mm/dd"")))"),"#N/A") -> #N/A
A44: 人事本部 | B44: 人材採用部 | C44: 合致 | D44: =IFERROR(__xludf.DUMMYFUNCTION("XLOOKUP(JOIN(""/"",$A44:$B44),'source merged_div_data'!$A:$A,'source merged_div_data'!B:B)"),26.0) -> 26 | E44: =IFERROR(__xludf.DUMMYFUNCTION("XLOOKUP(JOIN(""/"",$A44:$B44),'source merged_div_data'!$A:$A,'source merged_div_data'!C:C)"),30.0) -> 30 | F44: {=IFERROR( IFS( XLOOKUP(TEXTJOIN("/", TRUE, $A44:$B44), 'source merged_div_data'!$A:$A, 'source merged_div_data'!F:F) < 1024, XLOOKUP(TEXTJOIN("/", TRUE, $A44:$B44), 'source merged_div_data'!$A:$A, 'source merged_div_data'!F:F) & " B", XLOOKUP(TEXTJOIN("/", TRUE, $A44:$B44), 'source merged_div_data'!$A:$A, 'source merged_div_data'!F:F) < 1048576, ROUND(XLOOKUP(TEXTJOIN("/", TRUE, $A44:$B44), 'source merged_div_data'!$A:$A, 'source merged_div_data'!F:F)/1024, 2) & " KB", XLOOKUP(TEXTJOIN("/", TRUE, $A44:$B44), 'source merged_div_data'!$A:$A, 'source merged_div_data'!F:F) < 1073741824, ROUND(XLOOKUP(TEXTJOIN("/", TRUE, $A44:$B44), 'source merged_div_data'!$A:$A, 'source merged_div_data'!F:F)/1048576, 2) & " MB", TRUE, ROUND(XLOOKUP(TEXTJOIN("/", TRUE, $A44:$B44), 'source merged_div_data'!$A:$A, 'source merged_div_data'!F:F)/1073741824, 2) & " GB" ), "×" )} -> 4.98 MB | G44: 2022/09/30 | H44: AWS S3 | J44: {=XLOOKUP(K44,'部署遍歴'!D:D,'部署遍歴'!B:B,"×")} -> 人事本部 | K44: 人材開発部 | L44: 杉村 元規 | M44: × | P44: =IFERROR(__xludf.DUMMYFUNCTION("XLOOKUP(JOIN(""/"",$A44:$B44),'source isilon_divまとめ'!$A:$A,'source isilon_divまとめ'!$D:$D,XLOOKUP(JOIN(""\"",$A44:$B44),'source NetApp-file-sv01-div'!A:A,TEXT('source NetApp-file-sv01-div'!C:C,""yyyy/mm/dd"")))"),"2022/09/30") -> 2022/09/30
A45: 人事本部 | B45: 人材採用部付 | C45: 0file | D45: =IFERROR(__xludf.DUMMYFUNCTION("XLOOKUP(JOIN(""/"",$A45:$B45),'source merged_div_data'!$A:$A,'source merged_div_data'!B:B)"),2.0) -> 2 | E45: =IFERROR(__xludf.DUMMYFUNCTION("XLOOKUP(JOIN(""/"",$A45:$B45),'source merged_div_data'!$A:$A,'source merged_div_data'!C:C)"),0.0) -> 0 | F45: {=IFERROR( IFS( XLOOKUP(TEXTJOIN("/", TRUE, $A45:$B45), 'source merged_div_data'!$A:$A, 'source merged_div_data'!F:F) < 1024, XLOOKUP(TEXTJOIN("/", TRUE, $A45:$B45), 'source merged_div_data'!$A:$A, 'source merged_div_data'!F:F) & " B", XLOOKUP(TEXTJOIN("/", TRUE, $A45:$B45), 'source merged_div_data'!$A:$A, 'source merged_div_data'!F:F) < 1048576, ROUND(XLOOKUP(TEXTJOIN("/", TRUE, $A45:$B45), 'source merged_div_data'!$A:$A, 'source merged_div_data'!F:F)/1024, 2) & " KB", XLOOKUP(TEXTJOIN("/", TRUE, $A45:$B45), 'source merged_div_data'!$A:$A, 'source merged_div_data'!F:F) < 1073741824, ROUND(XLOOKUP(TEXTJOIN("/", TRUE, $A45:$B45), 'source merged_div_data'!$A:$A, 'source merged_div_data'!F:F)/1048576, 2) & " MB", TRUE, ROUND(XLOOKUP(TEXTJOIN("/", TRUE, $A45:$B45), 'source merged_div_data'!$A:$A, 'source merged_div_data'!F:F)/1073741824, 2) & " GB" ), "×" )} -> 27 B | G45: × | J45: 人事本部 | K45: × | L45: 杉村 元規 | M45: × | P45: =IFERROR(__xludf.DUMMYFUNCTION("XLOOKUP(JOIN(""/"",$A45:$B45),'source isilon_divまとめ'!$A:$A,'source isilon_divまとめ'!$D:$D,XLOOKUP(JOIN(""\"",$A45:$B45),'source NetApp-file-sv01-div'!A:A,TEXT('source NetApp-file-sv01-div'!C:C,""yyyy/mm/dd"")))"),"#N/A") -> #N/A
A46: 人事本部 | B46: 人事戦略部 | C46: 合致 | D46: =IFERROR(__xludf.DUMMYFUNCTION("XLOOKUP(JOIN(""/"",$A46:$B46),'source merged_div_data'!$A:$A,'source merged_div_data'!B:B)"),3705.0) -> 3705 | E46: =IFERROR(__xludf.DUMMYFUNCTION("XLOOKUP(JOIN(""/"",$A46:$B46),'source merged_div_data'!$A:$A,'source merged_div_data'!C:C)"),6381.0) -> 6381 | F46: {=IFERROR( IFS( XLOOKUP(TEXTJOIN("/", TRUE, $A46:$B46), 'source merged_div_data'!$A:$A, 'source merged_div_data'!F:F) < 1024, XLOOKUP(TEXTJOIN("/", TRUE, $A46:$B46), 'source merged_div_data'!$A:$A, 'source merged_div_data'!F:F) & " B", XLOOKUP(TEXTJOIN("/", TRUE, $A46:$B46), 'source merged_div_data'!$A:$A, 'source merged_div_data'!F:F) < 1048576, ROUND(XLOOKUP(TEXTJOIN("/", TRUE, $A46:$B46), 'source merged_div_data'!$A:$A, 'source merged_div_data'!F:F)/1024, 2) & " KB", XLOOKUP(TEXTJOIN("/", TRUE, $A46:$B46), 'source merged_div_data'!$A:$A, 'source merged_div_data'!F:F) < 1073741824, ROUND(XLOOKUP(TEXTJOIN("/", TRUE, $A46:$B46), 'source merged_div_data'!$A:$A, 'source merged_div_data'!F:F)/1048576, 2) & " MB", TRUE, ROUND(XLOOKUP(TEXTJOIN("/", TRUE, $A46:$B46), 'source merged_div_data'!$A:$A, 'source merged_div_data'!F:F)/1073741824, 2) & " GB" ), "×" )} -> 12.84 GB | G46: 2025/06/18 | H46: Googleドライブ | J46: 人事本部 | K46: 人事戦略部 | L46: 杉村 元規 | M46: 加藤 里紗 | P46: =IFERROR(__xludf.DUMMYFUNCTION("XLOOKUP(JOIN(""/"",$A46:$B46),'source isilon_divまとめ'!$A:$A,'source isilon_divまとめ'!$D:$D,XLOOKUP(JOIN(""\"",$A46:$B46),'source NetApp-file-sv01-div'!A:A,TEXT('source NetApp-file-sv01-div'!C:C,""yyyy/mm/dd"")))"),"2025/06/18") -> 2025/06/18
A47: 人事本部 | B47: 組織戦略部 | C47: 合致 | D47: =IFERROR(__xludf.DUMMYFUNCTION("XLOOKUP(JOIN(""/"",$A47:$B47),'source merged_div_data'!$A:$A,'source merged_div_data'!B:B)"),3512.0) -> 3512 | E47: =IFERROR(__xludf.DUMMYFUNCTION("XLOOKUP(JOIN(""/"",$A47:$B47),'source merged_div_data'!$A:$A,'source merged_div_data'!C:C)"),10523.0) -> 10523 | F47: {=IFERROR( IFS( XLOOKUP(TEXTJOIN("/", TRUE, $A47:$B47), 'source merged_div_data'!$A:$A, 'source merged_div_data'!F:F) < 1024, XLOOKUP(TEXTJOIN("/", TRUE, $A47:$B47), 'source merged_div_data'!$A:$A, 'source merged_div_data'!F:F) & " B", XLOOKUP(TEXTJOIN("/", TRUE, $A47:$B47), 'source merged_div_data'!$A:$A, 'source merged_div_data'!F:F) < 1048576, ROUND(XLOOKUP(TEXTJOIN("/", TRUE, $A47:$B47), 'source merged_div_data'!$A:$A, 'source merged_div_data'!F:F)/1024, 2) & " KB", XLOOKUP(TEXTJOIN("/", TRUE, $A47:$B47), 'source merged_div_data'!$A:$A, 'source merged_div_data'!F:F) < 1073741824, ROUND(XLOOKUP(TEXTJOIN("/", TRUE, $A47:$B47), 'source merged_div_data'!$A:$A, 'source merged_div_data'!F:F)/1048576, 2) & " MB", TRUE, ROUND(XLOOKUP(TEXTJOIN("/", TRUE, $A47:$B47), 'source merged_div_data'!$A:$A, 'source merged_div_data'!F:F)/1073741824, 2) & " GB" ), "×" )} -> 1.66 GB | G47: 2025/07/08 | H47: Googleドライブ | J47: 人事本部 | K47: 組織戦略部 | L47: 杉村 元規 | M47: 山本 陽司 | P47: =IFERROR(__xludf.DUMMYFUNCTION("XLOOKUP(JOIN(""/"",$A47:$B47),'source isilon_divまとめ'!$A:$A,'source isilon_divまとめ'!$D:$D,XLOOKUP(JOIN(""\"",$A47:$B47),'source NetApp-file-sv01-div'!A:A,TEXT('source NetApp-file-sv01-div'!C:C,""yyyy/mm/dd"")))"),"2025/07/08") -> 2025/07/08
A48: 人事本部 | B48: エンパワーメント推進室 | C48: 0file | D48: =IFERROR(__xludf.DUMMYFUNCTION("XLOOKUP(JOIN(""/"",$A48:$B48),'source merged_div_data'!$A:$A,'source merged_div_data'!B:B)"),11.0) -> 11 | E48: =IFERROR(__xludf.DUMMYFUNCTION("XLOOKUP(JOIN(""/"",$A48:$B48),'source merged_div_data'!$A:$A,'source merged_div_data'!C:C)"),0.0) -> 0 | F48: {=IFERROR( IFS( XLOOKUP(TEXTJOIN("/", TRUE, $A48:$B48), 'source merged_div_data'!$A:$A, 'source merged_div_data'!F:F) < 1024, XLOOKUP(TEXTJOIN("/", TRUE, $A48:$B48), 'source merged_div_data'!$A:$A, 'source merged_div_data'!F:F) & " B", XLOOKUP(TEXTJOIN("/", TRUE, $A48:$B48), 'source merged_div_data'!$A:$A, 'source merged_div_data'!F:F) < 1048576, ROUND(XLOOKUP(TEXTJOIN("/", TRUE, $A48:$B48), 'source merged_div_data'!$A:$A, 'source merged_div_data'!F:F)/1024, 2) & " KB", XLOOKUP(TEXTJOIN("/", TRUE, $A48:$B48), 'source merged_div_data'!$A:$A, 'source merged_div_data'!F:F) < 1073741824, ROUND(XLOOKUP(TEXTJOIN("/", TRUE, $A48:$B48), 'source merged_div_data'!$A:$A, 'source merged_div_data'!F:F)/1048576, 2) & " MB", TRUE, ROUND(XLOOKUP(TEXTJOIN("/", TRUE, $A48:$B48), 'source merged_div_data'!$A:$A, 'source merged_div_data'!F:F)/1073741824, 2) & " GB" ), "×" )} -> 338 B | G48: × | J48: 人事本部 | K48: エンパワーメント推進室 | L48: 杉村 元規 | M48: × | P48: =IFERROR(__xludf.DUMMYFUNCTION("XLOOKUP(JOIN(""/"",$A48:$B48),'source isilon_divまとめ'!$A:$A,'source isilon_divまとめ'!$D:$D,XLOOKUP(JOIN(""\"",$A48:$B48),'source NetApp-file-sv01-div'!A:A,TEXT('source NetApp-file-sv01-div'!C:C,""yyyy/mm/dd"")))"),"#N/A") -> #N/A
A49: 人事本部 | B49: 本部共有 | C49: 合致 | D49: =IFERROR(__xludf.DUMMYFUNCTION("XLOOKUP(JOIN(""/"",$A49:$B49),'source merged_div_data'!$A:$A,'source merged_div_data'!B:B)"),220.0) -> 220 | E49: =IFERROR(__xludf.DUMMYFUNCTION("XLOOKUP(JOIN(""/"",$A49:$B49),'source merged_div_data'!$A:$A,'source merged_div_data'!C:C)"),1083.0) -> 1083 | F49: {=IFERROR( IFS( XLOOKUP(TEXTJOIN("/", TRUE, $A49:$B49), 'source merged_div_data'!$A:$A, 'source merged_div_data'!F:F) < 1024, XLOOKUP(TEXTJOIN("/", TRUE, $A49:$B49), 'source merged_div_data'!$A:$A, 'source merged_div_data'!F:F) & " B", XLOOKUP(TEXTJOIN("/", TRUE, $A49:$B49), 'source merged_div_data'!$A:$A, 'source merged_div_data'!F:F) < 1048576, ROUND(XLOOKUP(TEXTJOIN("/", TRUE, $A49:$B49), 'source merged_div_data'!$A:$A, 'source merged_div_data'!F:F)/1024, 2) & " KB", XLOOKUP(TEXTJOIN("/", TRUE, $A49:$B49), 'source merged_div_data'!$A:$A, 'source merged_div_data'!F:F) < 1073741824, ROUND(XLOOKUP(TEXTJOIN("/", TRUE, $A49:$B49), 'source merged_div_data'!$A:$A, 'source merged_div_data'!F:F)/1048576, 2) & " MB", TRUE, ROUND(XLOOKUP(TEXTJOIN("/", TRUE, $A49:$B49), 'source merged_div_data'!$A:$A, 'source merged_div_data'!F:F)/1073741824, 2) & " GB" ), "×" )} -> 479.34 MB | G49: 2025/07/03 | H49: Googleドライブ | J49: 人事本部 | K49: × | L49: 杉村 元規 | M49: × | P49: =IFERROR(__xludf.DUMMYFUNCTION("XLOOKUP(JOIN(""/"",$A49:$B49),'source isilon_divまとめ'!$A:$A,'source isilon_divまとめ'!$D:$D,XLOOKUP(JOIN(""\"",$A49:$B49),'source NetApp-file-sv01-div'!A:A,TEXT('source NetApp-file-sv01-div'!C:C,""yyyy/mm/dd"")))"),"2025/07/03") -> 2025/07/03
A50: 人事本部 | B50: 人事部 | C50: 合致 | D50: =IFERROR(__xludf.DUMMYFUNCTION("XLOOKUP(JOIN(""/"",$A50:$B50),'source merged_div_data'!$A:$A,'source merged_div_data'!B:B)"),2477.0) -> 2477 | E50: =IFERROR(__xludf.DUMMYFUNCTION("XLOOKUP(JOIN(""/"",$A50:$B50),'source merged_div_data'!$A:$A,'source merged_div_data'!C:C)"),15890.0) -> 15890 | F50: {=IFERROR( IFS( XLOOKUP(TEXTJOIN("/", TRUE, $A50:$B50), 'source merged_div_data'!$A:$A, 'source merged_div_data'!F:F) < 1024, XLOOKUP(TEXTJOIN("/", TRUE, $A50:$B50), 'source merged_div_data'!$A:$A, 'source merged_div_data'!F:F) & " B", XLOOKUP(TEXTJOIN("/", TRUE, $A50:$B50), 'source merged_div_data'!$A:$A, 'source merged_div_data'!F:F) < 1048576, ROUND(XLOOKUP(TEXTJOIN("/", TRUE, $A50:$B50), 'source merged_div_data'!$A:$A, 'source merged_div_data'!F:F)/1024, 2) & " KB", XLOOKUP(TEXTJOIN("/", TRUE, $A50:$B50), 'source merged_div_data'!$A:$A, 'source merged_div_data'!F:F) < 1073741824, ROUND(XLOOKUP(TEXTJOIN("/", TRUE, $A50:$B50), 'source merged_div_data'!$A:$A, 'source merged_div_data'!F:F)/1048576, 2) & " MB", TRUE, ROUND(XLOOKUP(TEXTJOIN("/", TRUE, $A50:$B50), 'source merged_div_data'!$A:$A, 'source merged_div_data'!F:F)/1073741824, 2) & " GB" ), "×" )} -> 20.07 GB | G50: 2020/03/11 | H50: AWS S3 | J50: 人事本部 | K50: × | L50: 杉村 元規 | M50: × | P50: =IFERROR(__xludf.DUMMYFUNCTION("XLOOKUP(JOIN(""/"",$A50:$B50),'source isilon_divまとめ'!$A:$A,'source isilon_divまとめ'!$D:$D,XLOOKUP(JOIN(""\"",$A50:$B50),'source NetApp-file-sv01-div'!A:A,TEXT('source NetApp-file-sv01-div'!C:C,""yyyy/mm/dd"")))"),"2020/03/11") -> 2020/03/11
A51: 人事本部 | B51: 人事部付 | C51: 0file | D51: =IFERROR(__xludf.DUMMYFUNCTION("XLOOKUP(JOIN(""/"",$A51:$B51),'source merged_div_data'!$A:$A,'source merged_div_data'!B:B)"),2.0) -> 2 | E51: =IFERROR(__xludf.DUMMYFUNCTION("XLOOKUP(JOIN(""/"",$A51:$B51),'source merged_div_data'!$A:$A,'source merged_div_data'!C:C)"),0.0) -> 0 | F51: {=IFERROR( IFS( XLOOKUP(TEXTJOIN("/", TRUE, $A51:$B51), 'source merged_div_data'!$A:$A, 'source merged_div_data'!F:F) < 1024, XLOOKUP(TEXTJOIN("/", TRUE, $A51:$B51), 'source merged_div_data'!$A:$A, 'source merged_div_data'!F:F) & " B", XLOOKUP(TEXTJOIN("/", TRUE, $A51:$B51), 'source merged_div_data'!$A:$A, 'source merged_div_data'!F:F) < 1048576, ROUND(XLOOKUP(TEXTJOIN("/", TRUE, $A51:$B51), 'source merged_div_data'!$A:$A, 'source merged_div_data'!F:F)/1024, 2) & " KB", XLOOKUP(TEXTJOIN("/", TRUE, $A51:$B51), 'source merged_div_data'!$A:$A, 'source merged_div_data'!F:F) < 1073741824, ROUND(XLOOKUP(TEXTJOIN("/", TRUE, $A51:$B51), 'source merged_div_data'!$A:$A, 'source merged_div_data'!F:F)/1048576, 2) & " MB", TRUE, ROUND(XLOOKUP(TEXTJOIN("/", TRUE, $A51:$B51), 'source merged_div_data'!$A:$A, 'source merged_div_data'!F:F)/1073741824, 2) & " GB" ), "×" )} -> 27 B | G51: × | J51: 人事本部 | K51: × | L51: 杉村 元規 | M51: × | P51: =IFERROR(__xludf.DUMMYFUNCTION("XLOOKUP(JOIN(""/"",$A51:$B51),'source isilon_divまとめ'!$A:$A,'source isilon_divまとめ'!$D:$D,XLOOKUP(JOIN(""\"",$A51:$B51),'source NetApp-file-sv01-div'!A:A,TEXT('source NetApp-file-sv01-div'!C:C,""yyyy/mm/dd"")))"),"#N/A") -> #N/A
A52: 人事本部 | B52: MCS室 | C52: 0file | D52: =IFERROR(__xludf.DUMMYFUNCTION("XLOOKUP(JOIN(""/"",$A52:$B52),'source merged_div_data'!$A:$A,'source merged_div_data'!B:B)"),4.0) -> 4 | E52: =IFERROR(__xludf.DUMMYFUNCTION("XLOOKUP(JOIN(""/"",$A52:$B52),'source merged_div_data'!$A:$A,'source merged_div_data'!C:C)"),0.0) -> 0 | F52: {=IFERROR( IFS( XLOOKUP(TEXTJOIN("/", TRUE, $A52:$B52), 'source merged_div_data'!$A:$A, 'source merged_div_data'!F:F) < 1024, XLOOKUP(TEXTJOIN("/", TRUE, $A52:$B52), 'source merged_div_data'!$A:$A, 'source merged_div_data'!F:F) & " B", XLOOKUP(TEXTJOIN("/", TRUE, $A52:$B52), 'source merged_div_data'!$A:$A, 'source merged_div_data'!F:F) < 1048576, ROUND(XLOOKUP(TEXTJOIN("/", TRUE, $A52:$B52), 'source merged_div_data'!$A:$A, 'source merged_div_data'!F:F)/1024, 2) & " KB", XLOOKUP(TEXTJOIN("/", TRUE, $A52:$B52), 'source merged_div_data'!$A:$A, 'source merged_div_data'!F:F) < 1073741824, ROUND(XLOOKUP(TEXTJOIN("/", TRUE, $A52:$B52), 'source merged_div_data'!$A:$A, 'source merged_div_data'!F:F)/1048576, 2) & " MB", TRUE, ROUND(XLOOKUP(TEXTJOIN("/", TRUE, $A52:$B52), 'source merged_div_data'!$A:$A, 'source merged_div_data'!F:F)/1073741824, 2) & " GB" ), "×" )} -> 91 B | G52: × | J52: 人事本部 | K52: MCS室 | L52: 杉村 元規 | M52: 柳本 修平 | P52: =IFERROR(__xludf.DUMMYFUNCTION("XLOOKUP(JOIN(""/"",$A52:$B52),'source isilon_divまとめ'!$A:$A,'source isilon_divまとめ'!$D:$D,XLOOKUP(JOIN(""\"",$A52:$B52),'source NetApp-file-sv01-div'!A:A,TEXT('source NetApp-file-sv01-div'!C:C,""yyyy/mm/dd"")))"),"#N/A") -> #N/A
A53: コーポレートファイナンス本部 | B53: 財務企画部 | C53: 合致 | D53: =IFERROR(__xludf.DUMMYFUNCTION("XLOOKUP(JOIN(""/"",$A53:$B53),'source merged_div_data'!$A:$A,'source merged_div_data'!B:B)"),14.0) -> 14 | E53: =IFERROR(__xludf.DUMMYFUNCTION("XLOOKUP(JOIN(""/"",$A53:$B53),'source merged_div_data'!$A:$A,'source merged_div_data'!C:C)"),24.0) -> 24 | F53: {=IFERROR( IFS( XLOOKUP(TEXTJOIN("/", TRUE, $A53:$B53), 'source merged_div_data'!$A:$A, 'source merged_div_data'!F:F) < 1024, XLOOKUP(TEXTJOIN("/", TRUE, $A53:$B53), 'source merged_div_data'!$A:$A, 'source merged_div_data'!F:F) & " B", XLOOKUP(TEXTJOIN("/", TRUE, $A53:$B53), 'source merged_div_data'!$A:$A, 'source merged_div_data'!F:F) < 1048576, ROUND(XLOOKUP(TEXTJOIN("/", TRUE, $A53:$B53), 'source merged_div_data'!$A:$A, 'source merged_div_data'!F:F)/1024, 2) & " KB", XLOOKUP(TEXTJOIN("/", TRUE, $A53:$B53), 'source merged_div_data'!$A:$A, 'source merged_div_data'!F:F) < 1073741824, ROUND(XLOOKUP(TEXTJOIN("/", TRUE, $A53:$B53), 'source merged_div_data'!$A:$A, 'source merged_div_data'!F:F)/1048576, 2) & " MB", TRUE, ROUND(XLOOKUP(TEXTJOIN("/", TRUE, $A53:$B53), 'source merged_div_data'!$A:$A, 'source merged_div_data'!F:F)/1073741824, 2) & " GB" ), "×" )} -> 4.77 MB | G53: × | H53: AWS S3 | J53: コーポレートファイナンス本部 | K53: 財務企画部 | L53: 井上 慎也 | M53: × | P53: =IFERROR(__xludf.DUMMYFUNCTION("XLOOKUP(JOIN(""/"",$A53:$B53),'source isilon_divまとめ'!$A:$A,'source isilon_divまとめ'!$D:$D,XLOOKUP(JOIN(""\"",$A53:$B53),'source NetApp-file-sv01-div'!A:A,TEXT('source NetApp-file-sv01-div'!C:C,""yyyy/mm/dd"")))"),"#N/A") -> #N/A
A54: コーポレートファイナンス本部 | B54: 本部共有 | C54: 0file | D54: =IFERROR(__xludf.DUMMYFUNCTION("XLOOKUP(JOIN(""/"",$A54:$B54),'source merged_div_data'!$A:$A,'source merged_div_data'!B:B)"),1.0) -> 1 | E54: =IFERROR(__xludf.DUMMYFUNCTION("XLOOKUP(JOIN(""/"",$A54:$B54),'source merged_div_data'!$A:$A,'source merged_div_data'!C:C)"),0.0) -> 0 | F54: {=IFERROR( IFS( XLOOKUP(TEXTJOIN("/", TRUE, $A54:$B54), 'source merged_div_data'!$A:$A, 'source merged_div_data'!F:F) < 1024, XLOOKUP(TEXTJOIN("/", TRUE, $A54:$B54), 'source merged_div_data'!$A:$A, 'source merged_div_data'!F:F) & " B", XLOOKUP(TEXTJOIN("/", TRUE, $A54:$B54), 'source merged_div_data'!$A:$A, 'source merged_div_data'!F:F) < 1048576, ROUND(XLOOKUP(TEXTJOIN("/", TRUE, $A54:$B54), 'source merged_div_data'!$A:$A, 'source merged_div_data'!F:F)/1024, 2) & " KB", XLOOKUP(TEXTJOIN("/", TRUE, $A54:$B54), 'source merged_div_data'!$A:$A, 'source merged_div_data'!F:F) < 1073741824, ROUND(XLOOKUP(TEXTJOIN("/", TRUE, $A54:$B54), 'source merged_div_data'!$A:$A, 'source merged_div_data'!F:F)/1048576, 2) & " MB", TRUE, ROUND(XLOOKUP(TEXTJOIN("/", TRUE, $A54:$B54), 'source merged_div_data'!$A:$A, 'source merged_div_data'!F:F)/1073741824, 2) & " GB" ), "×" )} -> 0 B | G54: × | J54: コーポレートファイナンス本部 | K54: × | L54: 井上 慎也 | M54: × | P54: =IFERROR(__xludf.DUMMYFUNCTION("XLOOKUP(JOIN(""/"",$A54:$B54),'source isilon_divまとめ'!$A:$A,'source isilon_divまとめ'!$D:$D,XLOOKUP(JOIN(""\"",$A54:$B54),'source NetApp-file-sv01-div'!A:A,TEXT('source NetApp-file-sv01-div'!C:C,""yyyy/mm/dd"")))"),"#N/A") -> #N/A
A55: コーポレートファイナンス本部 | B55: 経理税務部 | C55: 0file | D55: =IFERROR(__xludf.DUMMYFUNCTION("XLOOKUP(JOIN(""/"",$A55:$B55),'source merged_div_data'!$A:$A,'source merged_div_data'!B:B)"),11.0) -> 11 | E55: =IFERROR(__xludf.DUMMYFUNCTION("XLOOKUP(JOIN(""/"",$A55:$B55),'source merged_div_data'!$A:$A,'source merged_div_data'!C:C)"),0.0) -> 0 | F55: {=IFERROR( IFS( XLOOKUP(TEXTJOIN("/", TRUE, $A55:$B55), 'source merged_div_data'!$A:$A, 'source merged_div_data'!F:F) < 1024, XLOOKUP(TEXTJOIN("/", TRUE, $A55:$B55), 'source merged_div_data'!$A:$A, 'source merged_div_data'!F:F) & " B", XLOOKUP(TEXTJOIN("/", TRUE, $A55:$B55), 'source merged_div_data'!$A:$A, 'source merged_div_data'!F:F) < 1048576, ROUND(XLOOKUP(TEXTJOIN("/", TRUE, $A55:$B55), 'source merged_div_data'!$A:$A, 'source merged_div_data'!F:F)/1024, 2) & " KB", XLOOKUP(TEXTJOIN("/", TRUE, $A55:$B55), 'source merged_div_data'!$A:$A, 'source merged_div_data'!F:F) < 1073741824, ROUND(XLOOKUP(TEXTJOIN("/", TRUE, $A55:$B55), 'source merged_div_data'!$A:$A, 'source merged_div_data'!F:F)/1048576, 2) & " MB", TRUE, ROUND(XLOOKUP(TEXTJOIN("/", TRUE, $A55:$B55), 'source merged_div_data'!$A:$A, 'source merged_div_data'!F:F)/1073741824, 2) & " GB" ), "×" )} -> 323 B | G55: × | J55: コーポレートファイナンス本部 | K55: 経理税務部 | L55: 井上 慎也 | M55: 望月 大輔 | P55: =IFERROR(__xludf.DUMMYFUNCTION("XLOOKUP(JOIN(""/"",$A55:$B55),'source isilon_divまとめ'!$A:$A,'source isilon_divまとめ'!$D:$D,XLOOKUP(JOIN(""\"",$A55:$B55),'source NetApp-file-sv01-div'!A:A,TEXT('source NetApp-file-sv01-div'!C:C,""yyyy/mm/dd"")))"),"#N/A") -> #N/A
A56: コーポレートデベロップメント本部 | B56: Integration Management部 | C56: 0file | D56: =IFERROR(__xludf.DUMMYFUNCTION("XLOOKUP(JOIN(""/"",$A56:$B56),'source merged_div_data'!$A:$A,'source merged_div_data'!B:B)"),2.0) -> 2 | E56: =IFERROR(__xludf.DUMMYFUNCTION("XLOOKUP(JOIN(""/"",$A56:$B56),'source merged_div_data'!$A:$A,'source merged_div_data'!C:C)"),0.0) -> 0 | F56: {=IFERROR( IFS( XLOOKUP(TEXTJOIN("/", TRUE, $A56:$B56), 'source merged_div_data'!$A:$A, 'source merged_div_data'!F:F) < 1024, XLOOKUP(TEXTJOIN("/", TRUE, $A56:$B56), 'source merged_div_data'!$A:$A, 'source merged_div_data'!F:F) & " B", XLOOKUP(TEXTJOIN("/", TRUE, $A56:$B56), 'source merged_div_data'!$A:$A, 'source merged_div_data'!F:F) < 1048576, ROUND(XLOOKUP(TEXTJOIN("/", TRUE, $A56:$B56), 'source merged_div_data'!$A:$A, 'source merged_div_data'!F:F)/1024, 2) & " KB", XLOOKUP(TEXTJOIN("/", TRUE, $A56:$B56), 'source merged_div_data'!$A:$A, 'source merged_div_data'!F:F) < 1073741824, ROUND(XLOOKUP(TEXTJOIN("/", TRUE, $A56:$B56), 'source merged_div_data'!$A:$A, 'source merged_div_data'!F:F)/1048576, 2) & " MB", TRUE, ROUND(XLOOKUP(TEXTJOIN("/", TRUE, $A56:$B56), 'source merged_div_data'!$A:$A, 'source merged_div_data'!F:F)/1073741824, 2) & " GB" ), "×" )} -> 27 B | G56: × | J56: コーポレートデベロップメント本部 | K56: Integration Management部 | L56: 荒木 豪司 | M56: 大場 大史 | P56: =IFERROR(__xludf.DUMMYFUNCTION("XLOOKUP(JOIN(""/"",$A56:$B56),'source isilon_divまとめ'!$A:$A,'source isilon_divまとめ'!$D:$D,XLOOKUP(JOIN(""\"",$A56:$B56),'source NetApp-file-sv01-div'!A:A,TEXT('source NetApp-file-sv01-div'!C:C,""yyyy/mm/dd"")))"),"#N/A") -> #N/A
A57: コーポレートデベロップメント本部 | B57: 事業開発部 | C57: 0file | D57: =IFERROR(__xludf.DUMMYFUNCTION("XLOOKUP(JOIN(""/"",$A57:$B57),'source merged_div_data'!$A:$A,'source merged_div_data'!B:B)"),8.0) -> 8 | E57: =IFERROR(__xludf.DUMMYFUNCTION("XLOOKUP(JOIN(""/"",$A57:$B57),'source merged_div_data'!$A:$A,'source merged_div_data'!C:C)"),0.0) -> 0 | F57: {=IFERROR( IFS( XLOOKUP(TEXTJOIN("/", TRUE, $A57:$B57), 'source merged_div_data'!$A:$A, 'source merged_div_data'!F:F) < 1024, XLOOKUP(TEXTJOIN("/", TRUE, $A57:$B57), 'source merged_div_data'!$A:$A, 'source merged_div_data'!F:F) & " B", XLOOKUP(TEXTJOIN("/", TRUE, $A57:$B57), 'source merged_div_data'!$A:$A, 'source merged_div_data'!F:F) < 1048576, ROUND(XLOOKUP(TEXTJOIN("/", TRUE, $A57:$B57), 'source merged_div_data'!$A:$A, 'source merged_div_data'!F:F)/1024, 2) & " KB", XLOOKUP(TEXTJOIN("/", TRUE, $A57:$B57), 'source merged_div_data'!$A:$A, 'source merged_div_data'!F:F) < 1073741824, ROUND(XLOOKUP(TEXTJOIN("/", TRUE, $A57:$B57), 'source merged_div_data'!$A:$A, 'source merged_div_data'!F:F)/1048576, 2) & " MB", TRUE, ROUND(XLOOKUP(TEXTJOIN("/", TRUE, $A57:$B57), 'source merged_div_data'!$A:$A, 'source merged_div_data'!F:F)/1073741824, 2) & " GB" ), "×" )} -> 224 B | G57: × | J57: コーポレートデベロップメント本部 | K57: × | L57: 荒木 豪司 | M57: × | P57: =IFERROR(__xludf.DUMMYFUNCTION("XLOOKUP(JOIN(""/"",$A57:$B57),'source isilon_divまとめ'!$A:$A,'source isilon_divまとめ'!$D:$D,XLOOKUP(JOIN(""\"",$A57:$B57),'source NetApp-file-sv01-div'!A:A,TEXT('source NetApp-file-sv01-div'!C:C,""yyyy/mm/dd"")))"),"#N/A") -> #N/A
A58: コーポレートデベロップメント本部 | B58: 本部共有 | C58: 0file | D58: =IFERROR(__xludf.DUMMYFUNCTION("XLOOKUP(JOIN(""/"",$A58:$B58),'source merged_div_data'!$A:$A,'source merged_div_data'!B:B)"),1.0) -> 1 | E58: =IFERROR(__xludf.DUMMYFUNCTION("XLOOKUP(JOIN(""/"",$A58:$B58),'source merged_div_data'!$A:$A,'source merged_div_data'!C:C)"),0.0) -> 0 | F58: {=IFERROR( IFS( XLOOKUP(TEXTJOIN("/", TRUE, $A58:$B58), 'source merged_div_data'!$A:$A, 'source merged_div_data'!F:F) < 1024, XLOOKUP(TEXTJOIN("/", TRUE, $A58:$B58), 'source merged_div_data'!$A:$A, 'source merged_div_data'!F:F) & " B", XLOOKUP(TEXTJOIN("/", TRUE, $A58:$B58), 'source merged_div_data'!$A:$A, 'source merged_div_data'!F:F) < 1048576, ROUND(XLOOKUP(TEXTJOIN("/", TRUE, $A58:$B58), 'source merged_div_data'!$A:$A, 'source merged_div_data'!F:F)/1024, 2) & " KB", XLOOKUP(TEXTJOIN("/", TRUE, $A58:$B58), 'source merged_div_data'!$A:$A, 'source merged_div_data'!F:F) < 1073741824, ROUND(XLOOKUP(TEXTJOIN("/", TRUE, $A58:$B58), 'source merged_div_data'!$A:$A, 'source merged_div_data'!F:F)/1048576, 2) & " MB", TRUE, ROUND(XLOOKUP(TEXTJOIN("/", TRUE, $A58:$B58), 'source merged_div_data'!$A:$A, 'source merged_div_data'!F:F)/1073741824, 2) & " GB" ), "×" )} -> 0 B | G58: × | J58: コーポレートデベロップメント本部 | K58: × | L58: 荒木 豪司 | M58: × | P58: =IFERROR(__xludf.DUMMYFUNCTION("XLOOKUP(JOIN(""/"",$A58:$B58),'source isilon_divまとめ'!$A:$A,'source isilon_divまとめ'!$D:$D,XLOOKUP(JOIN(""\"",$A58:$B58),'source NetApp-file-sv01-div'!A:A,TEXT('source NetApp-file-sv01-div'!C:C,""yyyy/mm/dd"")))"),"#N/A") -> #N/A
A59: コーポレートデベロップメント本部 | B59: 投資事業部 | C59: 0file | D59: =IFERROR(__xludf.DUMMYFUNCTION("XLOOKUP(JOIN(""/"",$A59:$B59),'source merged_div_data'!$A:$A,'source merged_div_data'!B:B)"),30.0) -> 30 | E59: =IFERROR(__xludf.DUMMYFUNCTION("XLOOKUP(JOIN(""/"",$A59:$B59),'source merged_div_data'!$A:$A,'source merged_div_data'!C:C)"),0.0) -> 0 | F59: {=IFERROR( IFS( XLOOKUP(TEXTJOIN("/", TRUE, $A59:$B59), 'source merged_div_data'!$A:$A, 'source merged_div_data'!F:F) < 1024, XLOOKUP(TEXTJOIN("/", TRUE, $A59:$B59), 'source merged_div_data'!$A:$A, 'source merged_div_data'!F:F) & " B", XLOOKUP(TEXTJOIN("/", TRUE, $A59:$B59), 'source merged_div_data'!$A:$A, 'source merged_div_data'!F:F) < 1048576, ROUND(XLOOKUP(TEXTJOIN("/", TRUE, $A59:$B59), 'source merged_div_data'!$A:$A, 'source merged_div_data'!F:F)/1024, 2) & " KB", XLOOKUP(TEXTJOIN("/", TRUE, $A59:$B59), 'source merged_div_data'!$A:$A, 'source merged_div_data'!F:F) < 1073741824, ROUND(XLOOKUP(TEXTJOIN("/", TRUE, $A59:$B59), 'source merged_div_data'!$A:$A, 'source merged_div_data'!F:F)/1048576, 2) & " MB", TRUE, ROUND(XLOOKUP(TEXTJOIN("/", TRUE, $A59:$B59), 'source merged_div_data'!$A:$A, 'source merged_div_data'!F:F)/1073741824, 2) & " GB" ), "×" )} -> 1011 B | G59: × | J59: コーポレートデベロップメント本部 | K59: 投資事業部 | L59: 荒木 豪司 | M59: × | P59: =IFERROR(__xludf.DUMMYFUNCTION("XLOOKUP(JOIN(""/"",$A59:$B59),'source isilon_divまとめ'!$A:$A,'source isilon_divまとめ'!$D:$D,XLOOKUP(JOIN(""\"",$A59:$B59),'source NetApp-file-sv01-div'!A:A,TEXT('source NetApp-file-sv01-div'!C:C,""yyyy/mm/dd"")))"),"#N/A") -> #N/A
A60: コーポレートデベロップメント本部 | B60: 事業企画推進部 | C60: 0file | D60: =IFERROR(__xludf.DUMMYFUNCTION("XLOOKUP(JOIN(""/"",$A60:$B60),'source merged_div_data'!$A:$A,'source merged_div_data'!B:B)"),9.0) -> 9 | E60: =IFERROR(__xludf.DUMMYFUNCTION("XLOOKUP(JOIN(""/"",$A60:$B60),'source merged_div_data'!$A:$A,'source merged_div_data'!C:C)"),0.0) -> 0 | F60: {=IFERROR( IFS( XLOOKUP(TEXTJOIN("/", TRUE, $A60:$B60), 'source merged_div_data'!$A:$A, 'source merged_div_data'!F:F) < 1024, XLOOKUP(TEXTJOIN("/", TRUE, $A60:$B60), 'source merged_div_data'!$A:$A, 'source merged_div_data'!F:F) & " B", XLOOKUP(TEXTJOIN("/", TRUE, $A60:$B60), 'source merged_div_data'!$A:$A, 'source merged_div_data'!F:F) < 1048576, ROUND(XLOOKUP(TEXTJOIN("/", TRUE, $A60:$B60), 'source merged_div_data'!$A:$A, 'source merged_div_data'!F:F)/1024, 2) & " KB", XLOOKUP(TEXTJOIN("/", TRUE, $A60:$B60), 'source merged_div_data'!$A:$A, 'source merged_div_data'!F:F) < 1073741824, ROUND(XLOOKUP(TEXTJOIN("/", TRUE, $A60:$B60), 'source merged_div_data'!$A:$A, 'source merged_div_data'!F:F)/1048576, 2) & " MB", TRUE, ROUND(XLOOKUP(TEXTJOIN("/", TRUE, $A60:$B60), 'source merged_div_data'!$A:$A, 'source merged_div_data'!F:F)/1073741824, 2) & " GB" ), "×" )} -> 274 B | G60: × | J60: コーポレートデベロップメント本部 | K60: 事業企画推進部 | L60: 荒木 豪司 | M60: 宇田川 浩彦 | P60: =IFERROR(__xludf.DUMMYFUNCTION("XLOOKUP(JOIN(""/"",$A60:$B60),'source isilon_divまとめ'!$A:$A,'source isilon_divまとめ'!$D:$D,XLOOKUP(JOIN(""\"",$A60:$B60),'source NetApp-file-sv01-div'!A:A,TEXT('source NetApp-file-sv01-div'!C:C,""yyyy/mm/dd"")))"),"#N/A") -> #N/A
A61: 経営企画室 | B61: 室共有 | C61: 合致 | D61: =IFERROR(__xludf.DUMMYFUNCTION("XLOOKUP(JOIN(""/"",$A61:$B61),'source merged_div_data'!$A:$A,'source merged_div_data'!B:B)"),228.0) -> 228 | E61: =IFERROR(__xludf.DUMMYFUNCTION("XLOOKUP(JOIN(""/"",$A61:$B61),'source merged_div_data'!$A:$A,'source merged_div_data'!C:C)"),1811.0) -> 1811 | F61: {=IFERROR( IFS( XLOOKUP(TEXTJOIN("/", TRUE, $A61:$B61), 'source merged_div_data'!$A:$A, 'source merged_div_data'!F:F) < 1024, XLOOKUP(TEXTJOIN("/", TRUE, $A61:$B61), 'source merged_div_data'!$A:$A, 'source merged_div_data'!F:F) & " B", XLOOKUP(TEXTJOIN("/", TRUE, $A61:$B61), 'source merged_div_data'!$A:$A, 'source merged_div_data'!F:F) < 1048576, ROUND(XLOOKUP(TEXTJOIN("/", TRUE, $A61:$B61), 'source merged_div_data'!$A:$A, 'source merged_div_data'!F:F)/1024, 2) & " KB", XLOOKUP(TEXTJOIN("/", TRUE, $A61:$B61), 'source merged_div_data'!$A:$A, 'source merged_div_data'!F:F) < 1073741824, ROUND(XLOOKUP(TEXTJOIN("/", TRUE, $A61:$B61), 'source merged_div_data'!$A:$A, 'source merged_div_data'!F:F)/1048576, 2) & " MB", TRUE, ROUND(XLOOKUP(TEXTJOIN("/", TRUE, $A61:$B61), 'source merged_div_data'!$A:$A, 'source merged_div_data'!F:F)/1073741824, 2) & " GB" ), "×" )} -> 1.44 GB | G61: 2013/09/12 | H61: AWS S3 | J61: 経営管理本部 | K61: 経営企画室 | L61: 野原 孝行 | M61: 志々目 孝広 | P61: =IFERROR(__xludf.DUMMYFUNCTION("XLOOKUP(JOIN(""/"",$A61:$B61),'source isilon_divまとめ'!$A:$A,'source isilon_divまとめ'!$D:$D,XLOOKUP(JOIN(""\"",$A61:$B61),'source NetApp-file-sv01-div'!A:A,TEXT('source NetApp-file-sv01-div'!C:C,""yyyy/mm/dd"")))"),"2013/09/12") -> 2013/09/12
A62: マーケティング本部 | B62: デジタルマーケティング室 | C62: 不明 | D62: =IFERROR(__xludf.DUMMYFUNCTION("XLOOKUP(JOIN(""/"",$A62:$B62),'source merged_div_data'!$A:$A,'source merged_div_data'!B:B)"),14.0) -> 14 | E62: =IFERROR(__xludf.DUMMYFUNCTION("XLOOKUP(JOIN(""/"",$A62:$B62),'source merged_div_data'!$A:$A,'source merged_div_data'!C:C)"),0.0) -> 0 | F62: {=IFERROR( IFS( XLOOKUP(TEXTJOIN("/", TRUE, $A62:$B62), 'source merged_div_data'!$A:$A, 'source merged_div_data'!F:F) < 1024, XLOOKUP(TEXTJOIN("/", TRUE, $A62:$B62), 'source merged_div_data'!$A:$A, 'source merged_div_data'!F:F) & " B", XLOOKUP(TEXTJOIN("/", TRUE, $A62:$B62), 'source merged_div_data'!$A:$A, 'source merged_div_data'!F:F) < 1048576, ROUND(XLOOKUP(TEXTJOIN("/", TRUE, $A62:$B62), 'source merged_div_data'!$A:$A, 'source merged_div_data'!F:F)/1024, 2) & " KB", XLOOKUP(TEXTJOIN("/", TRUE, $A62:$B62), 'source merged_div_data'!$A:$A, 'source merged_div_data'!F:F) < 1073741824, ROUND(XLOOKUP(TEXTJOIN("/", TRUE, $A62:$B62), 'source merged_div_data'!$A:$A, 'source merged_div_data'!F:F)/1048576, 2) & " MB", TRUE, ROUND(XLOOKUP(TEXTJOIN("/", TRUE, $A62:$B62), 'source merged_div_data'!$A:$A, 'source merged_div_data'!F:F)/1073741824, 2) & " GB" ), "×" )} -> 509 B | G62: × | J62: デザイン本部 / 各事業部 | L62: × | M62: × | N62: 廃止/再編 | O62: デザイン本部 / 各事業部 | P62: =IFERROR(__xludf.DUMMYFUNCTION("XLOOKUP(JOIN(""/"",$A62:$B62),'source isilon_divまとめ'!$A:$A,'source isilon_divまとめ'!$D:$D,XLOOKUP(JOIN(""\"",$A62:$B62),'source NetApp-file-sv01-div'!A:A,TEXT('source NetApp-file-sv01-div'!C:C,""yyyy/mm/dd"")))"),"#N/A") -> #N/A
A63: マーケティング本部 | B63: ブランド戦略室 | C63: 不明 | D63: =IFERROR(__xludf.DUMMYFUNCTION("XLOOKUP(JOIN(""/"",$A63:$B63),'source merged_div_data'!$A:$A,'source merged_div_data'!B:B)"),6.0) -> 6 | E63: =IFERROR(__xludf.DUMMYFUNCTION("XLOOKUP(JOIN(""/"",$A63:$B63),'source merged_div_data'!$A:$A,'source merged_div_data'!C:C)"),0.0) -> 0 | F63: {=IFERROR( IFS( XLOOKUP(TEXTJOIN("/", TRUE, $A63:$B63), 'source merged_div_data'!$A:$A, 'source merged_div_data'!F:F) < 1024, XLOOKUP(TEXTJOIN("/", TRUE, $A63:$B63), 'source merged_div_data'!$A:$A, 'source merged_div_data'!F:F) & " B", XLOOKUP(TEXTJOIN("/", TRUE, $A63:$B63), 'source merged_div_data'!$A:$A, 'source merged_div_data'!F:F) < 1048576, ROUND(XLOOKUP(TEXTJOIN("/", TRUE, $A63:$B63), 'source merged_div_data'!$A:$A, 'source merged_div_data'!F:F)/1024, 2) & " KB", XLOOKUP(TEXTJOIN("/", TRUE, $A63:$B63), 'source merged_div_data'!$A:$A, 'source merged_div_data'!F:F) < 1073741824, ROUND(XLOOKUP(TEXTJOIN("/", TRUE, $A63:$B63), 'source merged_div_data'!$A:$A, 'source merged_div_data'!F:F)/1048576, 2) & " MB", TRUE, ROUND(XLOOKUP(TEXTJOIN("/", TRUE, $A63:$B63), 'source merged_div_data'!$A:$A, 'source merged_div_data'!F:F)/1073741824, 2) & " GB" ), "×" )} -> 185 B | G63: × | J63: デザイン本部 / 各事業部 | L63: × | M63: × | N63: 廃止/再編 | O63: デザイン本部 / 各事業部 | P63: =IFERROR(__xludf.DUMMYFUNCTION("XLOOKUP(JOIN(""/"",$A63:$B63),'source isilon_divまとめ'!$A:$A,'source isilon_divまとめ'!$D:$D,XLOOKUP(JOIN(""\"",$A63:$B63),'source NetApp-file-sv01-div'!A:A,TEXT('source NetApp-file-sv01-div'!C:C,""yyyy/mm/dd"")))"),"#N/A") -> #N/A
A64: マーケティング本部 | B64: マーケティング推進室 | C64: 不明 | D64: =IFERROR(__xludf.DUMMYFUNCTION("XLOOKUP(JOIN(""/"",$A64:$B64),'source merged_div_data'!$A:$A,'source merged_div_data'!B:B)"),16.0) -> 16 | E64: =IFERROR(__xludf.DUMMYFUNCTION("XLOOKUP(JOIN(""/"",$A64:$B64),'source merged_div_data'!$A:$A,'source merged_div_data'!C:C)"),0.0) -> 0 | F64: {=IFERROR( IFS( XLOOKUP(TEXTJOIN("/", TRUE, $A64:$B64), 'source merged_div_data'!$A:$A, 'source merged_div_data'!F:F) < 1024, XLOOKUP(TEXTJOIN("/", TRUE, $A64:$B64), 'source merged_div_data'!$A:$A, 'source merged_div_data'!F:F) & " B", XLOOKUP(TEXTJOIN("/", TRUE, $A64:$B64), 'source merged_div_data'!$A:$A, 'source merged_div_data'!F:F) < 1048576, ROUND(XLOOKUP(TEXTJOIN("/", TRUE, $A64:$B64), 'source merged_div_data'!$A:$A, 'source merged_div_data'!F:F)/1024, 2) & " KB", XLOOKUP(TEXTJOIN("/", TRUE, $A64:$B64), 'source merged_div_data'!$A:$A, 'source merged_div_data'!F:F) < 1073741824, ROUND(XLOOKUP(TEXTJOIN("/", TRUE, $A64:$B64), 'source merged_div_data'!$A:$A, 'source merged_div_data'!F:F)/1048576, 2) & " MB", TRUE, ROUND(XLOOKUP(TEXTJOIN("/", TRUE, $A64:$B64), 'source merged_div_data'!$A:$A, 'source merged_div_data'!F:F)/1073741824, 2) & " GB" ), "×" )} -> 673 B | G64: × | J64: デザイン本部 / 各事業部 | L64: × | M64: × | N64: 廃止/再編 | O64: デザイン本部 / 各事業部 | P64: =IFERROR(__xludf.DUMMYFUNCTION("XLOOKUP(JOIN(""/"",$A64:$B64),'source isilon_divまとめ'!$A:$A,'source isilon_divまとめ'!$D:$D,XLOOKUP(JOIN(""\"",$A64:$B64),'source NetApp-file-sv01-div'!A:A,TEXT('source NetApp-file-sv01-div'!C:C,""yyyy/mm/dd"")))"),"#N/A") -> #N/A
A65: マーケティング本部 | B65: PR室 | C65: 不明 | D65: =IFERROR(__xludf.DUMMYFUNCTION("XLOOKUP(JOIN(""/"",$A65:$B65),'source merged_div_data'!$A:$A,'source merged_div_data'!B:B)"),5.0) -> 5 | E65: =IFERROR(__xludf.DUMMYFUNCTION("XLOOKUP(JOIN(""/"",$A65:$B65),'source merged_div_data'!$A:$A,'source merged_div_data'!C:C)"),0.0) -> 0 | F65: {=IFERROR( IFS( XLOOKUP(TEXTJOIN("/", TRUE, $A65:$B65), 'source merged_div_data'!$A:$A, 'source merged_div_data'!F:F) < 1024, XLOOKUP(TEXTJOIN("/", TRUE, $A65:$B65), 'source merged_div_data'!$A:$A, 'source merged_div_data'!F:F) & " B", XLOOKUP(TEXTJOIN("/", TRUE, $A65:$B65), 'source merged_div_data'!$A:$A, 'source merged_div_data'!F:F) < 1048576, ROUND(XLOOKUP(TEXTJOIN("/", TRUE, $A65:$B65), 'source merged_div_data'!$A:$A, 'source merged_div_data'!F:F)/1024, 2) & " KB", XLOOKUP(TEXTJOIN("/", TRUE, $A65:$B65), 'source merged_div_data'!$A:$A, 'source merged_div_data'!F:F) < 1073741824, ROUND(XLOOKUP(TEXTJOIN("/", TRUE, $A65:$B65), 'source merged_div_data'!$A:$A, 'source merged_div_data'!F:F)/1048576, 2) & " MB", TRUE, ROUND(XLOOKUP(TEXTJOIN("/", TRUE, $A65:$B65), 'source merged_div_data'!$A:$A, 'source merged_div_data'!F:F)/1073741824, 2) & " GB" ), "×" )} -> 111 B | G65: × | J65: デザイン本部 / 各事業部 | L65: × | M65: × | N65: 廃止/再編 | O65: デザイン本部 / 各事業部 | P65: =IFERROR(__xludf.DUMMYFUNCTION("XLOOKUP(JOIN(""/"",$A65:$B65),'source isilon_divまとめ'!$A:$A,'source isilon_divまとめ'!$D:$D,XLOOKUP(JOIN(""\"",$A65:$B65),'source NetApp-file-sv01-div'!A:A,TEXT('source NetApp-file-sv01-div'!C:C,""yyyy/mm/dd"")))"),"#N/A") -> #N/A
A66: マーケティング本部 | B66: 本部共有 | C66: 不明 | D66: =IFERROR(__xludf.DUMMYFUNCTION("XLOOKUP(JOIN(""/"",$A66:$B66),'source merged_div_data'!$A:$A,'source merged_div_data'!B:B)"),1.0) -> 1 | E66: =IFERROR(__xludf.DUMMYFUNCTION("XLOOKUP(JOIN(""/"",$A66:$B66),'source merged_div_data'!$A:$A,'source merged_div_data'!C:C)"),0.0) -> 0 | F66: {=IFERROR( IFS( XLOOKUP(TEXTJOIN("/", TRUE, $A66:$B66), 'source merged_div_data'!$A:$A, 'source merged_div_data'!F:F) < 1024, XLOOKUP(TEXTJOIN("/", TRUE, $A66:$B66), 'source merged_div_data'!$A:$A, 'source merged_div_data'!F:F) & " B", XLOOKUP(TEXTJOIN("/", TRUE, $A66:$B66), 'source merged_div_data'!$A:$A, 'source merged_div_data'!F:F) < 1048576, ROUND(XLOOKUP(TEXTJOIN("/", TRUE, $A66:$B66), 'source merged_div_data'!$A:$A, 'source merged_div_data'!F:F)/1024, 2) & " KB", XLOOKUP(TEXTJOIN("/", TRUE, $A66:$B66), 'source merged_div_data'!$A:$A, 'source merged_div_data'!F:F) < 1073741824, ROUND(XLOOKUP(TEXTJOIN("/", TRUE, $A66:$B66), 'source merged_div_data'!$A:$A, 'source merged_div_data'!F:F)/1048576, 2) & " MB", TRUE, ROUND(XLOOKUP(TEXTJOIN("/", TRUE, $A66:$B66), 'source merged_div_data'!$A:$A, 'source merged_div_data'!F:F)/1073741824, 2) & " GB" ), "×" )} -> 0 B | G66: × | J66: - | L66: × | M66: × | N66: 廃止/再編 | O66: - | P66: =IFERROR(__xludf.DUMMYFUNCTION("XLOOKUP(JOIN(""/"",$A66:$B66),'source isilon_divまとめ'!$A:$A,'source isilon_divまとめ'!$D:$D,XLOOKUP(JOIN(""\"",$A66:$B66),'source NetApp-file-sv01-div'!A:A,TEXT('source NetApp-file-sv01-div'!C:C,""yyyy/mm/dd"")))"),"#N/A") -> #N/A
A67: マーケティング本部 | B67: マーケティング戦略室 | C67: 仮説 | D67: =IFERROR(__xludf.DUMMYFUNCTION("XLOOKUP(JOIN(""/"",$A67:$B67),'source merged_div_data'!$A:$A,'source merged_div_data'!B:B)"),2792.0) -> 2792 | E67: =IFERROR(__xludf.DUMMYFUNCTION("XLOOKUP(JOIN(""/"",$A67:$B67),'source merged_div_data'!$A:$A,'source merged_div_data'!C:C)"),13760.0) -> 13760 | F67: {=IFERROR( IFS( XLOOKUP(TEXTJOIN("/", TRUE, $A67:$B67), 'source merged_div_data'!$A:$A, 'source merged_div_data'!F:F) < 1024, XLOOKUP(TEXTJOIN("/", TRUE, $A67:$B67), 'source merged_div_data'!$A:$A, 'source merged_div_data'!F:F) & " B", XLOOKUP(TEXTJOIN("/", TRUE, $A67:$B67), 'source merged_div_data'!$A:$A, 'source merged_div_data'!F:F) < 1048576, ROUND(XLOOKUP(TEXTJOIN("/", TRUE, $A67:$B67), 'source merged_div_data'!$A:$A, 'source merged_div_data'!F:F)/1024, 2) & " KB", XLOOKUP(TEXTJOIN("/", TRUE, $A67:$B67), 'source merged_div_data'!$A:$A, 'source merged_div_data'!F:F) < 1073741824, ROUND(XLOOKUP(TEXTJOIN("/", TRUE, $A67:$B67), 'source merged_div_data'!$A:$A, 'source merged_div_data'!F:F)/1048576, 2) & " MB", TRUE, ROUND(XLOOKUP(TEXTJOIN("/", TRUE, $A67:$B67), 'source merged_div_data'!$A:$A, 'source merged_div_data'!F:F)/1073741824, 2) & " GB" ), "×" )} -> 70.76 GB | G67: 2019/03/14 | H67: AWS S3 | J67: デジタルエンターテインメントオペレーションズ本部 | K67: 事業戦略部 | L67: × | M67: 青山 智史 | N67: 廃止/再編 | O67: デザイン本部 / 各事業部 | P67: =IFERROR(__xludf.DUMMYFUNCTION("XLOOKUP(JOIN(""/"",$A67:$B67),'source isilon_divまとめ'!$A:$A,'source isilon_divまとめ'!$D:$D,XLOOKUP(JOIN(""\"",$A67:$B67),'source NetApp-file-sv01-div'!A:A,TEXT('source NetApp-file-sv01-div'!C:C,""yyyy/mm/dd"")))"),"2019/03/14") -> 2019/03/14
A68: デザイン本部 | B68: クリエイティブ室 | C68: 仮説 | D68: =IFERROR(__xludf.DUMMYFUNCTION("XLOOKUP(JOIN(""/"",$A68:$B68),'source merged_div_data'!$A:$A,'source merged_div_data'!B:B)"),43.0) -> 43 | E68: =IFERROR(__xludf.DUMMYFUNCTION("XLOOKUP(JOIN(""/"",$A68:$B68),'source merged_div_data'!$A:$A,'source merged_div_data'!C:C)"),45.0) -> 45 | F68: {=IFERROR( IFS( XLOOKUP(TEXTJOIN("/", TRUE, $A68:$B68), 'source merged_div_data'!$A:$A, 'source merged_div_data'!F:F) < 1024, XLOOKUP(TEXTJOIN("/", TRUE, $A68:$B68), 'source merged_div_data'!$A:$A, 'source merged_div_data'!F:F) & " B", XLOOKUP(TEXTJOIN("/", TRUE, $A68:$B68), 'source merged_div_data'!$A:$A, 'source merged_div_data'!F:F) < 1048576, ROUND(XLOOKUP(TEXTJOIN("/", TRUE, $A68:$B68), 'source merged_div_data'!$A:$A, 'source merged_div_data'!F:F)/1024, 2) & " KB", XLOOKUP(TEXTJOIN("/", TRUE, $A68:$B68), 'source merged_div_data'!$A:$A, 'source merged_div_data'!F:F) < 1073741824, ROUND(XLOOKUP(TEXTJOIN("/", TRUE, $A68:$B68), 'source merged_div_data'!$A:$A, 'source merged_div_data'!F:F)/1048576, 2) & " MB", TRUE, ROUND(XLOOKUP(TEXTJOIN("/", TRUE, $A68:$B68), 'source merged_div_data'!$A:$A, 'source merged_div_data'!F:F)/1073741824, 2) & " GB" ), "×" )} -> 7.47 MB | G68: 2023/11/07 | H68: Googleドライブ | J68: デザイン本部 | K68: × | L68: 横山 義之 | M68: × | P68: =IFERROR(__xludf.DUMMYFUNCTION("XLOOKUP(JOIN(""/"",$A68:$B68),'source isilon_divまとめ'!$A:$A,'source isilon_divまとめ'!$D:$D,XLOOKUP(JOIN(""\"",$A68:$B68),'source NetApp-file-sv01-div'!A:A,TEXT('source NetApp-file-sv01-div'!C:C,""yyyy/mm/dd"")))"),"2023/11/07") -> 2023/11/07
A69: デザイン本部 | B69: 制作室 | C69: 仮説 | D69: =IFERROR(__xludf.DUMMYFUNCTION("XLOOKUP(JOIN(""/"",$A69:$B69),'source merged_div_data'!$A:$A,'source merged_div_data'!B:B)"),1044.0) -> 1044 | E69: =IFERROR(__xludf.DUMMYFUNCTION("XLOOKUP(JOIN(""/"",$A69:$B69),'source merged_div_data'!$A:$A,'source merged_div_data'!C:C)"),245586.0) -> 245586 | F69: {=IFERROR( IFS( XLOOKUP(TEXTJOIN("/", TRUE, $A69:$B69), 'source merged_div_data'!$A:$A, 'source merged_div_data'!F:F) < 1024, XLOOKUP(TEXTJOIN("/", TRUE, $A69:$B69), 'source merged_div_data'!$A:$A, 'source merged_div_data'!F:F) & " B", XLOOKUP(TEXTJOIN("/", TRUE, $A69:$B69), 'source merged_div_data'!$A:$A, 'source merged_div_data'!F:F) < 1048576, ROUND(XLOOKUP(TEXTJOIN("/", TRUE, $A69:$B69), 'source merged_div_data'!$A:$A, 'source merged_div_data'!F:F)/1024, 2) & " KB", XLOOKUP(TEXTJOIN("/", TRUE, $A69:$B69), 'source merged_div_data'!$A:$A, 'source merged_div_data'!F:F) < 1073741824, ROUND(XLOOKUP(TEXTJOIN("/", TRUE, $A69:$B69), 'source merged_div_data'!$A:$A, 'source merged_div_data'!F:F)/1048576, 2) & " MB", TRUE, ROUND(XLOOKUP(TEXTJOIN("/", TRUE, $A69:$B69), 'source merged_div_data'!$A:$A, 'source merged_div_data'!F:F)/1073741824, 2) & " GB" ), "×" )} -> 1549.98 GB | G69: 2019/03/19 | H69: AWS S3 | J69: デザイン本部 | K69: × | L69: 横山 義之 | M69: × | N69: 廃止 | P69: =IFERROR(__xludf.DUMMYFUNCTION("XLOOKUP(JOIN(""/"",$A69:$B69),'source isilon_divまとめ'!$A:$A,'source isilon_divまとめ'!$D:$D,XLOOKUP(JOIN(""\"",$A69:$B69),'source NetApp-file-sv01-div'!A:A,TEXT('source NetApp-file-sv01-div'!C:C,""yyyy/mm/dd"")))"),"2019/03/19") -> 2019/03/19
A70: デザイン本部 | B70: テクニカルデザイン室 | C70: 合致 | D70: =IFERROR(__xludf.DUMMYFUNCTION("XLOOKUP(JOIN(""/"",$A70:$B70),'source merged_div_data'!$A:$A,'source merged_div_data'!B:B)"),919.0) -> 919 | E70: =IFERROR(__xludf.DUMMYFUNCTION("XLOOKUP(JOIN(""/"",$A70:$B70),'source merged_div_data'!$A:$A,'source merged_div_data'!C:C)"),10232.0) -> 10232 | F70: {=IFERROR( IFS( XLOOKUP(TEXTJOIN("/", TRUE, $A70:$B70), 'source merged_div_data'!$A:$A, 'source merged_div_data'!F:F) < 1024, XLOOKUP(TEXTJOIN("/", TRUE, $A70:$B70), 'source merged_div_data'!$A:$A, 'source merged_div_data'!F:F) & " B", XLOOKUP(TEXTJOIN("/", TRUE, $A70:$B70), 'source merged_div_data'!$A:$A, 'source merged_div_data'!F:F) < 1048576, ROUND(XLOOKUP(TEXTJOIN("/", TRUE, $A70:$B70), 'source merged_div_data'!$A:$A, 'source merged_div_data'!F:F)/1024, 2) & " KB", XLOOKUP(TEXTJOIN("/", TRUE, $A70:$B70), 'source merged_div_data'!$A:$A, 'source merged_div_data'!F:F) < 1073741824, ROUND(XLOOKUP(TEXTJOIN("/", TRUE, $A70:$B70), 'source merged_div_data'!$A:$A, 'source merged_div_data'!F:F)/1048576, 2) & " MB", TRUE, ROUND(XLOOKUP(TEXTJOIN("/", TRUE, $A70:$B70), 'source merged_div_data'!$A:$A, 'source merged_div_data'!F:F)/1073741824, 2) & " GB" ), "×" )} -> 163.21 GB | G70: 2025/05/27 | H70: Googleドライブ | J70: ﾃﾞｻﾞｲﾝ本部 | K70: ﾃｸﾆｶﾙﾃﾞｻﾞｲﾝ室 | L70: × | M70: 谷 賢史 | P70: =IFERROR(__xludf.DUMMYFUNCTION("XLOOKUP(JOIN(""/"",$A70:$B70),'source isilon_divまとめ'!$A:$A,'source isilon_divまとめ'!$D:$D,XLOOKUP(JOIN(""\"",$A70:$B70),'source NetApp-file-sv01-div'!A:A,TEXT('source NetApp-file-sv01-div'!C:C,""yyyy/mm/dd"")))"),"2025/05/27") -> 2025/05/27
A71: デザイン本部 | B71: プロダクトデザイン室 | C71: 仮説 | D71: =IFERROR(__xludf.DUMMYFUNCTION("XLOOKUP(JOIN(""/"",$A71:$B71),'source merged_div_data'!$A:$A,'source merged_div_data'!B:B)"),43.0) -> 43 | E71: =IFERROR(__xludf.DUMMYFUNCTION("XLOOKUP(JOIN(""/"",$A71:$B71),'source merged_div_data'!$A:$A,'source merged_div_data'!C:C)"),2.0) -> 2 | F71: {=IFERROR( IFS( XLOOKUP(TEXTJOIN("/", TRUE, $A71:$B71), 'source merged_div_data'!$A:$A, 'source merged_div_data'!F:F) < 1024, XLOOKUP(TEXTJOIN("/", TRUE, $A71:$B71), 'source merged_div_data'!$A:$A, 'source merged_div_data'!F:F) & " B", XLOOKUP(TEXTJOIN("/", TRUE, $A71:$B71), 'source merged_div_data'!$A:$A, 'source merged_div_data'!F:F) < 1048576, ROUND(XLOOKUP(TEXTJOIN("/", TRUE, $A71:$B71), 'source merged_div_data'!$A:$A, 'source merged_div_data'!F:F)/1024, 2) & " KB", XLOOKUP(TEXTJOIN("/", TRUE, $A71:$B71), 'source merged_div_data'!$A:$A, 'source merged_div_data'!F:F) < 1073741824, ROUND(XLOOKUP(TEXTJOIN("/", TRUE, $A71:$B71), 'source merged_div_data'!$A:$A, 'source merged_div_data'!F:F)/1048576, 2) & " MB", TRUE, ROUND(XLOOKUP(TEXTJOIN("/", TRUE, $A71:$B71), 'source merged_div_data'!$A:$A, 'source merged_div_data'!F:F)/1073741824, 2) & " GB" ), "×" )} -> 13.73 KB | G71: × | H71: AWS S3 | J71: デザイン本部 | K71: プロダクトデザイン室 | L71: 横山 義之 | M71: × | P71: =IFERROR(__xludf.DUMMYFUNCTION("XLOOKUP(JOIN(""/"",$A71:$B71),'source isilon_divまとめ'!$A:$A,'source isilon_divまとめ'!$D:$D,XLOOKUP(JOIN(""\"",$A71:$B71),'source NetApp-file-sv01-div'!A:A,TEXT('source NetApp-file-sv01-div'!C:C,""yyyy/mm/dd"")))"),"#N/A") -> #N/A
A72: デザイン本部 | B72: ブランドデザイン室 | C72: 合致 | D72: =IFERROR(__xludf.DUMMYFUNCTION("XLOOKUP(JOIN(""/"",$A72:$B72),'source merged_div_data'!$A:$A,'source merged_div_data'!B:B)"),29.0) -> 29 | E72: =IFERROR(__xludf.DUMMYFUNCTION("XLOOKUP(JOIN(""/"",$A72:$B72),'source merged_div_data'!$A:$A,'source merged_div_data'!C:C)"),8.0) -> 8 | F72: {=IFERROR( IFS( XLOOKUP(TEXTJOIN("/", TRUE, $A72:$B72), 'source merged_div_data'!$A:$A, 'source merged_div_data'!F:F) < 1024, XLOOKUP(TEXTJOIN("/", TRUE, $A72:$B72), 'source merged_div_data'!$A:$A, 'source merged_div_data'!F:F) & " B", XLOOKUP(TEXTJOIN("/", TRUE, $A72:$B72), 'source merged_div_data'!$A:$A, 'source merged_div_data'!F:F) < 1048576, ROUND(XLOOKUP(TEXTJOIN("/", TRUE, $A72:$B72), 'source merged_div_data'!$A:$A, 'source merged_div_data'!F:F)/1024, 2) & " KB", XLOOKUP(TEXTJOIN("/", TRUE, $A72:$B72), 'source merged_div_data'!$A:$A, 'source merged_div_data'!F:F) < 1073741824, ROUND(XLOOKUP(TEXTJOIN("/", TRUE, $A72:$B72), 'source merged_div_data'!$A:$A, 'source merged_div_data'!F:F)/1048576, 2) & " MB", TRUE, ROUND(XLOOKUP(TEXTJOIN("/", TRUE, $A72:$B72), 'source merged_div_data'!$A:$A, 'source merged_div_data'!F:F)/1073741824, 2) & " GB" ), "×" )} -> 2.92 MB | G72: 2024/06/05 | H72: Googleドライブ | J72: ﾃﾞｻﾞｲﾝ本部 | K72: ﾌﾞﾗﾝﾄﾞﾃﾞｻﾞｲﾝ室 | L72: × | M72: 安井 聡史 | P72: =IFERROR(__xludf.DUMMYFUNCTION("XLOOKUP(JOIN(""/"",$A72:$B72),'source isilon_divまとめ'!$A:$A,'source isilon_divまとめ'!$D:$D,XLOOKUP(JOIN(""\"",$A72:$B72),'source NetApp-file-sv01-div'!A:A,TEXT('source NetApp-file-sv01-div'!C:C,""yyyy/mm/dd"")))"),"2024/06/05") -> 2024/06/05
A73: デザイン本部 | B73: デザイン戦略室 | C73: 仮説 | D73: =IFERROR(__xludf.DUMMYFUNCTION("XLOOKUP(JOIN(""/"",$A73:$B73),'source merged_div_data'!$A:$A,'source merged_div_data'!B:B)"),137.0) -> 137 | E73: =IFERROR(__xludf.DUMMYFUNCTION("XLOOKUP(JOIN(""/"",$A73:$B73),'source merged_div_data'!$A:$A,'source merged_div_data'!C:C)"),1031.0) -> 1031 | F73: {=IFERROR( IFS( XLOOKUP(TEXTJOIN("/", TRUE, $A73:$B73), 'source merged_div_data'!$A:$A, 'source merged_div_data'!F:F) < 1024, XLOOKUP(TEXTJOIN("/", TRUE, $A73:$B73), 'source merged_div_data'!$A:$A, 'source merged_div_data'!F:F) & " B", XLOOKUP(TEXTJOIN("/", TRUE, $A73:$B73), 'source merged_div_data'!$A:$A, 'source merged_div_data'!F:F) < 1048576, ROUND(XLOOKUP(TEXTJOIN("/", TRUE, $A73:$B73), 'source merged_div_data'!$A:$A, 'source merged_div_data'!F:F)/1024, 2) & " KB", XLOOKUP(TEXTJOIN("/", TRUE, $A73:$B73), 'source merged_div_data'!$A:$A, 'source merged_div_data'!F:F) < 1073741824, ROUND(XLOOKUP(TEXTJOIN("/", TRUE, $A73:$B73), 'source merged_div_data'!$A:$A, 'source merged_div_data'!F:F)/1048576, 2) & " MB", TRUE, ROUND(XLOOKUP(TEXTJOIN("/", TRUE, $A73:$B73), 'source merged_div_data'!$A:$A, 'source merged_div_data'!F:F)/1073741824, 2) & " GB" ), "×" )} -> 1.59 GB | G73: 2023/05/31 | H73: Googleドライブ | J73: デザイン本部 | K73: クリエイティブ室 | L73: 横山 義之 | M73: × | P73: =IFERROR(__xludf.DUMMYFUNCTION("XLOOKUP(JOIN(""/"",$A73:$B73),'source isilon_divまとめ'!$A:$A,'source isilon_divまとめ'!$D:$D,XLOOKUP(JOIN(""\"",$A73:$B73),'source NetApp-file-sv01-div'!A:A,TEXT('source NetApp-file-sv01-div'!C:C,""yyyy/mm/dd"")))"),"2023/05/31") -> 2023/05/31
A74: デザイン本部 | B74: デザイン推進室 | C74: 0file | D74: =IFERROR(__xludf.DUMMYFUNCTION("XLOOKUP(JOIN(""/"",$A74:$B74),'source merged_div_data'!$A:$A,'source merged_div_data'!B:B)"),8.0) -> 8 | E74: =IFERROR(__xludf.DUMMYFUNCTION("XLOOKUP(JOIN(""/"",$A74:$B74),'source merged_div_data'!$A:$A,'source merged_div_data'!C:C)"),0.0) -> 0 | F74: {=IFERROR( IFS( XLOOKUP(TEXTJOIN("/", TRUE, $A74:$B74), 'source merged_div_data'!$A:$A, 'source merged_div_data'!F:F) < 1024, XLOOKUP(TEXTJOIN("/", TRUE, $A74:$B74), 'source merged_div_data'!$A:$A, 'source merged_div_data'!F:F) & " B", XLOOKUP(TEXTJOIN("/", TRUE, $A74:$B74), 'source merged_div_data'!$A:$A, 'source merged_div_data'!F:F) < 1048576, ROUND(XLOOKUP(TEXTJOIN("/", TRUE, $A74:$B74), 'source merged_div_data'!$A:$A, 'source merged_div_data'!F:F)/1024, 2) & " KB", XLOOKUP(TEXTJOIN("/", TRUE, $A74:$B74), 'source merged_div_data'!$A:$A, 'source merged_div_data'!F:F) < 1073741824, ROUND(XLOOKUP(TEXTJOIN("/", TRUE, $A74:$B74), 'source merged_div_data'!$A:$A, 'source merged_div_data'!F:F)/1048576, 2) & " MB", TRUE, ROUND(XLOOKUP(TEXTJOIN("/", TRUE, $A74:$B74), 'source merged_div_data'!$A:$A, 'source merged_div_data'!F:F)/1073741824, 2) & " GB" ), "×" )} -> 321 B | G74: × | J74: ﾃﾞｻﾞｲﾝ本部 | K74: × | L74: 横山 義之 | M74: × | N74: 廃止 | P74: =IFERROR(__xludf.DUMMYFUNCTION("XLOOKUP(JOIN(""/"",$A74:$B74),'source isilon_divまとめ'!$A:$A,'source isilon_divまとめ'!$D:$D,XLOOKUP(JOIN(""\"",$A74:$B74),'source NetApp-file-sv01-div'!A:A,TEXT('source NetApp-file-sv01-div'!C:C,""yyyy/mm/dd"")))"),"#N/A") -> #N/A
A75: デザイン本部 | B75: モンストデザイン室 | C75: 0file | D75: =IFERROR(__xludf.DUMMYFUNCTION("XLOOKUP(JOIN(""/"",$A75:$B75),'source merged_div_data'!$A:$A,'source merged_div_data'!B:B)"),10.0) -> 10 | E75: =IFERROR(__xludf.DUMMYFUNCTION("XLOOKUP(JOIN(""/"",$A75:$B75),'source merged_div_data'!$A:$A,'source merged_div_data'!C:C)"),0.0) -> 0 | F75: {=IFERROR( IFS( XLOOKUP(TEXTJOIN("/", TRUE, $A75:$B75), 'source merged_div_data'!$A:$A, 'source merged_div_data'!F:F) < 1024, XLOOKUP(TEXTJOIN("/", TRUE, $A75:$B75), 'source merged_div_data'!$A:$A, 'source merged_div_data'!F:F) & " B", XLOOKUP(TEXTJOIN("/", TRUE, $A75:$B75), 'source merged_div_data'!$A:$A, 'source merged_div_data'!F:F) < 1048576, ROUND(XLOOKUP(TEXTJOIN("/", TRUE, $A75:$B75), 'source merged_div_data'!$A:$A, 'source merged_div_data'!F:F)/1024, 2) & " KB", XLOOKUP(TEXTJOIN("/", TRUE, $A75:$B75), 'source merged_div_data'!$A:$A, 'source merged_div_data'!F:F) < 1073741824, ROUND(XLOOKUP(TEXTJOIN("/", TRUE, $A75:$B75), 'source merged_div_data'!$A:$A, 'source merged_div_data'!F:F)/1048576, 2) & " MB", TRUE, ROUND(XLOOKUP(TEXTJOIN("/", TRUE, $A75:$B75), 'source merged_div_data'!$A:$A, 'source merged_div_data'!F:F)/1073741824, 2) & " GB" ), "×" )} -> 363 B | G75: × | J75: ﾃﾞｻﾞｲﾝ本部 | K75: × | L75: 横山 義之 | M75: × | P75: =IFERROR(__xludf.DUMMYFUNCTION("XLOOKUP(JOIN(""/"",$A75:$B75),'source isilon_divまとめ'!$A:$A,'source isilon_divまとめ'!$D:$D,XLOOKUP(JOIN(""\"",$A75:$B75),'source NetApp-file-sv01-div'!A:A,TEXT('source NetApp-file-sv01-div'!C:C,""yyyy/mm/dd"")))"),"#N/A") -> #N/A
A76: デザイン本部 | B76: 本部共有 | C76: 仮説 | D76: =IFERROR(__xludf.DUMMYFUNCTION("XLOOKUP(JOIN(""/"",$A76:$B76),'source merged_div_data'!$A:$A,'source merged_div_data'!B:B)"),23.0) -> 23 | E76: =IFERROR(__xludf.DUMMYFUNCTION("XLOOKUP(JOIN(""/"",$A76:$B76),'source merged_div_data'!$A:$A,'source merged_div_data'!C:C)"),244.0) -> 244 | F76: {=IFERROR( IFS( XLOOKUP(TEXTJOIN("/", TRUE, $A76:$B76), 'source merged_div_data'!$A:$A, 'source merged_div_data'!F:F) < 1024, XLOOKUP(TEXTJOIN("/", TRUE, $A76:$B76), 'source merged_div_data'!$A:$A, 'source merged_div_data'!F:F) & " B", XLOOKUP(TEXTJOIN("/", TRUE, $A76:$B76), 'source merged_div_data'!$A:$A, 'source merged_div_data'!F:F) < 1048576, ROUND(XLOOKUP(TEXTJOIN("/", TRUE, $A76:$B76), 'source merged_div_data'!$A:$A, 'source merged_div_data'!F:F)/1024, 2) & " KB", XLOOKUP(TEXTJOIN("/", TRUE, $A76:$B76), 'source merged_div_data'!$A:$A, 'source merged_div_data'!F:F) < 1073741824, ROUND(XLOOKUP(TEXTJOIN("/", TRUE, $A76:$B76), 'source merged_div_data'!$A:$A, 'source merged_div_data'!F:F)/1048576, 2) & " MB", TRUE, ROUND(XLOOKUP(TEXTJOIN("/", TRUE, $A76:$B76), 'source merged_div_data'!$A:$A, 'source merged_div_data'!F:F)/1073741824, 2) & " GB" ), "×" )} -> 32.29 GB | G76: 2023/01/31 | H76: Googleドライブ | J76: デザイン本部 | K76: × | L76: 横山 義之 | M76: × | P76: =IFERROR(__xludf.DUMMYFUNCTION("XLOOKUP(JOIN(""/"",$A76:$B76),'source isilon_divまとめ'!$A:$A,'source isilon_divまとめ'!$D:$D,XLOOKUP(JOIN(""\"",$A76:$B76),'source NetApp-file-sv01-div'!A:A,TEXT('source NetApp-file-sv01-div'!C:C,""yyyy/mm/dd"")))"),"2023/01/31") -> 2023/01/31
A77: デザイン本部 | B77: XFLAGデザイン室 | C77: 仮説 | D77: =IFERROR(__xludf.DUMMYFUNCTION("XLOOKUP(JOIN(""/"",$A77:$B77),'source merged_div_data'!$A:$A,'source merged_div_data'!B:B)"),46.0) -> 46 | E77: =IFERROR(__xludf.DUMMYFUNCTION("XLOOKUP(JOIN(""/"",$A77:$B77),'source merged_div_data'!$A:$A,'source merged_div_data'!C:C)"),7.0) -> 7 | F77: {=IFERROR( IFS( XLOOKUP(TEXTJOIN("/", TRUE, $A77:$B77), 'source merged_div_data'!$A:$A, 'source merged_div_data'!F:F) < 1024, XLOOKUP(TEXTJOIN("/", TRUE, $A77:$B77), 'source merged_div_data'!$A:$A, 'source merged_div_data'!F:F) & " B", XLOOKUP(TEXTJOIN("/", TRUE, $A77:$B77), 'source merged_div_data'!$A:$A, 'source merged_div_data'!F:F) < 1048576, ROUND(XLOOKUP(TEXTJOIN("/", TRUE, $A77:$B77), 'source merged_div_data'!$A:$A, 'source merged_div_data'!F:F)/1024, 2) & " KB", XLOOKUP(TEXTJOIN("/", TRUE, $A77:$B77), 'source merged_div_data'!$A:$A, 'source merged_div_data'!F:F) < 1073741824, ROUND(XLOOKUP(TEXTJOIN("/", TRUE, $A77:$B77), 'source merged_div_data'!$A:$A, 'source merged_div_data'!F:F)/1048576, 2) & " MB", TRUE, ROUND(XLOOKUP(TEXTJOIN("/", TRUE, $A77:$B77), 'source merged_div_data'!$A:$A, 'source merged_div_data'!F:F)/1073741824, 2) & " GB" ), "×" )} -> 95.65 MB | G77: 2018/12/20 | H77: AWS S3 | J77: デザイン本部 | K77: × | L77: 横山 義之 | M77: × | P77: =IFERROR(__xludf.DUMMYFUNCTION("XLOOKUP(JOIN(""/"",$A77:$B77),'source isilon_divまとめ'!$A:$A,'source isilon_divまとめ'!$D:$D,XLOOKUP(JOIN(""\"",$A77:$B77),'source NetApp-file-sv01-div'!A:A,TEXT('source NetApp-file-sv01-div'!C:C,""yyyy/mm/dd"")))"),"2018/12/20") -> 2018/12/20
A78: デザイン本部 | B78: 動画クリエイティブ室 | C78: 0file | D78: =IFERROR(__xludf.DUMMYFUNCTION("XLOOKUP(JOIN(""/"",$A78:$B78),'source merged_div_data'!$A:$A,'source merged_div_data'!B:B)"),52.0) -> 52 | E78: =IFERROR(__xludf.DUMMYFUNCTION("XLOOKUP(JOIN(""/"",$A78:$B78),'source merged_div_data'!$A:$A,'source merged_div_data'!C:C)"),0.0) -> 0 | F78: {=IFERROR( IFS( XLOOKUP(TEXTJOIN("/", TRUE, $A78:$B78), 'source merged_div_data'!$A:$A, 'source merged_div_data'!F:F) < 1024, XLOOKUP(TEXTJOIN("/", TRUE, $A78:$B78), 'source merged_div_data'!$A:$A, 'source merged_div_data'!F:F) & " B", XLOOKUP(TEXTJOIN("/", TRUE, $A78:$B78), 'source merged_div_data'!$A:$A, 'source merged_div_data'!F:F) < 1048576, ROUND(XLOOKUP(TEXTJOIN("/", TRUE, $A78:$B78), 'source merged_div_data'!$A:$A, 'source merged_div_data'!F:F)/1024, 2) & " KB", XLOOKUP(TEXTJOIN("/", TRUE, $A78:$B78), 'source merged_div_data'!$A:$A, 'source merged_div_data'!F:F) < 1073741824, ROUND(XLOOKUP(TEXTJOIN("/", TRUE, $A78:$B78), 'source merged_div_data'!$A:$A, 'source merged_div_data'!F:F)/1048576, 2) & " MB", TRUE, ROUND(XLOOKUP(TEXTJOIN("/", TRUE, $A78:$B78), 'source merged_div_data'!$A:$A, 'source merged_div_data'!F:F)/1073741824, 2) & " GB" ), "×" )} -> 1.97 KB | G78: × | J78: ﾃﾞｻﾞｲﾝ本部 | K78: 動画ｸﾘｴｲﾃｨﾌﾞ室 | L78: × | M78: 越智 純平 | P78: =IFERROR(__xludf.DUMMYFUNCTION("XLOOKUP(JOIN(""/"",$A78:$B78),'source isilon_divまとめ'!$A:$A,'source isilon_divまとめ'!$D:$D,XLOOKUP(JOIN(""\"",$A78:$B78),'source NetApp-file-sv01-div'!A:A,TEXT('source NetApp-file-sv01-div'!C:C,""yyyy/mm/dd"")))"),"#N/A") -> #N/A
A79: デザイン本部 | B79: XFLAG PICTURES | C79: 仮説 | D79: =IFERROR(__xludf.DUMMYFUNCTION("XLOOKUP(JOIN(""/"",$A79:$B79),'source merged_div_data'!$A:$A,'source merged_div_data'!B:B)"),366.0) -> 366 | E79: =IFERROR(__xludf.DUMMYFUNCTION("XLOOKUP(JOIN(""/"",$A79:$B79),'source merged_div_data'!$A:$A,'source merged_div_data'!C:C)"),624.0) -> 624 | F79: {=IFERROR( IFS( XLOOKUP(TEXTJOIN("/", TRUE, $A79:$B79), 'source merged_div_data'!$A:$A, 'source merged_div_data'!F:F) < 1024, XLOOKUP(TEXTJOIN("/", TRUE, $A79:$B79), 'source merged_div_data'!$A:$A, 'source merged_div_data'!F:F) & " B", XLOOKUP(TEXTJOIN("/", TRUE, $A79:$B79), 'source merged_div_data'!$A:$A, 'source merged_div_data'!F:F) < 1048576, ROUND(XLOOKUP(TEXTJOIN("/", TRUE, $A79:$B79), 'source merged_div_data'!$A:$A, 'source merged_div_data'!F:F)/1024, 2) & " KB", XLOOKUP(TEXTJOIN("/", TRUE, $A79:$B79), 'source merged_div_data'!$A:$A, 'source merged_div_data'!F:F) < 1073741824, ROUND(XLOOKUP(TEXTJOIN("/", TRUE, $A79:$B79), 'source merged_div_data'!$A:$A, 'source merged_div_data'!F:F)/1048576, 2) & " MB", TRUE, ROUND(XLOOKUP(TEXTJOIN("/", TRUE, $A79:$B79), 'source merged_div_data'!$A:$A, 'source merged_div_data'!F:F)/1073741824, 2) & " GB" ), "×" )} -> 58.75 MB | G79: 2021/01/06 | H79: AWS S3 | J79: デザイン本部 | K79: × | L79: 横山 義之 | M79: × | N79: 廃止 | P79: =IFERROR(__xludf.DUMMYFUNCTION("XLOOKUP(JOIN(""/"",$A79:$B79),'source isilon_divまとめ'!$A:$A,'source isilon_divまとめ'!$D:$D,XLOOKUP(JOIN(""\"",$A79:$B79),'source NetApp-file-sv01-div'!A:A,TEXT('source NetApp-file-sv01-div'!C:C,""yyyy/mm/dd"")))"),"2021/01/06") -> 2021/01/06
A80: デジタルエンターテインメントオペレーションズ本部 | B80: コトダマン運営部 | C80: 0file | D80: =IFERROR(__xludf.DUMMYFUNCTION("XLOOKUP(JOIN(""/"",$A80:$B80),'source merged_div_data'!$A:$A,'source merged_div_data'!B:B)"),34.0) -> 34 | E80: =IFERROR(__xludf.DUMMYFUNCTION("XLOOKUP(JOIN(""/"",$A80:$B80),'source merged_div_data'!$A:$A,'source merged_div_data'!C:C)"),0.0) -> 0 | F80: {=IFERROR( IFS( XLOOKUP(TEXTJOIN("/", TRUE, $A80:$B80), 'source merged_div_data'!$A:$A, 'source merged_div_data'!F:F) < 1024, XLOOKUP(TEXTJOIN("/", TRUE, $A80:$B80), 'source merged_div_data'!$A:$A, 'source merged_div_data'!F:F) & " B", XLOOKUP(TEXTJOIN("/", TRUE, $A80:$B80), 'source merged_div_data'!$A:$A, 'source merged_div_data'!F:F) < 1048576, ROUND(XLOOKUP(TEXTJOIN("/", TRUE, $A80:$B80), 'source merged_div_data'!$A:$A, 'source merged_div_data'!F:F)/1024, 2) & " KB", XLOOKUP(TEXTJOIN("/", TRUE, $A80:$B80), 'source merged_div_data'!$A:$A, 'source merged_div_data'!F:F) < 1073741824, ROUND(XLOOKUP(TEXTJOIN("/", TRUE, $A80:$B80), 'source merged_div_data'!$A:$A, 'source merged_div_data'!F:F)/1048576, 2) & " MB", TRUE, ROUND(XLOOKUP(TEXTJOIN("/", TRUE, $A80:$B80), 'source merged_div_data'!$A:$A, 'source merged_div_data'!F:F)/1073741824, 2) & " GB" ), "×" )} -> 1.23 KB | G80: × | J80: デジタルエンターテインメントオペレーションズ本部 | K80: ｺﾄﾀﾞﾏﾝ運営部 | L80: × | M80: 大槻 一彦 | P80: =IFERROR(__xludf.DUMMYFUNCTION("XLOOKUP(JOIN(""/"",$A80:$B80),'source isilon_divまとめ'!$A:$A,'source isilon_divまとめ'!$D:$D,XLOOKUP(JOIN(""\"",$A80:$B80),'source NetApp-file-sv01-div'!A:A,TEXT('source NetApp-file-sv01-div'!C:C,""yyyy/mm/dd"")))"),"#N/A") -> #N/A
A81: デジタルエンターテインメントオペレーションズ本部 | B81: 宣伝部 | C81: 0file | D81: =IFERROR(__xludf.DUMMYFUNCTION("XLOOKUP(JOIN(""/"",$A81:$B81),'source merged_div_data'!$A:$A,'source merged_div_data'!B:B)"),28.0) -> 28 | E81: =IFERROR(__xludf.DUMMYFUNCTION("XLOOKUP(JOIN(""/"",$A81:$B81),'source merged_div_data'!$A:$A,'source merged_div_data'!C:C)"),0.0) -> 0 | F81: {=IFERROR( IFS( XLOOKUP(TEXTJOIN("/", TRUE, $A81:$B81), 'source merged_div_data'!$A:$A, 'source merged_div_data'!F:F) < 1024, XLOOKUP(TEXTJOIN("/", TRUE, $A81:$B81), 'source merged_div_data'!$A:$A, 'source merged_div_data'!F:F) & " B", XLOOKUP(TEXTJOIN("/", TRUE, $A81:$B81), 'source merged_div_data'!$A:$A, 'source merged_div_data'!F:F) < 1048576, ROUND(XLOOKUP(TEXTJOIN("/", TRUE, $A81:$B81), 'source merged_div_data'!$A:$A, 'source merged_div_data'!F:F)/1024, 2) & " KB", XLOOKUP(TEXTJOIN("/", TRUE, $A81:$B81), 'source merged_div_data'!$A:$A, 'source merged_div_data'!F:F) < 1073741824, ROUND(XLOOKUP(TEXTJOIN("/", TRUE, $A81:$B81), 'source merged_div_data'!$A:$A, 'source merged_div_data'!F:F)/1048576, 2) & " MB", TRUE, ROUND(XLOOKUP(TEXTJOIN("/", TRUE, $A81:$B81), 'source merged_div_data'!$A:$A, 'source merged_div_data'!F:F)/1073741824, 2) & " GB" ), "×" )} -> 977 B | G81: × | J81: デジタルエンターテインメントオペレーションズ本部 | K81: 宣伝部 | L81: × | M81: 松本 太寛 | P81: =IFERROR(__xludf.DUMMYFUNCTION("XLOOKUP(JOIN(""/"",$A81:$B81),'source isilon_divまとめ'!$A:$A,'source isilon_divまとめ'!$D:$D,XLOOKUP(JOIN(""\"",$A81:$B81),'source NetApp-file-sv01-div'!A:A,TEXT('source NetApp-file-sv01-div'!C:C,""yyyy/mm/dd"")))"),"#N/A") -> #N/A
A82: デジタルエンターテインメントオペレーションズ本部 | B82: 事業戦略部 | C82: 0file | D82: =IFERROR(__xludf.DUMMYFUNCTION("XLOOKUP(JOIN(""/"",$A82:$B82),'source merged_div_data'!$A:$A,'source merged_div_data'!B:B)"),29.0) -> 29 | E82: =IFERROR(__xludf.DUMMYFUNCTION("XLOOKUP(JOIN(""/"",$A82:$B82),'source merged_div_data'!$A:$A,'source merged_div_data'!C:C)"),0.0) -> 0 | F82: {=IFERROR( IFS( XLOOKUP(TEXTJOIN("/", TRUE, $A82:$B82), 'source merged_div_data'!$A:$A, 'source merged_div_data'!F:F) < 1024, XLOOKUP(TEXTJOIN("/", TRUE, $A82:$B82), 'source merged_div_data'!$A:$A, 'source merged_div_data'!F:F) & " B", XLOOKUP(TEXTJOIN("/", TRUE, $A82:$B82), 'source merged_div_data'!$A:$A, 'source merged_div_data'!F:F) < 1048576, ROUND(XLOOKUP(TEXTJOIN("/", TRUE, $A82:$B82), 'source merged_div_data'!$A:$A, 'source merged_div_data'!F:F)/1024, 2) & " KB", XLOOKUP(TEXTJOIN("/", TRUE, $A82:$B82), 'source merged_div_data'!$A:$A, 'source merged_div_data'!F:F) < 1073741824, ROUND(XLOOKUP(TEXTJOIN("/", TRUE, $A82:$B82), 'source merged_div_data'!$A:$A, 'source merged_div_data'!F:F)/1048576, 2) & " MB", TRUE, ROUND(XLOOKUP(TEXTJOIN("/", TRUE, $A82:$B82), 'source merged_div_data'!$A:$A, 'source merged_div_data'!F:F)/1073741824, 2) & " GB" ), "×" )} -> 901 B | G82: × | J82: デジタルエンターテインメントオペレーションズ本部 | K82: 事業戦略部 | L82: × | M82: 青山 智史 | P82: =IFERROR(__xludf.DUMMYFUNCTION("XLOOKUP(JOIN(""/"",$A82:$B82),'source isilon_divまとめ'!$A:$A,'source isilon_divまとめ'!$D:$D,XLOOKUP(JOIN(""\"",$A82:$B82),'source NetApp-file-sv01-div'!A:A,TEXT('source NetApp-file-sv01-div'!C:C,""yyyy/mm/dd"")))"),"#N/A") -> #N/A
A83: デジタルエンターテインメントオペレーションズ本部 | B83: コトダマン制作部 | C83: 0file | D83: =IFERROR(__xludf.DUMMYFUNCTION("XLOOKUP(JOIN(""/"",$A83:$B83),'source merged_div_data'!$A:$A,'source merged_div_data'!B:B)"),24.0) -> 24 | E83: =IFERROR(__xludf.DUMMYFUNCTION("XLOOKUP(JOIN(""/"",$A83:$B83),'source merged_div_data'!$A:$A,'source merged_div_data'!C:C)"),0.0) -> 0 | F83: {=IFERROR( IFS( XLOOKUP(TEXTJOIN("/", TRUE, $A83:$B83), 'source merged_div_data'!$A:$A, 'source merged_div_data'!F:F) < 1024, XLOOKUP(TEXTJOIN("/", TRUE, $A83:$B83), 'source merged_div_data'!$A:$A, 'source merged_div_data'!F:F) & " B", XLOOKUP(TEXTJOIN("/", TRUE, $A83:$B83), 'source merged_div_data'!$A:$A, 'source merged_div_data'!F:F) < 1048576, ROUND(XLOOKUP(TEXTJOIN("/", TRUE, $A83:$B83), 'source merged_div_data'!$A:$A, 'source merged_div_data'!F:F)/1024, 2) & " KB", XLOOKUP(TEXTJOIN("/", TRUE, $A83:$B83), 'source merged_div_data'!$A:$A, 'source merged_div_data'!F:F) < 1073741824, ROUND(XLOOKUP(TEXTJOIN("/", TRUE, $A83:$B83), 'source merged_div_data'!$A:$A, 'source merged_div_data'!F:F)/1048576, 2) & " MB", TRUE, ROUND(XLOOKUP(TEXTJOIN("/", TRUE, $A83:$B83), 'source merged_div_data'!$A:$A, 'source merged_div_data'!F:F)/1073741824, 2) & " GB" ), "×" )} -> 791 B | G83: × | J83: デジタルエンターテインメントオペレーションズ本部 | K83: ｺﾄﾀﾞﾏﾝ制作部 | L83: × | M83: 髙橋 勇太 | P83: =IFERROR(__xludf.DUMMYFUNCTION("XLOOKUP(JOIN(""/"",$A83:$B83),'source isilon_divまとめ'!$A:$A,'source isilon_divまとめ'!$D:$D,XLOOKUP(JOIN(""\"",$A83:$B83),'source NetApp-file-sv01-div'!A:A,TEXT('source NetApp-file-sv01-div'!C:C,""yyyy/mm/dd"")))"),"#N/A") -> #N/A
A84: デジタルエンターテインメントオペレーションズ本部 | B84: モンスト開発部 | C84: 0file | D84: =IFERROR(__xludf.DUMMYFUNCTION("XLOOKUP(JOIN(""/"",$A84:$B84),'source merged_div_data'!$A:$A,'source merged_div_data'!B:B)"),41.0) -> 41 | E84: =IFERROR(__xludf.DUMMYFUNCTION("XLOOKUP(JOIN(""/"",$A84:$B84),'source merged_div_data'!$A:$A,'source merged_div_data'!C:C)"),0.0) -> 0 | F84: {=IFERROR( IFS( XLOOKUP(TEXTJOIN("/", TRUE, $A84:$B84), 'source merged_div_data'!$A:$A, 'source merged_div_data'!F:F) < 1024, XLOOKUP(TEXTJOIN("/", TRUE, $A84:$B84), 'source merged_div_data'!$A:$A, 'source merged_div_data'!F:F) & " B", XLOOKUP(TEXTJOIN("/", TRUE, $A84:$B84), 'source merged_div_data'!$A:$A, 'source merged_div_data'!F:F) < 1048576, ROUND(XLOOKUP(TEXTJOIN("/", TRUE, $A84:$B84), 'source merged_div_data'!$A:$A, 'source merged_div_data'!F:F)/1024, 2) & " KB", XLOOKUP(TEXTJOIN("/", TRUE, $A84:$B84), 'source merged_div_data'!$A:$A, 'source merged_div_data'!F:F) < 1073741824, ROUND(XLOOKUP(TEXTJOIN("/", TRUE, $A84:$B84), 'source merged_div_data'!$A:$A, 'source merged_div_data'!F:F)/1048576, 2) & " MB", TRUE, ROUND(XLOOKUP(TEXTJOIN("/", TRUE, $A84:$B84), 'source merged_div_data'!$A:$A, 'source merged_div_data'!F:F)/1073741824, 2) & " GB" ), "×" )} -> 1.33 KB | G84: × | J84: デジタルエンターテインメントオペレーションズ本部 | K84: ﾓﾝｽﾄ開発部 | L84: × | M84: 岡本 勇太 | P84: =IFERROR(__xludf.DUMMYFUNCTION("XLOOKUP(JOIN(""/"",$A84:$B84),'source isilon_divまとめ'!$A:$A,'source isilon_divまとめ'!$D:$D,XLOOKUP(JOIN(""\"",$A84:$B84),'source NetApp-file-sv01-div'!A:A,TEXT('source NetApp-file-sv01-div'!C:C,""yyyy/mm/dd"")))"),"#N/A") -> #N/A
A85: デジタルエンターテインメントオペレーションズ本部 | B85: 本部共有 | C85: 0file | D85: =IFERROR(__xludf.DUMMYFUNCTION("XLOOKUP(JOIN(""/"",$A85:$B85),'source merged_div_data'!$A:$A,'source merged_div_data'!B:B)"),1.0) -> 1 | E85: =IFERROR(__xludf.DUMMYFUNCTION("XLOOKUP(JOIN(""/"",$A85:$B85),'source merged_div_data'!$A:$A,'source merged_div_data'!C:C)"),0.0) -> 0 | F85: {=IFERROR( IFS( XLOOKUP(TEXTJOIN("/", TRUE, $A85:$B85), 'source merged_div_data'!$A:$A, 'source merged_div_data'!F:F) < 1024, XLOOKUP(TEXTJOIN("/", TRUE, $A85:$B85), 'source merged_div_data'!$A:$A, 'source merged_div_data'!F:F) & " B", XLOOKUP(TEXTJOIN("/", TRUE, $A85:$B85), 'source merged_div_data'!$A:$A, 'source merged_div_data'!F:F) < 1048576, ROUND(XLOOKUP(TEXTJOIN("/", TRUE, $A85:$B85), 'source merged_div_data'!$A:$A, 'source merged_div_data'!F:F)/1024, 2) & " KB", XLOOKUP(TEXTJOIN("/", TRUE, $A85:$B85), 'source merged_div_data'!$A:$A, 'source merged_div_data'!F:F) < 1073741824, ROUND(XLOOKUP(TEXTJOIN("/", TRUE, $A85:$B85), 'source merged_div_data'!$A:$A, 'source merged_div_data'!F:F)/1048576, 2) & " MB", TRUE, ROUND(XLOOKUP(TEXTJOIN("/", TRUE, $A85:$B85), 'source merged_div_data'!$A:$A, 'source merged_div_data'!F:F)/1073741824, 2) & " GB" ), "×" )} -> 0 B | G85: × | J85: デジタルエンターテインメントオペレーションズ本部 | K85: × | L85: 三島 圭介 | M85: × | P85: =IFERROR(__xludf.DUMMYFUNCTION("XLOOKUP(JOIN(""/"",$A85:$B85),'source isilon_divまとめ'!$A:$A,'source isilon_divまとめ'!$D:$D,XLOOKUP(JOIN(""\"",$A85:$B85),'source NetApp-file-sv01-div'!A:A,TEXT('source NetApp-file-sv01-div'!C:C,""yyyy/mm/dd"")))"),"#N/A") -> #N/A
A86: デジタルエンターテインメントオペレーションズ本部 | B86: ファンマーケティング部 | C86: 0file | D86: =IFERROR(__xludf.DUMMYFUNCTION("XLOOKUP(JOIN(""/"",$A86:$B86),'source merged_div_data'!$A:$A,'source merged_div_data'!B:B)"),29.0) -> 29 | E86: =IFERROR(__xludf.DUMMYFUNCTION("XLOOKUP(JOIN(""/"",$A86:$B86),'source merged_div_data'!$A:$A,'source merged_div_data'!C:C)"),0.0) -> 0 | F86: {=IFERROR( IFS( XLOOKUP(TEXTJOIN("/", TRUE, $A86:$B86), 'source merged_div_data'!$A:$A, 'source merged_div_data'!F:F) < 1024, XLOOKUP(TEXTJOIN("/", TRUE, $A86:$B86), 'source merged_div_data'!$A:$A, 'source merged_div_data'!F:F) & " B", XLOOKUP(TEXTJOIN("/", TRUE, $A86:$B86), 'source merged_div_data'!$A:$A, 'source merged_div_data'!F:F) < 1048576, ROUND(XLOOKUP(TEXTJOIN("/", TRUE, $A86:$B86), 'source merged_div_data'!$A:$A, 'source merged_div_data'!F:F)/1024, 2) & " KB", XLOOKUP(TEXTJOIN("/", TRUE, $A86:$B86), 'source merged_div_data'!$A:$A, 'source merged_div_data'!F:F) < 1073741824, ROUND(XLOOKUP(TEXTJOIN("/", TRUE, $A86:$B86), 'source merged_div_data'!$A:$A, 'source merged_div_data'!F:F)/1048576, 2) & " MB", TRUE, ROUND(XLOOKUP(TEXTJOIN("/", TRUE, $A86:$B86), 'source merged_div_data'!$A:$A, 'source merged_div_data'!F:F)/1073741824, 2) & " GB" ), "×" )} -> 999 B | G86: × | J86: デジタルエンターテインメントオペレーションズ本部 | K86: ファンマーケティング部 | L86: × | M86: 吉永 英恵 | P86: =IFERROR(__xludf.DUMMYFUNCTION("XLOOKUP(JOIN(""/"",$A86:$B86),'source isilon_divまとめ'!$A:$A,'source isilon_divまとめ'!$D:$D,XLOOKUP(JOIN(""\"",$A86:$B86),'source NetApp-file-sv01-div'!A:A,TEXT('source NetApp-file-sv01-div'!C:C,""yyyy/mm/dd"")))"),"#N/A") -> #N/A
A87: デジタルエンターテインメントオペレーションズ本部 | B87: モンスト運営部 | C87: 0file | D87: =IFERROR(__xludf.DUMMYFUNCTION("XLOOKUP(JOIN(""/"",$A87:$B87),'source merged_div_data'!$A:$A,'source merged_div_data'!B:B)"),44.0) -> 44 | E87: =IFERROR(__xludf.DUMMYFUNCTION("XLOOKUP(JOIN(""/"",$A87:$B87),'source merged_div_data'!$A:$A,'source merged_div_data'!C:C)"),0.0) -> 0 | F87: {=IFERROR( IFS( XLOOKUP(TEXTJOIN("/", TRUE, $A87:$B87), 'source merged_div_data'!$A:$A, 'source merged_div_data'!F:F) < 1024, XLOOKUP(TEXTJOIN("/", TRUE, $A87:$B87), 'source merged_div_data'!$A:$A, 'source merged_div_data'!F:F) & " B", XLOOKUP(TEXTJOIN("/", TRUE, $A87:$B87), 'source merged_div_data'!$A:$A, 'source merged_div_data'!F:F) < 1048576, ROUND(XLOOKUP(TEXTJOIN("/", TRUE, $A87:$B87), 'source merged_div_data'!$A:$A, 'source merged_div_data'!F:F)/1024, 2) & " KB", XLOOKUP(TEXTJOIN("/", TRUE, $A87:$B87), 'source merged_div_data'!$A:$A, 'source merged_div_data'!F:F) < 1073741824, ROUND(XLOOKUP(TEXTJOIN("/", TRUE, $A87:$B87), 'source merged_div_data'!$A:$A, 'source merged_div_data'!F:F)/1048576, 2) & " MB", TRUE, ROUND(XLOOKUP(TEXTJOIN("/", TRUE, $A87:$B87), 'source merged_div_data'!$A:$A, 'source merged_div_data'!F:F)/1073741824, 2) & " GB" ), "×" )} -> 1.34 KB | G87: × | J87: デジタルエンターテインメントオペレーションズ本部 | K87: ﾓﾝｽﾄ運営部 | L87: × | M87: 照内 大丈 | P87: =IFERROR(__xludf.DUMMYFUNCTION("XLOOKUP(JOIN(""/"",$A87:$B87),'source isilon_divまとめ'!$A:$A,'source isilon_divまとめ'!$D:$D,XLOOKUP(JOIN(""\"",$A87:$B87),'source NetApp-file-sv01-div'!A:A,TEXT('source NetApp-file-sv01-div'!C:C,""yyyy/mm/dd"")))"),"#N/A") -> #N/A
A88: デジタルエンターテインメントオペレーションズ本部 | B88: コトダマン事業部 | C88: 0file | D88: =IFERROR(__xludf.DUMMYFUNCTION("XLOOKUP(JOIN(""/"",$A88:$B88),'source merged_div_data'!$A:$A,'source merged_div_data'!B:B)"),70.0) -> 70 | E88: =IFERROR(__xludf.DUMMYFUNCTION("XLOOKUP(JOIN(""/"",$A88:$B88),'source merged_div_data'!$A:$A,'source merged_div_data'!C:C)"),0.0) -> 0 | F88: {=IFERROR( IFS( XLOOKUP(TEXTJOIN("/", TRUE, $A88:$B88), 'source merged_div_data'!$A:$A, 'source merged_div_data'!F:F) < 1024, XLOOKUP(TEXTJOIN("/", TRUE, $A88:$B88), 'source merged_div_data'!$A:$A, 'source merged_div_data'!F:F) & " B", XLOOKUP(TEXTJOIN("/", TRUE, $A88:$B88), 'source merged_div_data'!$A:$A, 'source merged_div_data'!F:F) < 1048576, ROUND(XLOOKUP(TEXTJOIN("/", TRUE, $A88:$B88), 'source merged_div_data'!$A:$A, 'source merged_div_data'!F:F)/1024, 2) & " KB", XLOOKUP(TEXTJOIN("/", TRUE, $A88:$B88), 'source merged_div_data'!$A:$A, 'source merged_div_data'!F:F) < 1073741824, ROUND(XLOOKUP(TEXTJOIN("/", TRUE, $A88:$B88), 'source merged_div_data'!$A:$A, 'source merged_div_data'!F:F)/1048576, 2) & " MB", TRUE, ROUND(XLOOKUP(TEXTJOIN("/", TRUE, $A88:$B88), 'source merged_div_data'!$A:$A, 'source merged_div_data'!F:F)/1073741824, 2) & " GB" ), "×" )} -> 2.43 KB | G88: × | J88: {=XLOOKUP(K88,'部署遍歴'!D:D,'部署遍歴'!B:B,"×")} -> デジタルエンターテインメントオペレーションズ本部 | K88: コトダマン運営部 | L88: 三島 圭介 | M88: × | P88: =IFERROR(__xludf.DUMMYFUNCTION("XLOOKUP(JOIN(""/"",$A88:$B88),'source isilon_divまとめ'!$A:$A,'source isilon_divまとめ'!$D:$D,XLOOKUP(JOIN(""\"",$A88:$B88),'source NetApp-file-sv01-div'!A:A,TEXT('source NetApp-file-sv01-div'!C:C,""yyyy/mm/dd"")))"),"#N/A") -> #N/A
A89: デジタルエンターテインメントオペレーションズ本部 | B89: モンストIPクリエイション部 | C89: 0file | D89: =IFERROR(__xludf.DUMMYFUNCTION("XLOOKUP(JOIN(""/"",$A89:$B89),'source merged_div_data'!$A:$A,'source merged_div_data'!B:B)"),43.0) -> 43 | E89: =IFERROR(__xludf.DUMMYFUNCTION("XLOOKUP(JOIN(""/"",$A89:$B89),'source merged_div_data'!$A:$A,'source merged_div_data'!C:C)"),0.0) -> 0 | F89: {=IFERROR( IFS( XLOOKUP(TEXTJOIN("/", TRUE, $A89:$B89), 'source merged_div_data'!$A:$A, 'source merged_div_data'!F:F) < 1024, XLOOKUP(TEXTJOIN("/", TRUE, $A89:$B89), 'source merged_div_data'!$A:$A, 'source merged_div_data'!F:F) & " B", XLOOKUP(TEXTJOIN("/", TRUE, $A89:$B89), 'source merged_div_data'!$A:$A, 'source merged_div_data'!F:F) < 1048576, ROUND(XLOOKUP(TEXTJOIN("/", TRUE, $A89:$B89), 'source merged_div_data'!$A:$A, 'source merged_div_data'!F:F)/1024, 2) & " KB", XLOOKUP(TEXTJOIN("/", TRUE, $A89:$B89), 'source merged_div_data'!$A:$A, 'source merged_div_data'!F:F) < 1073741824, ROUND(XLOOKUP(TEXTJOIN("/", TRUE, $A89:$B89), 'source merged_div_data'!$A:$A, 'source merged_div_data'!F:F)/1048576, 2) & " MB", TRUE, ROUND(XLOOKUP(TEXTJOIN("/", TRUE, $A89:$B89), 'source merged_div_data'!$A:$A, 'source merged_div_data'!F:F)/1073741824, 2) & " GB" ), "×" )} -> 1.36 KB | G89: × | J89: デジタルエンターテインメントオペレーションズ本部 | K89: ﾓﾝｽﾄIPｸﾘｴｲｼｮﾝ部 | L89: × | M89: 砂村 哲平 | P89: =IFERROR(__xludf.DUMMYFUNCTION("XLOOKUP(JOIN(""/"",$A89:$B89),'source isilon_divまとめ'!$A:$A,'source isilon_divまとめ'!$D:$D,XLOOKUP(JOIN(""\"",$A89:$B89),'source NetApp-file-sv01-div'!A:A,TEXT('source NetApp-file-sv01-div'!C:C,""yyyy/mm/dd"")))"),"#N/A") -> #N/A
A90: アイ・マーキュリーキャピタル | B90: 全社共有 | C90: 不明 | D90: =IFERROR(__xludf.DUMMYFUNCTION("XLOOKUP(JOIN(""/"",$A90:$B90),'source merged_div_data'!$A:$A,'source merged_div_data'!B:B)"),1.0) -> 1 | E90: =IFERROR(__xludf.DUMMYFUNCTION("XLOOKUP(JOIN(""/"",$A90:$B90),'source merged_div_data'!$A:$A,'source merged_div_data'!C:C)"),0.0) -> 0 | F90: {=IFERROR( IFS( XLOOKUP(TEXTJOIN("/", TRUE, $A90:$B90), 'source merged_div_data'!$A:$A, 'source merged_div_data'!F:F) < 1024, XLOOKUP(TEXTJOIN("/", TRUE, $A90:$B90), 'source merged_div_data'!$A:$A, 'source merged_div_data'!F:F) & " B", XLOOKUP(TEXTJOIN("/", TRUE, $A90:$B90), 'source merged_div_data'!$A:$A, 'source merged_div_data'!F:F) < 1048576, ROUND(XLOOKUP(TEXTJOIN("/", TRUE, $A90:$B90), 'source merged_div_data'!$A:$A, 'source merged_div_data'!F:F)/1024, 2) & " KB", XLOOKUP(TEXTJOIN("/", TRUE, $A90:$B90), 'source merged_div_data'!$A:$A, 'source merged_div_data'!F:F) < 1073741824, ROUND(XLOOKUP(TEXTJOIN("/", TRUE, $A90:$B90), 'source merged_div_data'!$A:$A, 'source merged_div_data'!F:F)/1048576, 2) & " MB", TRUE, ROUND(XLOOKUP(TEXTJOIN("/", TRUE, $A90:$B90), 'source merged_div_data'!$A:$A, 'source merged_div_data'!F:F)/1073741824, 2) & " GB" ), "×" )} -> 0 B | G90: × | J90: 株式会社アイ・マーキュリーキャピタル | L90: × | M90: × | N90: 存続 (子会社) | O90: 株式会社アイ・マーキュリーキャピタル | P90: =IFERROR(__xludf.DUMMYFUNCTION("XLOOKUP(JOIN(""/"",$A90:$B90),'source isilon_divまとめ'!$A:$A,'source isilon_divまとめ'!$D:$D,XLOOKUP(JOIN(""\"",$A90:$B90),'source NetApp-file-sv01-div'!A:A,TEXT('source NetApp-file-sv01-div'!C:C,""yyyy/mm/dd"")))"),"#N/A") -> #N/A
A91: エックスフラッグスタジオ本部 | B91: アドテク部 | C91: 不明 | D91: =IFERROR(__xludf.DUMMYFUNCTION("XLOOKUP(JOIN(""/"",$A91:$B91),'source merged_div_data'!$A:$A,'source merged_div_data'!B:B)"),13.0) -> 13 | E91: =IFERROR(__xludf.DUMMYFUNCTION("XLOOKUP(JOIN(""/"",$A91:$B91),'source merged_div_data'!$A:$A,'source merged_div_data'!C:C)"),4.0) -> 4 | F91: {=IFERROR( IFS( XLOOKUP(TEXTJOIN("/", TRUE, $A91:$B91), 'source merged_div_data'!$A:$A, 'source merged_div_data'!F:F) < 1024, XLOOKUP(TEXTJOIN("/", TRUE, $A91:$B91), 'source merged_div_data'!$A:$A, 'source merged_div_data'!F:F) & " B", XLOOKUP(TEXTJOIN("/", TRUE, $A91:$B91), 'source merged_div_data'!$A:$A, 'source merged_div_data'!F:F) < 1048576, ROUND(XLOOKUP(TEXTJOIN("/", TRUE, $A91:$B91), 'source merged_div_data'!$A:$A, 'source merged_div_data'!F:F)/1024, 2) & " KB", XLOOKUP(TEXTJOIN("/", TRUE, $A91:$B91), 'source merged_div_data'!$A:$A, 'source merged_div_data'!F:F) < 1073741824, ROUND(XLOOKUP(TEXTJOIN("/", TRUE, $A91:$B91), 'source merged_div_data'!$A:$A, 'source merged_div_data'!F:F)/1048576, 2) & " MB", TRUE, ROUND(XLOOKUP(TEXTJOIN("/", TRUE, $A91:$B91), 'source merged_div_data'!$A:$A, 'source merged_div_data'!F:F)/1073741824, 2) & " GB" ), "×" )} -> 1.74 GB | G91: 2016/07/05 | H91: AWS S3 | J91: 開発本部 / デザイン本部 | L91: × | M91: × | N91: 廃止/再編 | O91: 開発本部 / デザイン本部 | P91: =IFERROR(__xludf.DUMMYFUNCTION("XLOOKUP(JOIN(""/"",$A91:$B91),'source isilon_divまとめ'!$A:$A,'source isilon_divまとめ'!$D:$D,XLOOKUP(JOIN(""\"",$A91:$B91),'source NetApp-file-sv01-div'!A:A,TEXT('source NetApp-file-sv01-div'!C:C,""yyyy/mm/dd"")))"),"2016/07/05") -> 2016/07/05
A92: エックスフラッグスタジオ本部 | B92: 企画・運用部 | C92: 不明 | D92: =IFERROR(__xludf.DUMMYFUNCTION("XLOOKUP(JOIN(""/"",$A92:$B92),'source merged_div_data'!$A:$A,'source merged_div_data'!B:B)"),4363.0) -> 4363 | E92: =IFERROR(__xludf.DUMMYFUNCTION("XLOOKUP(JOIN(""/"",$A92:$B92),'source merged_div_data'!$A:$A,'source merged_div_data'!C:C)"),29376.0) -> 29376 | F92: {=IFERROR( IFS( XLOOKUP(TEXTJOIN("/", TRUE, $A92:$B92), 'source merged_div_data'!$A:$A, 'source merged_div_data'!F:F) < 1024, XLOOKUP(TEXTJOIN("/", TRUE, $A92:$B92), 'source merged_div_data'!$A:$A, 'source merged_div_data'!F:F) & " B", XLOOKUP(TEXTJOIN("/", TRUE, $A92:$B92), 'source merged_div_data'!$A:$A, 'source merged_div_data'!F:F) < 1048576, ROUND(XLOOKUP(TEXTJOIN("/", TRUE, $A92:$B92), 'source merged_div_data'!$A:$A, 'source merged_div_data'!F:F)/1024, 2) & " KB", XLOOKUP(TEXTJOIN("/", TRUE, $A92:$B92), 'source merged_div_data'!$A:$A, 'source merged_div_data'!F:F) < 1073741824, ROUND(XLOOKUP(TEXTJOIN("/", TRUE, $A92:$B92), 'source merged_div_data'!$A:$A, 'source merged_div_data'!F:F)/1048576, 2) & " MB", TRUE, ROUND(XLOOKUP(TEXTJOIN("/", TRUE, $A92:$B92), 'source merged_div_data'!$A:$A, 'source merged_div_data'!F:F)/1073741824, 2) & " GB" ), "×" )} -> 60.25 GB | G92: 2020/04/02 | H92: AWS S3 | J92: 開発本部 / デザイン本部 / 各事業部 | L92: × | M92: × | N92: 廃止/再編 | O92: 開発本部 / デザイン本部 / 各事業部 | P92: =IFERROR(__xludf.DUMMYFUNCTION("XLOOKUP(JOIN(""/"",$A92:$B92),'source isilon_divまとめ'!$A:$A,'source isilon_divまとめ'!$D:$D,XLOOKUP(JOIN(""\"",$A92:$B92),'source NetApp-file-sv01-div'!A:A,TEXT('source NetApp-file-sv01-div'!C:C,""yyyy/mm/dd"")))"),"2020/04/02") -> 2020/04/02
A93: エックスフラッグスタジオ本部 | B93: 海外運用部 | C93: 不明 | D93: =IFERROR(__xludf.DUMMYFUNCTION("XLOOKUP(JOIN(""/"",$A93:$B93),'source merged_div_data'!$A:$A,'source merged_div_data'!B:B)"),43.0) -> 43 | E93: =IFERROR(__xludf.DUMMYFUNCTION("XLOOKUP(JOIN(""/"",$A93:$B93),'source merged_div_data'!$A:$A,'source merged_div_data'!C:C)"),2.0) -> 2 | F93: {=IFERROR( IFS( XLOOKUP(TEXTJOIN("/", TRUE, $A93:$B93), 'source merged_div_data'!$A:$A, 'source merged_div_data'!F:F) < 1024, XLOOKUP(TEXTJOIN("/", TRUE, $A93:$B93), 'source merged_div_data'!$A:$A, 'source merged_div_data'!F:F) & " B", XLOOKUP(TEXTJOIN("/", TRUE, $A93:$B93), 'source merged_div_data'!$A:$A, 'source merged_div_data'!F:F) < 1048576, ROUND(XLOOKUP(TEXTJOIN("/", TRUE, $A93:$B93), 'source merged_div_data'!$A:$A, 'source merged_div_data'!F:F)/1024, 2) & " KB", XLOOKUP(TEXTJOIN("/", TRUE, $A93:$B93), 'source merged_div_data'!$A:$A, 'source merged_div_data'!F:F) < 1073741824, ROUND(XLOOKUP(TEXTJOIN("/", TRUE, $A93:$B93), 'source merged_div_data'!$A:$A, 'source merged_div_data'!F:F)/1048576, 2) & " MB", TRUE, ROUND(XLOOKUP(TEXTJOIN("/", TRUE, $A93:$B93), 'source merged_div_data'!$A:$A, 'source merged_div_data'!F:F)/1073741824, 2) & " GB" ), "×" )} -> 4.76 GB | G93: 2017/10/24 | H93: AWS S3 | J93: 開発本部 / デザイン本部 / 各事業部 | L93: × | M93: × | N93: 廃止/再編 | O93: 開発本部 / デザイン本部 / 各事業部 | P93: =IFERROR(__xludf.DUMMYFUNCTION("XLOOKUP(JOIN(""/"",$A93:$B93),'source isilon_divまとめ'!$A:$A,'source isilon_divまとめ'!$D:$D,XLOOKUP(JOIN(""\"",$A93:$B93),'source NetApp-file-sv01-div'!A:A,TEXT('source NetApp-file-sv01-div'!C:C,""yyyy/mm/dd"")))"),"2017/10/24") -> 2017/10/24
A94: エックスフラッグスタジオ本部 | B94: XFLAG | C94: 不明 | D94: =IFERROR(__xludf.DUMMYFUNCTION("XLOOKUP(JOIN(""/"",$A94:$B94),'source merged_div_data'!$A:$A,'source merged_div_data'!B:B)"),1.0) -> 1 | E94: =IFERROR(__xludf.DUMMYFUNCTION("XLOOKUP(JOIN(""/"",$A94:$B94),'source merged_div_data'!$A:$A,'source merged_div_data'!C:C)"),0.0) -> 0 | F94: {=IFERROR( IFS( XLOOKUP(TEXTJOIN("/", TRUE, $A94:$B94), 'source merged_div_data'!$A:$A, 'source merged_div_data'!F:F) < 1024, XLOOKUP(TEXTJOIN("/", TRUE, $A94:$B94), 'source merged_div_data'!$A:$A, 'source merged_div_data'!F:F) & " B", XLOOKUP(TEXTJOIN("/", TRUE, $A94:$B94), 'source merged_div_data'!$A:$A, 'source merged_div_data'!F:F) < 1048576, ROUND(XLOOKUP(TEXTJOIN("/", TRUE, $A94:$B94), 'source merged_div_data'!$A:$A, 'source merged_div_data'!F:F)/1024, 2) & " KB", XLOOKUP(TEXTJOIN("/", TRUE, $A94:$B94), 'source merged_div_data'!$A:$A, 'source merged_div_data'!F:F) < 1073741824, ROUND(XLOOKUP(TEXTJOIN("/", TRUE, $A94:$B94), 'source merged_div_data'!$A:$A, 'source merged_div_data'!F:F)/1048576, 2) & " MB", TRUE, ROUND(XLOOKUP(TEXTJOIN("/", TRUE, $A94:$B94), 'source merged_div_data'!$A:$A, 'source merged_div_data'!F:F)/1073741824, 2) & " GB" ), "×" )} -> 0 B | G94: × | J94: 開発本部 / デザイン本部 / 各事業部 | L94: × | M94: × | N94: 廃止/再編 | O94: 開発本部 / デザイン本部 / 各事業部 | P94: =IFERROR(__xludf.DUMMYFUNCTION("XLOOKUP(JOIN(""/"",$A94:$B94),'source isilon_divまとめ'!$A:$A,'source isilon_divまとめ'!$D:$D,XLOOKUP(JOIN(""\"",$A94:$B94),'source NetApp-file-sv01-div'!A:A,TEXT('source NetApp-file-sv01-div'!C:C,""yyyy/mm/dd"")))"),"#N/A") -> #N/A
